Workbook

Sheet PRECIOS
A1: CUBANITOS
B2: COMUNES | C2: BAÑADOS | D2: TOTAL
A3: 1 | B3: 900 | C3: 1200 | D3: =SUM(B3+C3) -> 2100
A4: 2 | B4: =+B3+900 -> 1800 | C4: =+C3+1200 -> 2400 | D4: =+B4+C4 -> 4200
A5: 3 | B5: =+B4+900 -> 2700 | C5: =+C4+1200 -> 3600 | D5: =+B5+C5 -> 6300
A6: 4 | B6: =+B5+900 -> 3600 | C6: =+C5+1200 -> 4800 | D6: =+B6+C6 -> 8400
A7: 5 | B7: =+B6+900 -> 4500 | C7: =+C6+1200 -> 6000 | D7: =+B7+C7 -> 10500
A8: 6 | B8: =+B7+900 -> 5400 | C8: =+C7+1200 -> 7200 | D8: =+B8+C8 -> 12600
A9: 7 | B9: =+B8+900 -> 6300 | C9: =+C8+1200 -> 8400 | D9: =+B9+C9 -> 14700
A10: 8 | B10: =+B9+900 -> 7200 | C10: =+C9+1200 -> 9600 | D10: =+B10+C10 -> 16800
A11: 9 | B11: =+B10+900 -> 8100 | C11: =+C10+1200 -> 10800 | D11: =+B11+C11 -> 18900
A12: 10 | B12: =+B11+900 -> 9000 | C12: =+C11+1200 -> 12000 | D12: =+B12+C12 -> 21000
A13: 11 | B13: =+B12+900 -> 9900 | C13: =+C12+1200 -> 13200 | D13: =+B13+C13 -> 23100
A14: 12 | B14: =+B13+900 -> 10800 | C14: =+C13+1200 -> 14400 | D14: =+B14+C14 -> 25200
A15: 13 | B15: =+B14+900 -> 11700 | C15: =+C14+1200 -> 15600 | D15: =+B15+C15 -> 27300
... A26: 24 | B26: =+B25+900 -> 21600 | C26: =+C25+1200 -> 28800 | D26: =+B26+C26 -> 50400

Sheet VENTAS JULIO
A1: MES:
B2: CUBANITOS | E2: METODO DE PAGO | G2: TOTAL | I2: MES JULIO
A3: DIA | B3: COMUNES | C3: BAÑADOS | D3: OTRO | E3: EFECTIVO | F3: TRANSFERENCIA | G3: VENTAS $
A4: 45854 | B4: =12+7+4 -> 23 | C4: =12+5+6+8 -> 31 | D4: 5 | E4: 25300 | F4: 37500 | G4: =E4+F4 -> 62800 | I4: Tranferencia | J4: =SUMIF(F4:F21,">0") -> 718400
A5: 45855 | B5: 15 | C5: 12 | D5: 3 | E5: 15000 | F5: 17700 | G5: =E5+F5 -> 32700 | I5: efectivo | J5: =SUMIF(E4:E21,">0") -> 871000
A6: 45856 | B6: =10+8+6+6+12 -> 42 | C6: =16+12 -> 28 | D6: 1 | E6: 46000 | F6: 21000 | G6: =E6+F6 -> 67000 | I6: TOTAL | J6: =J4+J5 -> 1589400
A7: 45857 | B7: =24+4+2+6+4+2+12+6+4+1+12+4 -> 81 | C7: =4+2+12+4+2+6+2+2+6+2+5+6+1+12+6 -> 72 | D7: 4 | E7: =4800+4400+4200+13600+4200+7000 -> 38200 | F7: =21600+14400+8400+6000+10800+12600+6900+7200+1200+25200+10800-600 -> 124500 | G7: =E7+F7 -> 162700 | I7: CONSUMO CUBANITOS
A8: 45858 | B8: =4+2+3+4+5+8+6+5+4+4+4+8+6+12+6+12+6+12+7+2 -> 120 | C8: =4+1+6+4+6+5+8+4+6+4+2+8+4+1+6+3 -> 72 | D8: 10 | E8: =9900+7200+9600+12000+9300+8400+6600+18000+5400+10800+6300+2800 -> 106300 | F8: =8400+1000+3000+9400+10500+12600+8000+13200+9100+9000+12800 -> 97000 | G8: =E8+F8 -> 203300 | I8: COMUNES | J8: BAÑADOS
A9: 45859 | B9: =3+4+1+4+6+4+8+6 -> 36 | C9: =1+6+8+2+1+6+12 -> 36 | D9: 1 | E9: =3900+7200+13200+5400+4600+7200+12600+14400 -> 68500 | F9: =3300+4800 -> 8100 | G9: =E9+F9 -> 76600 | I9: =SUM(B4:B20) -> 887 | J9: =SUM(C4:C20) -> 625
A10: 45860 | B10: =2+6+2+6+10+3+2+6+6+12+4+6+2+6 -> 73 | C10: =2+6+2+4+6+3+12+6+2+2+6 -> 51 | D10: 5 | E10: =4200+12600+6600+12600+9000+1800+5400+21800+4200+14600 -> 92800 | F10: =2400+6300+18000+7000+5400 -> 39100 | G10: =E10+F10 -> 131900
A11: 45861 | B11: =6+8+6+6+12+4+6+3+4+4 -> 59 | C11: =6+6+2+6+3+4+4 -> 31 | D11: =1+1 -> 2 | E11: =12600+7200+1000+6000+8400+8400 -> 43600 | F11: =5400+12600+11800+12600+6300+7200 -> 55900 | G11: =E11+F11 -> 99500
A12: 45862 | B12: =6+6+2 -> 14 | C12: =6+6+10+6 -> 28 | D12: 0 | E12: =5400+13700+7200 -> 26300 | F12: =7200+12600+100 -> 19900 | G12: =E12+F12 -> 46200
A13: 45863 | B13: =6+4+12+4+4+5+6+4+6+6 -> 57 | C13: =4+4+4+8 -> 20 | D13: =1+1+1 -> 3 | E13: =5400+8400+11800+3600+10300+5400+5400+5400+1000 -> 56700 | F13: =8400+14200 -> 22600 | G13: =E13+F13 -> 79300
A14: 45864 | B14: =12+2+7+2+22+11+6+3+12+2+3+8+10+4+4+6+6+6 -> 126 | C14: =3+4+8+2+4+2+1+4+4+2+6+2+4+6+6+6 -> 64 | D14: =1+1+1 -> 3 | E14: =14400+9600+9000+6600+11100+5400+2700+15600+5100+8200+8400+12600+12600+5400+7200 -> 133900 | F14: =7600+1000+1200+22000+6600+16200+6000 -> 60600 | G14: =E14+F14 -> 194500
A15: 45865 | B15: =6+3+6+6+6+3+8+4+8+12+6+6+7+3+8+6 -> 98 | C15: =6+2+6+2+3+8+4+2+12+3+6+1+9 -> 64 | D15: 1 | E15: =2700+8800+5400+6300+6000+7200+10800+5400+3600+7500+8100+5400 -> 77200 | F15: =12600+5400+1200+9600+12000+14400+12600+13500 -> 81300 | G15: =E15+F15 -> 158500
A16: 45866 | B16: =12+4+6+4+12+2 -> 40 | C16: =6+5+6 -> 17 | D16: 1 | E16: =18000+9600+10800+1700 -> 40100 | F16: =13600+3600 -> 17200 | G16: =E16+F16 -> 57300
A17: 45867 | B17: =4+6 -> 10 | C17: =8+6+5+12 -> 31 | D17: 1 | E17: =1000+3600+7200+6000+19800 -> 37600 | F17: 9600 | G17: =E17+F17 -> 47200
A18: 45868 | B18: =2+6+7+12+3+2+6 -> 38 | C18: =2+6+6+3+3 -> 20 | D18: 2 | E18: =4800+6300+10800+5400 -> 27300 | F18: =7200+12600+8300+5400 -> 33500 | G18: =E18+F18 -> 60800
A19: 45869 | B19: =6+5+6+6+6+6+3+2+8+1+6 -> 55 | C19: =5+4+4+6+5+12+6+3+2+1 -> 48 | D19: 2 | E19: =10500+6800+5400+6300+1800+5400 -> 36200 | F19: =5400+4800+12600+6000+19800+12600+2400+7200+2100 -> 72900 | G19: =E19+F19 -> 109100
A20: 45870
A21: 45871
A22: 45872
A23: 45873
A24: 45874
A25: 45875
A26: 45876
A27: 45877
A28: 45878
A29: 45879

Sheet GASTOS JULIO
A1: DETALLES GASTOS ENTREGADOS POR CONTRATISTA, FACTURAS "A"
K2: PAGOS
A3: FECHA | B3: ABONO | C3: RUBRO | D3: PROVEEDOR | E3: CANTIDAD | F3: DESCRIPCIÓN | G3: $ c/IVA+Ing.Br | H3: IVA | I3: 1/2IVA | J3: Perc.Ing.Bruto | K3: EFECTIVO | L3: TRANFERENCIA
A5: 45823 | B5: E | C5: HERRAJE | D5: FEDE VALENTE | F5: RUEDASN+ GUIAS PARA VENTA | G5: 17500 | K5: 17500
A6: 45823 | B6: E | C6: SELLADORES | D6: PROMAR | F6: FASTIC+ CINTA BURLETE | G6: 66900 | K6: 66900
A7: 45823 | B7: E | C7: IMPUESTO | D7: ARCA | F7: MONOTRIBUTO MES JUNIO | G7: 10143.98 | K7: 10143.98
A8: 45823 | B8: E | C8: PLAGAS | D8: LUGONES | F8: CONTROL DE PLGAS MES JUNIO | G8: 16000 | K8: 16000
A9: 45823 | B9: M | C9: IMPUESTO | D9: MUNICIPALIDAD | F9: TASA DE SEGURIDAD E HIGIENE + HABILITACION | G9: 31717 | K9: 31717
A10: 45823 | B10: E | C10: GARRAFA | D10: GARRAFA DON BOSCO | F10: CARGA DE GARRAFA | G10: 6600 | K10: 6600
A11: 45823 | B11: E | C11: BOLSAS | D11: MICRO ENVASES | F11: 1 00 GUANTES +200 BOLSAS N3+ 200 BOLSAS N4+ BOLSA CAMISETA | G11: 8200 | K11: 8200
A12: 45823 | B12: M | C12: ACRILICO | D12: ACRILICO | F12: ACRILICOS PARA VENTANA | G12: 124000 | K12: 124000
A13: 45823 | B13: M | C13: PLOTEO | D13: VICTOR | F13: PLOTEO CARRO | G13: 140000 | K13: 140000
A15: 45854 | B15: M | C15: CUBANITO COMUN | D15: MAXI | E15: 400 | F15: 1 CAJA X 400 CUBANITOS COMUNES ($156,00 X UNIDAD) | G15: =156*400 -> 62400
A16: 45854 | B16: M | C16: CUBANITO BAÑADO | D16: MAXI | E16: 300 | F16: 1 CAJA X 300 CUBANITOS BAÑADOS ($333,00 X UNIDAD) | G16: =333*300 -> 99900
A17: 45854 | B17: M | C17: DULCE DE LECHE | D17: MAXI | E17: 1 | F17: 1 POTE X 10KG DULCE DE LECHE LUZ AZUL | G17: 41032 | K17: =SUM(G15:G17) -> 203332
A18: 45853 | B18: M | C18: GARRAPIÑADA | D18: SEÑORA | E18: 3 | F18: 3 KG DE GARRAPIÑADA ($7.000 X KG) | G18: 21000 | K18: =+G18 -> 21000
A19: 45855 | B19: C | C19: CONTADOR | D19: JORGE | F19: PAGO INICIO ACTIVIDAD JORGE | G19: 20000 | L19: 20000
A20: 45855 | B20: C | C20: IMPUESTO | D20: MUNICIPALIDAD | F20: TASA SEGURIDAD E HIGIENE JULIO 2025 | G20: 13700 | L20: 13700
A21: 45856 | B21: C | C21: DULCE DE LECHE | D21: JULIA | E21: 1 | F21: 1 POTE X 10KG DULCE DE LECHE PIGUENSE | G21: 25000 | K21: 25000
A22: 45859 | B22: C | C22: PLAGAS | D22: LUGONES | F22: CONTROL DE PLGAS MES JULIO | G22: 16000 | K22: 16000
A23: 45859 | B23: C | C23: IMPUESTO | D23: ARCA | F23: MONOTRIBUTO MES JULIO | G23: 10143.98 | L23: 10143.98
A24: 45863 | B24: C | C24: CUBANITO COMUN | D24: MAXI | E24: 200 | F24: 1 CAJA X 200 CUBANITOS COMUNES ($156,00 X UNIDAD) | G24: =156*200 -> 31200
A25: 45863 | B25: C | C25: CUBANITO BAÑADO | D25: MAXI | E25: 400 | F25: 1 CAJA X 400 CUBANITOS BAÑADOS ($333,00 X UNIDAD) | G25: =333*400 -> 133200
A26: 45863 | B26: C | C26: DULCE DE LECHE | D26: MAXI | E26: 1 | F26: 1 POTE X 10KG DULCE DE LECHE PIGUENSE | G26: 22500 | K26: =SUM(G24:G26) -> 186900
A27: 45860 | B27: C | C27: DULCE DE LECHE | D27: JULIA | E27: 2 | F27: 2 POTE X 10KG DULCE DE LECHE PIGUENSE | G27: =2*25000 -> 50000 | K27: 50000
A28: 45862 | B28: C | C28: MOVIMIENTO | D28: CARRO | F28: TRANFERENCIA PARA GENERAR EFECTIVO | G28: 100000 | K28: -100000 | L28: 100000
A29: 45863 | B29: C | C29: GARRAPIÑADA | D29: GLORIA | E29: 5 | F29: 5 KG DE GARRAPIÑADA ($7.000 X KG) | G29: =7000*5 -> 35000 | K29: =+G29 -> 35000
A30: 45863 | B30: C | C30: CUBANITO COMUN | D30: MAXI | E30: 200 | F30: 1 CAJA X 200 CUBANITOS COMUNES ($156,00 X UNIDAD) | G30: =156*200 -> 31200
A31: 45863 | B31: C | C31: CUBANITO BAÑADO | D31: MAXI | E31: 200 | F31: 1 CAJA X 200 CUBANITOS BAÑADOS ($333,00 X UNIDAD) | G31: =333*200 -> 66600 | K31: =G30+G31 -> 97800
A32: 45866 | B32: C | C32: CUBANITO COMUN | D32: MAXI | E32: 400 | F32: 1 CAJA X 400 CUBANITOS COMUNES ($156,00 X UNIDAD) | G32: =156*400 -> 62400
A33: 45866 | B33: C | C33: DULCE DE LECHE | D33: MAXI | E33: 1 | F33: 1 POTE X 10KG DULCE DE LECHE PIGUENSE | G33: 22500 | K33: =SUM(G32:J33) -> 84900
A34: 45869 | B34: C | C34: EXTRACCION | D34: ERICA | F34: EXTRACCION MES JULIO EFECTIVO | G34: 200000 | K34: 200000 | L34: 0
A35: 45869 | B35: C | C35: EXTRACCION | D35: MATIAS | F35: EXTRACCION MES JULIO BANCARIZADA X TRANFERENCIAS | G35: 200000 | K35: 0 | L35: 200000
H37: =+(G37-J37)-(G37-J37)/1.21 -> 0
A38: INSERTAR FILAS ANTES QUE ESTA
F42: TOTAL FACTURAS | G42: =SUM(G14:G41) -> 1263776 | H42: =SUM(H14:H41) -> 0 | I42: =SUM(I14:I41) -> 0 | J42: =SUM(J14:J40) -> 0 | K42: =SUM(K15:K41) -> 819932 | L42: =SUM(L4:L40) -> 343843.98
H45: =+H42/0.105 -> 0 | I45: =+I42/0.105 -> 0

Sheet GASTOS AGOSTO
A1: DETALLES GASTOS ENTREGADOS POR CONTRATISTA, FACTURAS "A"
K2: PAGOS
A3: FECHA | B3: ABONO | C3: RUBRO | D3: PROVEEDOR | E3: CANTIDAD | F3: DESCRIPCIÓN | G3: $ c/IVA+Ing.Br | H3: IVA | I3: 1/2IVA | J3: Perc.Ing.Bruto | K3: EFECTIVO | L3: TRANFERENCIA
A4: 45870 | B4: C | C4: GARRAFA | D4: CASA DON BOSCO | F4: CARGA DE GARRAFA | G4: 6000 | K4: 6000
A5: 45873 | B5: C | C5: CUBANITO BAÑADO | D5: MAXI | E5: 200 | F5: 1 CAJA X 200 CUBANITOS BAÑADOS ($333,00 X UNIDAD) | G5: =333*200 -> 66600
A6: 45873 | B6: C | C6: DULCE DE LECHE | D6: MAXI | E6: 1 | F6: 1 POTE X 10KG DULCE DE LECHE PIGUENSE | G6: 25600 | K6: =G5+G6 -> 92200
A7: 45873 | B7: C | C7: CUBANITO COMUN | D7: MAXI | E7: 200 | F7: 1 CAJA X 200 CUBANITOS COMUNES ($156,00 X UNIDAD) | G7: =156*200 -> 31200
A8: 45873 | B8: C | C8: CUBANITO BAÑADO | D8: MAXI | E8: 200 | F8: 1 CAJA X 200 CUBANITOS BAÑADOS ($333,00 X UNIDAD) | G8: =333*200 -> 66600
A9: 45873 | B9: C | C9: DULCE DE LECHE | D9: MAXI | E9: 1 | F9: 1 POTE X 10KG DULCE DE LECHE PIGUENSE | G9: 25500 | K9: =G7+G8+G9 -> 123300
A10: 45874 | B10: C | C10: CERRAJERIA | D10: CERRAJERIA | E10: 1 | F10: LLAVE CARRO | G10: 5000 | K10: 5000
A11: 45880 | B11: C | C11: IMPUESTO | D11: ARCA | F11: MONOTRIBUTO MES AGOSTO | G11: 11677.6 | L11: =G11 -> 11677.6
A12: 45883 | B12: C | C12: CUBANITO COMUN | D12: MAXI | E12: 400 | F12: 1 CAJA X 400 CUBANITOS COMUNES ($156,00 X UNIDAD) | G12: =156*400 -> 62400
A13: 45883 | B13: C | C13: CUBANITO BAÑADO | D13: MAXI | E13: 400 | F13: 1 CAJA X 400 CUBANITOS BAÑADOS ($333,00 X UNIDAD) | G13: 133200
A14: 45883 | B14: C | C14: DULCE DE LECHE | D14: MAXI | E14: 4 | F14: 4 POTE X 10KG DULCE DE LECHE LUZ AZUL | G14: =82064+82064 -> 164128
A15: 45883 | B15: C | C15: REDONDEO | D15: MAXI | E15: 0 | F15: REDONDEO | G15: 272 | K15: =G12+G13+G14+G15 -> 360000
A16: 45883 | B16: C | C16: BOLSAS | D16: MICRO ENVASES | E16: 1000 | F16: 500 BOLSAS N3+ 500 BOLSAS N4 | G16: 23750 | K16: 23750
A17: 45883 | B17: C | C17: BOLSAS | D17: MICRO ENVASES | E17: 1 | F17: 200 GUANTES+ BOLSAS CAMISETAS | G17: 3800 | K17: 3800
A18: 45884 | B18: C | C18: EXTRACCION | D18: ERICA | F18: EXTRACCION MES AGOSTO EFECTIVO | G18: =K18+L18 -> 427000 | K18: 150000 | L18: 277000
A19: 45884 | B19: C | C19: EXTRACCION | D19: MATIAS | F19: EXTRACCION MES AGOSTO BANCARIZADA X TRANFERENCIAS | G19: =K19+L19 -> 427000 | K19: 150000 | L19: 277000
A20: 45870 | B20: C | C20: GARRAFA | D20: GARRAFAS DON BOSCO | F20: CARGA DE GARRAFA | G20: 6500 | K20: 6500
A21: 45883 | B21: C | C21: EMPLEADA | D21: EMPLEADA | E21: 1 | F21: MILI TRABAJO EL 17/08 | G21: 25000 | K21: 25000
A22: 45887 | B22: C | C22: PLAGAS | D22: LUGONES | E22: 1 | F22: CONTROL DE PLGAS MES JULIO | G22: 16000 | K22: 16000
A23: 45887 | B23: C | C23: CONTADOR | D23: JORGE | E23: 1 | F23: PAGO INICIO ACTIVIDAD JORGE | G23: 10000 | L23: 10000
A24: 45888 | B24: C | C24: BATERIA | D24: JACOB | E24: 1 | F24: COMPRA DE BATERIA | G24: 85000 | K24: 85000
A25: 45888 | B25: C | C25: GARRAPIÑADA | D25: GLORIA | E25: 5 | F25: 5 KG DE GARRAPIÑADA ($7.000 X KG) | G25: =7000*5 -> 35000 | K25: 0
A26: 45893 | B26: C | C26: EMPLEADA | D26: EMPLEADA | E26: 1 | F26: MILI TRABAJO EL 17/08 | G26: 25000 | K26: 25000
A27: 45894 | B27: C | C27: CERRAJERIA | D27: CERRAJERIA | E27: 1 | F27: LLAVE CANDADO | G27: 5000 | K27: 5000
A28: 45894 | B28: C | C28: BOLSAS | D28: PLASTICOS BLANCOS | E28: 400 | F28: BOLSAS PARA GARRAPIÑADAS | G28: 3200 | K28: 3200
A29: 45886 | B29: C | C29: CUBANITO BAÑADOS | D29: MAXI | E29: 200 | F29: 1 CAJA X 200 CUBANITOS BAÑADOS ($333,00 X UNIDAD) | G29: 66600
A30: 45892 | B30: C | C30: CUBANITO BAÑADO | D30: MAXI | E30: 400 | F30: 1 CAJA X 400 CUBANITOS BAÑADOS ($358,00 X UNIDAD) | G30: 143200
A31: 45892 | B31: C | C31: DULCE DE LECHE | D31: MAXI | E31: 2 | F31: 2 POTE X 10KG DULCE DE LECHE PIGUENSE | G31: =25000+25000 -> 50000
A32: 45892 | B32: C | C32: CUBANITO COMUN | D32: MAXI | E32: 400 | F32: 1 CAJA X 400 CUBANITOS COMUNES ($156,00 X UNIDAD) | G32: 62400 | K32: =G29+G30+G31+G32 -> 322200
A33: 45892 | B33: C | C33: DULCE DE LECHE | D33: LUZ AZUL | E33: 2 | F33: 2 POTE X 10KG DULCE DE LECHE LUZ AZUL | G33: =41032+41032 -> 82064
A34: 45898 | B34: C | C34: CUBANITO COMUN | D34: MAXI | E34: 400 | F34: 1 CAJA X 400 CUBANITOS COMUNES ($156,00 X UNIDAD) | G34: 62400 | K34: =G34 -> 62400
A35: 45898 | B35: C | C35: ARRMACO | D35: ARRUMACO | E35: 2 | F35: 2 DELANTALES NEGROS ADELANTO | G35: 12000 | K35: 0 | L35: =G35 -> 12000
A40: 45854 | B40: M | C40: CUBANITO COMUN | D40: MAXI | E40: 400 | F40: 1 CAJA X 400 CUBANITOS COMUNES ($156,00 X UNIDAD) | G40: =156*400 -> 62400
A41: 45854 | B41: M | C41: CUBANITO BAÑADO | D41: MAXI | E41: 300 | F41: 1 CAJA X 300 CUBANITOS BAÑADOS ($333,00 X UNIDAD) | G41: =333*300 -> 99900
A42: 45854 | B42: M | C42: DULCE DE LECHE | D42: MAXI | E42: 1 | F42: 1 POTE X 10KG DULCE DE LECHE LUZ AZUL | G42: 41032 | K42: 0
A43: 45853 | B43: M | C43: GARRAPIÑADA | D43: SEÑORA | E43: 3 | F43: 3 KG DE GARRAPIÑADA ($7.000 X KG) | G43: 21000 | K43: 0
A44: 45855 | B44: C | C44: CONTADOR | D44: JORGE | F44: PAGO INICIO ACTIVIDAD JORGE | G44: 20000 | L44: 0
A45: 45855 | B45: C | C45: IMPUESTO | D45: MUNICIPALIDAD | F45: TASA SEGURIDAD E HIGIENE JULIO 2025 | G45: 13700 | L45: 0
A46: 45856 | B46: C | C46: DULCE DE LECHE | D46: JULIA | E46: 1 | F46: 1 POTE X 10KG DULCE DE LECHE PIGUENSE | G46: 25000 | K46: 0
A47: 45859 | B47: C | C47: PLAGAS | D47: LUGONES | F47: CONTROL DE PLGAS MES JULIO | G47: 16000 | K47: 0
A48: 45859 | B48: C | C48: IMPUESTO | D48: ARCA | F48: MONOTRIBUTO MES JULIO | G48: 10143.98 | L48: 0
A49: 45863 | B49: C | C49: CUBANITO COMUN | D49: MAXI | E49: 200 | F49: 1 CAJA X 200 CUBANITOS COMUNES ($156,00 X UNIDAD) | G49: =156*200 -> 31200
A50: 45863 | B50: C | C50: CUBANITO BAÑADO | D50: MAXI | E50: 400 | F50: 1 CAJA X 400 CUBANITOS BAÑADOS ($333,00 X UNIDAD) | G50: =333*400 -> 133200
A51: 45863 | B51: C | C51: DULCE DE LECHE | D51: MAXI | E51: 1 | F51: 1 POTE X 10KG DULCE DE LECHE PIGUENSE | G51: 22500 | K51: 0
A52: 45860 | B52: C | C52: DULCE DE LECHE | D52: JULIA | E52: 2 | F52: 2 POTE X 10KG DULCE DE LECHE PIGUENSE | G52: =2*25000 -> 50000 | K52: 0
A53: 45862 | B53: C | C53: MOVIMIENTO | D53: CARRO | F53: TRANFERENCIA PARA GENERAR EFECTIVO | G53: 100000 | K53: 0 | L53: 0
A54: 45863 | B54: C | C54: GARRAPIÑADA | D54: GLORIA | E54: 5 | F54: 5 KG DE GARRAPIÑADA ($7.000 X KG) | G54: =7000*5 -> 35000 | K54: 0
A55: 45863 | B55: C | C55: CUBANITO COMUN | D55: MAXI | E55: 200 | F55: 1 CAJA X 200 CUBANITOS COMUNES ($156,00 X UNIDAD) | G55: =156*200 -> 31200
A56: 45863 | B56: C | C56: CUBANITO BAÑADO | D56: MAXI | E56: 200 | F56: 1 CAJA X 200 CUBANITOS BAÑADOS ($333,00 X UNIDAD) | G56: =333*200 -> 66600 | K56: 0
A57: 45866 | B57: C | C57: CUBANITO COMUN | D57: MAXI | E57: 400 | F57: 1 CAJA X 400 CUBANITOS COMUNES ($156,00 X UNIDAD) | G57: =156*400 -> 62400
A58: 45866 | B58: C | C58: DULCE DE LECHE | D58: MAXI | E58: 1 | F58: 1 POTE X 10KG DULCE DE LECHE PIGUENSE | G58: 22500 | K58: 0
A59: 45869 | B59: C | C59: EXTRACCION | D59: ERICA | F59: EXTRACCION MES JULIO EFECTIVO | G59: 0 | K59: 0 | L59: 0
A60: 45869 | B60: C | C60: EXTRACCION | D60: MATIAS | F60: EXTRACCION MES JULIO BANCARIZADA X TRANFERENCIAS | G60: 0 | K60: 0 | L60: 0
H62: =+(G62-J62)-(G62-J62)/1.21 -> 0
A63: INSERTAR FILAS ANTES QUE ESTA
F67: TOTAL FACTURAS | G67: =SUM(G39:G66) -> 863775.98 | H67: =SUM(H39:H66) -> 0 | I67: =SUM(I39:I66) -> 0 | J67: =SUM(J39:J65) -> 0 | K67: =SUM(K40:K66) -> 0 | L67: =SUM(L5:L65) -> 587677.6
H70: =+H67/0.105 -> 0 | I70: =+I67/0.105 -> 0

Sheet VENTAS AGOSTO
A1: MES:
B2: CUBANITOS | E2: METODO DE PAGO | G2: TOTAL | I2: MES AGOSTO
A3: DIA | B3: COMUNES | C3: BAÑADOS | D3: OTRO | E3: EFECTIVO | F3: TRANSFERENCIA | G3: VENTAS $
A4: 45870 | B4: =5+12+6+3 -> 26 | C4: =9+1+6+3 -> 19 | D4: =1+1 -> 2 | E4: =10800+6700+11800+12600+6300 -> 48200 | F4: 0 | G4: =E4+F4 -> 48200 | I4: Tranferencia | J4: =SUMIF(F4:F21,">0") -> 677500
A5: 45871 | B5: =6+20+2+4+6+6+2+4+6+3 -> 59 | C5: =3+6+6+6+4+4+3+4+6+4+6+5 -> 57 | D5: 2 | E5: =2000+3600+12600+7200+9000+4800+9000+9000+8400+12600 -> 78200 | F5: =18000+8400+10200+8700 -> 45300 | G5: =E5+F5 -> 123500 | I5: efectivo | J5: =SUMIF(E4:E21,">0") -> 908600
A6: 45872 | B6: =3+2+24+6+6+6+6+12+4+15+3+3+6+6+9+6+3+12 -> 132 | C6: =3+6+6+5+3+6+9+12+12+3 -> 65 | D6: =2+1+1+1 -> 5 | E6: =4400+5400+6400+1000+12600+3600+13500+5400+7200+10800 -> 70300 | F6: =6300+21600+12600+10800+8700+6300+12600+19900+19800+14800 -> 133400 | G6: =E6+F6 -> 203700 | I6: TOTAL | J6: =J4+J5 -> 1586100
A7: 45873 | B7: =6+3+6+1+3+2 -> 21 | C7: =12+3+6+3 -> 24 | D7: 1 | E7: =19800+6900+7300+1800 -> 35800 | F7: =6300+5400 -> 11700 | G7: =E7+F7 -> 47500 | I7: CONSUMO CUBANITOS
A8: 45874 | B8: =6+2+12+4 -> 24 | C8: =4+6+2+4 -> 16 | D8: 1 | E8: =4800+10800+4800+3600 -> 24000 | F8: =12600+5200 -> 17800 | G8: =E8+F8 -> 41800 | I8: COMUNES | J8: BAÑADOS
A9: 45875 | B9: =2+4+2+6+2 -> 16 | C9: =12+4+4+6+6 -> 32 | E9: =14400+1800+8400+6600+12600+1800 -> 45600 | F9: =7200 -> 7200 | G9: =E9+F9 -> 52800 | I9: =SUM(B4:B20) -> 806 | J9: =SUM(C4:C20) -> 641
A10: 45876 | B10: =6+3+3 -> 12 | C10: 3 | D10: =1+2 -> 3 | E10: 0 | F10: =8200+2700+6300+2000 -> 19200 | G10: =E10+F10 -> 19200
A11: 45877 | B11: =15+2+4+4+6+6+1+4+2 -> 44 | C11: =3+8+4+6+6+1+3+4+2 -> 37 | D11: 3 | E11: =13500+9300+8400+12600+7200+2100+3600+4200 -> 60900 | F11: =13200+8400+5400 -> 27000 | G11: =E11+F11 -> 87900
A12: 45878 | B12: =3+3+4+8+6+5+4+1+6+2+3+10+2+6+12 -> 75 | C12: =2+1+3+4+8+6+6+2+5+2+1+6+4+3+4+6+1 -> 64 | D12: =2+2 -> 4 | E12: =4400+3900+6300+8400+7200+9000+6900+9600+3300+1200+6300+9000+6600 -> 82100 | F12: =9600+9200+5400+12600+6600+5400+10800+7200+1200 -> 68000 | G12: =E12+F12 -> 150100
A13: 45879 | B13: =6+2+5+4+4+6+9+6+6+12+2+6+18+6+9+6+6+6+3+6 -> 128 | C13: =3+6+2+4+3+6+3+2+9+6+9+5+6+10+4+6+6+2+3+6+12+6+3+6+18+4 -> 150 | D13: =2+1+1+3+1+2+3 -> 13 | E13: =3600+2000+4200+4500+9400+7200+8200+3600+7800+18900+6000+6600+11700+16000+14600+12600+21600+3000 -> 161500 | F13: =12600+12600+10800+15600+12000+10800+13600+23400+7800+12600+3800+6300+4800 -> 146700 | G13: =E13+F13 -> 308200
A14: 45880 | B14: =8+6+2+3 -> 19 | C14: =1+3 -> 4 | D14: 2 | E14: =9200+5400+3000 -> 17600 | F14: =6300 -> 6300 | G14: =E14+F14 -> 23900
A15: 45881 | B15: =3+3+4 -> 10 | C15: =3+2 -> 5 | D15: 1 | E15: =6300+5400+4600 -> 16300 | G15: =E15+F15 -> 16300
A16: 45882 | B16: =4+1+2 -> 7 | C16: =4+5+2+2+2 -> 15 | D16: 1 | E16: =8400+7200+3300+5200 -> 24100 | F16: =2400 -> 2400 | G16: =E16+F16 -> 26500
A17: 45883 | B17: =3+6+5+3+4+12 -> 33 | C17: =3+6+2 -> 11 | D17: 1 | E17: =6300+4500+5100+11800 -> 27700 | F17: =12600+3600 -> 16200 | G17: =E17+F17 -> 43900
A18: 45884 | B18: =3+24+3+2 -> 32 | C18: =8+4+3+3+3+6+12 -> 39 | D18: =1+1 -> 2 | E18: =9600+7300+3600+2800+14400 -> 37700 | F18: =4800+21600+6300+7200 -> 39900 | G18: =E18+F18 -> 77600
A19: 45885 | B19: =4+4+6+6+6+6+6+8+4 -> 50 | C19: =2+6+6+4+10+1+6 -> 35 | D19: 2 | E19: =6000+5600+12600+5400+4800+5400+5000+1200 -> 46000 | F19: =12600+7000+12600+7200+3600 -> 43000 | G19: =E19+F19 -> 89000
A20: 45886 | B20: =3+6+6+3+6+4+8+12+5+6+6+4+3+8+5+3+6+4+8+2+6+4 -> 118 | C20: =1+6+12+3+6+2+4+4+6+6+1+3+4+2+5 -> 65 | D20: 7 | E20: =3900+6400+7200+6300+12600+6000+10800+12600+7200+5700+5400+4600+12000+5200+5400 -> 111300 | F20: =19800+12000+9300+14600+4600+3700+6300+9600 -> 79900 | G20: =E20+F20 -> 191200
A21: 45887 | B21: =3+3+2 -> 8 | C21: =6+3+7+1 -> 17 | E21: =2700+8400+3000+7200 -> 21300 | F21: =7200+6300 -> 13500 | G21: =E21+F21 -> 34800
A22: 45888 | B22: =3 -> 3 | C22: =8+4+2 -> 14 | D22: =2+1 -> 3 | E22: =9600+2400 -> 12000 | F22: =2000+2700+5800 -> 10500 | G22: =E22+F22 -> 22500
A23: 45889 | B23: =1+3+3+2+6+3+2 -> 20 | C23: =3+8+3+6+4+3+4 -> 31 | D23: 1 | E23: =900+6300+9600+6600+5400+6600 -> 35400 | F23: =6300+8200+6300 -> 20800 | G23: =E23+F23 -> 56200
A24: 45890 | B24: =3+12+6+6+2+12 -> 41 | C24: =6+6+1+6 -> 19 | E24: =2700+10800+12600+12600+1600+1200+10800+7200 -> 59500 | G24: =E24+F24 -> 59500
A25: 45891 | B25: =6+4+2+6+4+12+6+6 -> 46 | C25: =6+10+4+6+2+6+2+12 -> 48 | E25: =16600+8600+6000 -> 31200 | F25: =12600+12600+10800+12600+7800+14400 -> 70800 | G25: =E25+F25 -> 102000
A26: 45892 | B26: =2+6+6+3+6+4+6+1+12+2+6+2+6+3+4+1+2+8+9+2+15 -> 106 | C26: =4+6+6+3+6+4+9+6+2+3+8+4+4+3+2 -> 70 | D26: =2+1+3+1+1+1 -> 9 | E26: =6600+12600+7400+2000+7300+8400+5400+11700+18000+4800+6300+13200+1000+5700+6600+8200+11700+5200+13500 -> 155600 | F26: =5200+12600+4200+5400+5400 -> 32800 | G26: =E26+F26 -> 188400
A27: 45893 | B27: =8+6+9+3+2+4+12+12+6+6+6+1+12+8+4+4+6+5+8 -> 122 | C27: =6+3+6+2+1+8+12+6+5+4+4+12+7 -> 76 | D27: =2+2+2+1+1 -> 8 | E27: =7200+12600+11700+11900+13200+10800+12600+5400+5400+6900+10800+12000+1000+19800+7200 -> 148500 | F27: =4200+3200+25200+10400+3600+13900 -> 60500 | G27: =E27+F27 -> 209000
A28: 45894 | B28: =6+6+4 -> 16 | C28: 4 | E28: 5400 | F28: =5400+8400 -> 13800 | G28: =E28+F28 -> 19200
A29: 45895 | B29: =4+1+1+3+2+2+2+3+6 -> 24 | C29: =2+1+4+3+6+4+1+3+6+6 -> 36 | D29: =1+2 -> 3 | E29: =6000+2100+4800+7200+6600+3000+5400+9200 -> 44300 | F29: =900+6300+7300+7200 -> 21700 | G29: =E29+F29 -> 66000
A30: 45896 | B30: =6+10+1+2 -> 19 | C30: =2+3+6+4 -> 15 | E30: =5400+9000+1800+7200+4800 -> 28200 | F30: =2400+4500 -> 6900 | G30: =E30+F30 -> 35100
A31: 45897 | B31: =9+6+3 -> 18 | C31: =9+6+2+12+2 -> 31 | D31: 2 | E31: =18900+7800+2700+4400 -> 33800 | F31: =7200+14400 -> 21600 | G31: =E31+F31 -> 55400
A32: 45898 | B32: =3+6+3+2+2+6+4 -> 26 | C32: =3+4+4+4+6+2+8 -> 31 | D32: 4 | E32: =2700+10600+6600+13200 -> 33100 | F32: =5400+6300+4800+12600+2400 -> 31500 | G32: =E32+F32 -> 64600
A33: 45899 | B33: =2+6 -> 8 | C33: =2+9+4+6+12+9 -> 42 | D33: =2+2 -> 4 | E33: =2400+6600+7200+21800+10800+2000 -> 50800 | F33: =10800 -> 10800 | G33: =E33+F33 -> 61600
A34: 45900 | B34: =4+1+3+18+6 -> 32 | C34: =2+2+5 -> 9 | E34: =3300+8700+16200+5400 -> 33600 | F34: =6000 -> 6000 | G34: =E34+F34 -> 39600

Sheet GASTOS SEPTIEMBRE
A1: DETALLES GASTOS ENTREGADOS POR CONTRATISTA, FACTURAS "A"
K2: PAGOS
A3: FECHA | B3: ABONO | C3: RUBRO | D3: PROVEEDOR | E3: CANTIDAD | F3: DESCRIPCIÓN | G3: $ c/IVA+Ing.Br | H3: IVA | I3: 1/2IVA | J3: Perc.Ing.Bruto | K3: EFECTIVO | L3: TRANFERENCIA | M3: PEYA WALLET
A4: 45906 | B4: C | C4: DULCE DE LECHE | D4: LUZ AZUL | E4: 1 | F4: 1 POTE X 10KG DULCE DE LECHE LUZ AZUL | G4: 41000 | K4: 41000
A5: 45907 | B5: C | C5: CUBANITO COMUN | D5: MAXI | E5: 400 | F5: 1 CAJA X 400 CUBANITOS COMUNES ($156,00 X UNIDAD) | G5: 62400
A6: 45907 | B6: C | C6: CUBANITO BAÑADO | D6: MAXI | E6: 400 | F6: 1 CAJA X 400 CUBANITOS BAÑADOS ($358,00 X UNIDAD) | G6: 143200
A7: 45907 | B7: C | C7: DULCE DE LECHE | D7: MAXI | E7: 2 | F7: 1 POTE X 10KG DULCE DE LECHE PIGUENSE | G7: 51000 | K7: =SUM(G5:G7) -> 256600
A8: 45910 | B8: C | C8: VESTIMENTA | D8: ARRUMACO | E8: 1 | F8: 2 DELANTALES + 2 COFIA | G8: =12000+10000 -> 22000 | K8: =G8 -> 22000
A9: 45911 | B9: C | C9: IMPUESTO | D9: MUNICIPALIDAD | E9: 1 | F9: TASA SEGURIDAD E HIGIENE SEPTIEMBRE 2025 | G9: 14384 | L9: =G9 -> 14384
A10: 45911 | B10: C | C10: IMPUESTO | D10: ARCA | E10: 1 | F10: MONOTRIBUTO MES SEPTIEMBRE | G10: 11677.6 | L10: =G10 -> 11677.6
A11: 45912 | B11: C | C11: DULCE DE LECHE | D11: JULIA | E11: 2 | F11: 1 POTE X 10KG DULCE DE LECHE PIGUENSE | G11: 51000 | K11: =SUM(G11) -> 51000
A12: 45907 | B12: C | C12: CUBANITO COMUN | D12: MAXI | E12: 400 | F12: 1 CAJA X 400 CUBANITOS COMUNES ($156,00 X UNIDAD) | G12: 62400
A13: 45907 | B13: C | C13: CUBANITO BAÑADO | D13: MAXI | E13: 400 | F13: 1 CAJA X 400 CUBANITOS BAÑADOS ($358,00 X UNIDAD) | G13: 143200
A14: 45907 | B14: C | C14: CUBANITO BAÑADO | D14: MAXI | E14: 400 | F14: 1 CAJA X 400 CUBANITOS BAÑADOS BLANCOS ($358,00 X UNIDAD) | G14: 143200 | K14: =G12+G13+G14 -> 348800
A15: 45913 | B15: C | C15: GARRAPIÑADA | D15: CHICA | E15: 5 | F15: 35KG DE GARRAPIÑADA ($10.000 X KG) | G15: =10000*5 -> 50000 | K15: 0 | L15: =G15 -> 50000
A16: 45915 | B16: C | C16: REPUESTOS | D16: NITRAM | E16: 1 | F16: REPUESTOS PARA HACER PUNTERA DE CUBANERA | G16: 12750 | K16: 0 | L16: =G16 -> 12750
A17: 45916 | B17: C | C17: DULCE DE LECHE | D17: LUZ AZUL | E17: 2 | F17: 2 POTE X 10KG DULCE DE LECHE LUZ AZUL (42261.50) | G17: 84523 | K17: =G17 -> 84523
A18: 45916 | B18: C | C18: DULCE DE LECHE | D18: LUZ AZUL | E18: 4 | F18: 4 POTE X 10KG DULCE DE LECHE LUZ AZUL (42261.50) | G18: 169046 | L18: =G18 -> 169046
A19: 45916 | B19: C | C19: DULCE DE LECHE | D19: JULIA | E19: 6 | F19: 6 POTE X 10KG DULCE DE LECHE PIGUENSE ($25.000) | G19: =25000*6 -> 150000 | K19: =SUM(G19) -> 150000
A20: 45916 | B20: C | C20: REPUESTOS | D20: ALFA RODAMIENTO | E20: 1 | F20: REPUESTOS ORRIN PARA CUBANERA | G20: 1500 | K20: =G20 -> 1500
A21: 45917 | B21: C | C21: BOLSAS | D21: PAPELERA SAN LUIS | E21: 600 | F21: 500 BOLSAS N3L+ 100 BOLSAS N4 | G21: 13800 | L21: 13800
A22: 45918 | B22: C | C22: CONTADOR | D22: JORGE | E22: 1 | F22: PAGO MENSUAL JORGE | G22: 10000 | L22: =G22 -> 10000
A23: 45918 | B23: C | C23: GARRAPIÑADA | D23: GLORIA | E23: 10 | F23: 10 KG DE GARRAPIÑADA ($8.000 X KG) | G23: =8000*10 -> 80000 | K23: =G23 -> 80000
A24: 45919 | B24: C | C24: CUBANITO COMUN | D24: MAXI | E24: 600 | F24: 1 CAJA X 400 CUBANITOS COMUNES ($156,00 X UNIDAD) | G24: =62400+31200 -> 93600
A25: 45919 | B25: C | C25: CUBANITO BAÑADO | D25: MAXI | E25: 400 | F25: 1 CAJA X 400 CUBANITOS BAÑADOS ($358,00 X UNIDAD) | G25: 143200 | L25: =G24+G25 -> 236800
A26: 45918 | B26: C | C26: DULCE DE LECHE | D26: LUZ AZUL | E26: 3 | F26: 3 POTE X 10KG DULCE DE LECHE LUZ AZUL (42261.50) | G26: =42261.5*3 -> 126784.5 | K26: =G26 -> 126784.5 | L26: 0
A27: 45919 | B27: C | C27: PEDIDO YA | D27: PEDIDO YA | E27: 1 | F27: GASTOS DE COMICION 1-9 AL 7-9 | G27: =8925.94+415.87+2079.59 -> 11421.4 | K27: 0 | M27: =G27 -> 11421.4
A28: 45922 | B28: C | C28: PLAGAS | D28: LUGONES | F28: CONTROL DE PLGAS MES septiembre | G28: 16000 | L28: =G28 -> 16000
A29: 45922 | B29: C | C29: GARRAFA | D29: GARRAFAS DON BOSCO | F29: CARGA DE GARRAFA | G29: 7000 | K29: 7000
A30: 45924 | B30: C | C30: DULCE DE LECHE | D30: JULIA | E30: 4 | F30: 4 POTE X 10KG DULCE DE LECHE PIGUENSE ($25.000) | G30: =25000*4 -> 100000 | K30: =SUM(G30) -> 100000
A31: 45926 | B31: C | C31: CUBANITO COMUN | D31: MAXI | E31: 1200 | F31: 3 CAJA X 400 CUBANITOS COMUNES ($156,00 X UNIDAD) | G31: =62400*3 -> 187200
A32: 45926 | B32: C | C32: CUBANITO BAÑADO | D32: MAXI | E32: 2000 | F32: 5 CAJA X 400 CUBANITOS BAÑADOS ($358,00 X UNIDAD) | G32: =143200*5 -> 716000 | K32: =G31+G32-25000-62400 -> 815800
A33: 45929 | B33: C | C33: EMPLEADA | D33: EMPLEADA | E33: 2 | F33: MILI TRABAJO EL 27/09+28/09 | G33: =30000*2 -> 60000 | K33: =G33 -> 60000
A34: 45930 | B34: C | C34: PEDIDO YA | D34: PEDIDO YA | E34: 1 | F34: GASTOS DE COMICION 9-9 AL 14-9 | G34: =27287.49+4544.8+9231.36 -> 41063.65 | K34: 0 | M34: =G34 -> 41063.65
A35: 45930 | B35: C | C35: EXTRACCION | D35: ERICA | F35: EXTRACCION MES SEPTIEMBRE EFECTIVO | G35: 1300000 | K35: 800000 | L35: 500000
A36: 45930 | B36: C | C36: EXTRACCION | D36: MATIAS | F36: EXTRACCION MES SEPTIEMBRE BANCARIZADA X TRANFERENCIAS | G36: 1300000 | K36: 400000 | L36: 900000
B37: C
B38: C
B39: C
B40: C
B41: C
B42: C
B43: C
B44: C
B45: C
B46: C
B47: C
B48: C
... B67: C
A72: 45854 | B72: M | C72: CUBANITO COMUN | D72: MAXI | E72: 400 | F72: 1 CAJA X 400 CUBANITOS COMUNES ($156,00 X UNIDAD) | G72: =156*400 -> 62400
A73: 45854 | B73: M | C73: CUBANITO BAÑADO | D73: MAXI | E73: 300 | F73: 1 CAJA X 300 CUBANITOS BAÑADOS ($333,00 X UNIDAD) | G73: =333*300 -> 99900
A74: 45854 | B74: M | C74: DULCE DE LECHE | D74: MAXI | E74: 1 | F74: 1 POTE X 10KG DULCE DE LECHE LUZ AZUL | G74: 41032 | K74: 0
A75: 45853 | B75: M | C75: GARRAPIÑADA | D75: SEÑORA | E75: 3 | F75: 3 KG DE GARRAPIÑADA ($7.000 X KG) | G75: 21000 | K75: 0
A76: 45855 | B76: C | C76: CONTADOR | D76: JORGE | F76: PAGO INICIO ACTIVIDAD JORGE | G76: 20000 | L76: 0
A77: 45855 | B77: C | C77: IMPUESTO | D77: MUNICIPALIDAD | F77: TASA SEGURIDAD E HIGIENE JULIO 2025 | G77: 13700 | L77: 0
A78: 45856 | B78: C | C78: DULCE DE LECHE | D78: JULIA | E78: 1 | F78: 1 POTE X 10KG DULCE DE LECHE PIGUENSE | G78: 25000 | K78: 0
A79: 45859 | B79: C | C79: PLAGAS | D79: LUGONES | F79: CONTROL DE PLGAS MES JULIO | G79: 16000 | K79: 0
A80: 45859 | B80: C | C80: IMPUESTO | D80: ARCA | F80: MONOTRIBUTO MES JULIO | G80: 10143.98 | L80: 0
A81: 45863 | B81: C | C81: CUBANITO COMUN | D81: MAXI | E81: 200 | F81: 1 CAJA X 200 CUBANITOS COMUNES ($156,00 X UNIDAD) | G81: =156*200 -> 31200
A82: 45863 | B82: C | C82: CUBANITO BAÑADO | D82: MAXI | E82: 400 | F82: 1 CAJA X 400 CUBANITOS BAÑADOS ($333,00 X UNIDAD) | G82: =333*400 -> 133200
A83: 45863 | B83: C | C83: DULCE DE LECHE | D83: MAXI | E83: 1 | F83: 1 POTE X 10KG DULCE DE LECHE PIGUENSE | G83: 22500 | K83: 0
A84: 45860 | B84: C | C84: DULCE DE LECHE | D84: JULIA | E84: 2 | F84: 2 POTE X 10KG DULCE DE LECHE PIGUENSE | G84: =2*25000 -> 50000 | K84: 0
A85: 45862 | B85: C | C85: MOVIMIENTO | D85: CARRO | F85: TRANFERENCIA PARA GENERAR EFECTIVO | G85: 100000 | K85: 0 | L85: 0
A86: 45863 | B86: C | C86: GARRAPIÑADA | D86: GLORIA | E86: 5 | F86: 5 KG DE GARRAPIÑADA ($7.000 X KG) | G86: =7000*5 -> 35000 | K86: 0
A87: 45863 | B87: C | C87: CUBANITO COMUN | D87: MAXI | E87: 200 | F87: 1 CAJA X 200 CUBANITOS COMUNES ($156,00 X UNIDAD) | G87: =156*200 -> 31200
A88: 45863 | B88: C | C88: CUBANITO BAÑADO | D88: MAXI | E88: 200 | F88: 1 CAJA X 200 CUBANITOS BAÑADOS ($333,00 X UNIDAD) | G88: =333*200 -> 66600 | K88: 0
A89: 45866 | B89: C | C89: CUBANITO COMUN | D89: MAXI | E89: 400 | F89: 1 CAJA X 400 CUBANITOS COMUNES ($156,00 X UNIDAD) | G89: =156*400 -> 62400
A90: 45866 | B90: C | C90: DULCE DE LECHE | D90: MAXI | E90: 1 | F90: 1 POTE X 10KG DULCE DE LECHE PIGUENSE | G90: 22500 | K90: 0
A91: 45869 | B91: C | C91: EXTRACCION | D91: ERICA | F91: EXTRACCION MES JULIO EFECTIVO | G91: 0 | K91: 0 | L91: 0
A92: 45869 | B92: C | C92: EXTRACCION | D92: MATIAS | F92: EXTRACCION MES JULIO BANCARIZADA X TRANFERENCIAS | G92: 0 | K92: 0 | L92: 0
H94: =+(G94-J94)-(G94-J94)/1.21 -> 0
A95: INSERTAR FILAS ANTES QUE ESTA
F99: TOTAL FACTURAS | G99: =SUM(G71:G98) -> 863775.98 | H99: =SUM(H71:H98) -> 0 | I99: =SUM(I71:I98) -> 0 | J99: =SUM(J71:J97) -> 0 | K99: =SUM(K72:K98) -> 0 | L99: =SUM(L37:L97) -> 0
H102: =+H99/0.105 -> 0 | I102: =+I99/0.105 -> 0

Sheet VENTAS SEPTIEMBRE
A1: MES:
B2: CUBANITOS | E2: METODO DE PAGO | H2: TOTAL | J2: MES SEPTIEMBRE
A3: DIA | B3: COMUNES | C3: BAÑADOS | D3: OTRO | E3: EFECTIVO | F3: TRANSFERENCIA | G3: PEDIDOS YA | H3: VENTAS $
A4: 45901 | B4: =2+4+6+2 -> 14 | C4: =4+2+2 -> 8 | E4: =1800+4200 -> 6000 | F4: =8400+7800 -> 16200 | H4: =E4+F4 -> 22200 | J4: Tranferencia | K4: =SUMIF(F4:F31,">0") -> 1878100
A5: 45902 | B5: =2+12+6 -> 20 | C5: =6+6 -> 12 | E5: =2700+10800+7200 -> 20700 | F5: =12600 -> 12600 | H5: =E5+F5 -> 33300 | J5: efectivo | K5: =SUMIF(E4:E31,">0") -> 3134830
A6: 45903 | B6: =6+6+4+6+2+4+6 -> 34 | C6: =2+3+4+4 -> 13 | D6: 4 | E6: =5400+5400+3600+2000+6800 -> 23200 | F6: =7800+5400+8400+5400 -> 27000 | H6: =E6+F6 -> 50200 | J6: PedidosYA | K6: =SUMIF(G4:G34,">0") -> 364950
A7: 45904 | B7: =2+2+5 -> 9 | C7: =4+4+2+5+8 -> 23 | D7: 1 | E7: =6600+4800+5200+10500+9600 -> 36700 | H7: =E7+F7 -> 36700 | J7: TOTAL | K7: =K4+K5+K6 -> 5377880
A8: 45905 | B8: =10+6+4+6+6+8+6+6+2+1+12 -> 67 | C8: =12+2+3+8+2+6+2+10+6+5+9+2 -> 67 | D8: 3 | E8: =11400+3600+5400+15200+12600+5400+5400+1000+10800+4200 -> 75000 | F8: =14400+7800+9600+12000+900+18000 -> 62700 | G8: =10030+6800 -> 16830 | H8: =E8+F8 -> 137700
A9: 45906 | B9: =6+2+12+4+1+1+6+6+10+4+12+2+1 -> 67 | C9: =6+6+4+4+3+6+4+4+6+4+12+2+1 -> 62 | D9: =2+2 -> 4 | E9: =6600+8400+4500+5400+4800+14600+9000+8400+10800+2100 -> 74600 | F9: =7200+10800+7200+5700+14400+4200 -> 49500 | G9: =16740 -> 16740 | H9: =E9+F9 -> 124100 | J9: CONSUMO CUBANITOS
A10: 45907 | B10: =3+4+3+8+4+3+18+3+6+3+6+12+3+4+12+12+6+6+6+4 -> 126 | C10: =3+5+3+2+6+6+6+6+8+6+6+6+6+12+12+6+5+4+4+6+4+6+8+6 -> 142 | D10: =3+1 -> 4 | E10: =7200+16200+7200+12600+12300+14580+10800+9900+7200+3000+14400+3600+5940+7200+5200+4800+4800+1000+4800+13200 -> 165920 | F10: =6300+6300+6000+9900+9900+7200+10800+25200+6000+12600+7200 -> 107400 | G10: =11160+8640 -> 19800 | H10: =E10+F10+G10 -> 293120 | J10: COMUNES | K10: BAÑADOS
A11: 45908 | B11: =8+6+12+1+1+2 -> 30 | C11: =6+12+3+1+6+2 -> 30 | E11: =7200+7200+10000+3600+8000+4200 -> 40200 | F11: =19800+800+2100 -> 22700 | H11: =E11+F11+G11 -> 62900 | J11: =SUM(B4:B33) -> 2438 | K11: =SUM(C4:C33) -> 2579
A12: 45909 | B12: =12+2+6+2+2 -> 24 | C12: =6+6+3+2 -> 17 | D12: 1 | E12: =1000+7200+5400+5400+4200+1800 -> 25000 | F12: 7200 | G12: 11880 | H12: =E12+F12+G12 -> 44080
A13: 45910 | B13: =6+6+4+6+4+9+4+3+12 -> 54 | C13: =2+2+4+4+3 -> 15 | E13: =2400+5400+8100+3600+7300 -> 26800 | F13: =7800+8400+3600+10800 -> 30600 | G13: =11700 -> 11700 | H13: =E13+F13+G13 -> 69100
A14: 45911 | B14: =6+4+12+4+4+6+4+4+1+6 -> 51 | C14: =6+12+4+2+2+1+6 -> 33 | D14: 1 | E14: =1000+10800+8400+3600+2400+3600+2100+7200 -> 39100 | F14: =5400+5400+6000+5400 -> 22200 | G14: =29160 -> 29160 | H14: =E14+F14+G14 -> 90460
A15: 45912 | B15: =4+10+6+4+5+3+2 -> 34 | C15: =6+4+5+3+6+1 -> 25 | D15: =2+4 -> 6 | E15: =14600+8400+6300+11200 -> 40500 | F15: =3600+9000+10500+3000 -> 26100 | H15: =E15+F15+G15 -> 66600
A16: 45913 | B16: =12+3+6+2+12+1+4+6+3+6+6+1+8+3 -> 73 | C16: =3+4+6+1+8+6+4+5+3+12+6+3+12+8+3 -> 84 | D16: =1+2 -> 3 | E16: =10800+6400+6600+2000+12500+4800+6000+6300+19800+5400+4500+7200+6300 -> 98600 | F16: =18000+2100+13200+14400+9600 -> 57300 | G16: =7290+8640 -> 15930 | H16: =E16+F16+G16 -> 171830
A17: 45914 | B17: =6+4+6+2+4+6+2+6+3+4+3+8+6+4+8+4+6+6+24+12+6+2+2+18+6+6+6+3+6+4+12+4 -> 199 | C17: =4+4+7+3+2+12+4+2+5+12+12+8+12+4+8+6+6+6+6+4+2+4+12+3+6+12+4 -> 170 | D17: 5 | E17: =5400+5400+10200+4400+6000+14400+17100+3600+12000+13200+7200+12600+23760+7200+7400+4200+5400+5400+14580+3600+23220+2620 -> 208880 | F17: =8400+4800+7200+6600+7800+13200+2700+8200+10800+6600+4800+16200+19800+6300 -> 123400 | G17: =23220+23220+14580+10800 -> 71820 | H17: =E17+F17+G17 -> 404100
A18: 45915 | B18: =12+5+2 -> 19 | C18: =2+4+1 -> 7 | D18: 1 | E18: =10800+4500+8820+1200 -> 25320 | F18: =2400 -> 2400 | H18: =E18+F18+G18 -> 27720
A19: 45916 | B19: =1+6+12+2+6 -> 27 | C19: =2+12+2+4+1 -> 21 | D19: 2 | E19: =2000+3300+2400+5400+10800+3900 -> 27800 | F19: =14400+6600 -> 21000 | H19: =E19+F19+G19 -> 48800
A20: 45917 | B20: =6+4+6+5 -> 21 | C20: =6+4+8+6+5 -> 29 | E20: =12600+4800+13200 -> 30600 | F20: 10500 | G20: 14580 | H20: =E20+F20+G20 -> 55680
A21: 45918 | B21: =3+4+2+6 -> 15 | C21: =6+2+2 -> 10 | E21: =7200+3600+4200+5400 -> 20400 | F21: =5100 -> 5100 | H21: =E21+F21+G21 -> 25500
A22: 45919 | B22: =3+3+4+12+5+2+3+12 -> 44 | C22: =6+2+1+4+10+5 -> 28 | D22: 2 | E22: =2700+9900+6000+10800+5700+8600+12000+8700 -> 64400 | F22: =0 -> 0 | G22: =11880 -> 11880 | H22: =E22+F22+G22 -> 76280
A23: 45920 | B23: =9+12+8+12 -> 41 | C23: =9+6+4+6+18 -> 43 | D23: 1 | E23: =11000+8200+12000+7200 -> 38400 | F23: =10800 -> 10800 | G23: =21870+25920 -> 47790 | H23: =E23+F23+G23 -> 96990
A24: 45921 | B24: =4+10+6+2+4+6+1+9+7+12+1+6+6+8 -> 82 | C24: =8+8+4+2+6+6+3+6+6+7+5+6+6+3+6+6 -> 88 | E24: =2400+12500+4500+15300+6900+11000+12600+3600+7200+7200 -> 83200 | F24: =18600+7200+6900+7200 -> 39900 | G24: =15480+5940+7740+12600+8640+8640+14580 -> 73620 | H24: =E24+F24+G24 -> 196720
A25: 45922 | B25: 3 | C25: 6 | E25: 2700 | G25: 8640 | H25: =E25+F25+G25 -> 11340
A26: 45923 | B26: =3+2+6+2+6+3 -> 22 | C26: =3+6+2+2+6+3 -> 22 | D26: =2+1+1+2 -> 6 | E26: =9000+3400+14600+6300 -> 33300 | F26: =6300+7400+5200 -> 18900 | H26: =E26+F26+G26 -> 52200
A27: 45924 | B27: =12+12+6+4+3 -> 37 | C27: =4+2+3+4+3 -> 16 | E27: =10800+4800+10800+7800+3600 -> 37800 | F27: =3600+4800+6300 -> 14700 | H27: =E27+F27+G27 -> 52500
A28: 45925 | B28: =4+6+2+3+12+6+3+4+3+4+2 -> 49 | C28: =6+1+2+4+3+6+1+6+12+4+6+4 -> 55 | E28: =1200+6000+5400+6300+10800+12600+3900+14400+8400+7200+2700+6600+3000 -> 88500 | F28: =7200+6600+7200+3600 -> 24600 | H28: =E28+F28+G28 -> 113100
A29: 45926 | H29: =E29+F29+G29 -> 0
A30: 45927 | B30: =2+4+12+1+3+6+3+3+4+1+5+2+6+8+12+5+3+3+4+1+6+6+6+2+3+2+6+2+2+3+2+6+6+2+4+9+5+4+3+2+2+4+3+4+8+6+5+8+6+2+1+5+12+2+3+6+2+6+2+2+2+1+6+24+2+3+2+2+2+2+3+12+3+3+2+6+3+8+12+6+12+2+12+4+2+2+3+2+2+1+1+4+2+4+6+3+1+3+4+3+6+3+4+3+6+6+1+4+6+3+3+3+6+7+3+2+3+2+4+3+2+8+4+10+6+2+2+2 -> 549 | C30: =3+6+2+3+4+3+1+8+2+5+1+2+4+5+6+8+2+2+3+2+6+6+4+3+2+6+1+1+3+4+3+3+6+6+8+9+4+4+3+4+3+3+4+1+16+2+4+4+2+12+2+3+3+6+4+2+2+4+4+4+2+1+4+2+3+6+2+2+3+3+6+4+4+3+12+2+4+6+2+2+4+4+2+2+2+4+2+4+6+6+1+4+6+2+6+6+6+2+6+3+3+2+3+1+8+3+1+4+12+4+4+6+6+3+1+8+3+5+3+3+5+3+3+2+2+6+2+6+4+12+5+3 -> 530 | D30: =1+1+3+1+1+1+1+1+2+1 -> 13 | E30: =1800+3600+1800+1200+7200+3300+6300+7200+7500+6300+1200+3300+1200+4200+6000+12600+7200+9600+2400+14400+3600+6600+6600+4200+12600+3000+3000+6300+6600+3600+5400+3600+1800+7200+16200+4400+3600+6300+7200+5700+26400+2400+3000+6600+6900+14400+10800+6400+6600+4800+4800+5400+21600+4200+6300+1800+9000+6300+9900+10200+6300+15600+9000+2400+8400+4200+1200+6600+4200+5200+2100+3600+8400+7200+3600+7200+5400+6300+1200+6200+6000+8400+6300+1200+4800+19800+5700+8400+7200+12600+7500+6300+6300+6000+6300+4200+6000+9900+7200+14400+3600+5400+6000+1800+12000 -> 691200 | F30: =5700+13200+10500+4800+4500+6300+900+5400+12600+12600+6300+12600+18900+9300+8400+6300+6600+8400+5400+2400+5700+2400+6300+12600+5300+2200+4200+6600+4200+2100+4800+4200+4200+6300+10800+6600+7200+25200+7800+2400+10800+4800+4200+5400+7200+7200+4800+7200+4200+7200+2400+6300+3900+14400+3900+9600+11400+6300+5400+3600+7200+4800+9000+900+5400+4200 -> 453900 | H30: =E30+F30+G30 -> 1145100
A31: 45928 | B31: =3+1+3+2+6+6+6+6+3+6+3+6+1+4+6+4+3+2+10+2+6+1+12+3+4+3+10+6+3+12+24+2+1+2+6+6+2+1+6+2+6+6+3+2+6+12+6+2+6+4+4+3+2+6+12+4+6+6+3+3+2+3+6+9+6+5+4+4+1+1+2+6+7+6+1+2+8+4+4+2+4+6+6+6+6+4+12+6+6+2+6+12+6+1+6+1+2+1+12+12+3+3+2+4+4+6+3+4+6+2+6+4+6+3+4+4+6+12+2+2+6+3+3+4+6+4+2+4+2+6+3+12+4+6+6+6+3+3+4+1+6+5+3+2+6+3+3+5+4+6 -> 714 | C31: =2+1+4+8+12+4+2+5+8+6+1+2+1+2+2+6+1+5+2+8+9+2+12+6+6+4+8+6+6+4+6+6+4+6+4+6+1+6+3+5+3+4+4+4+6+3+2+12+5+2+6+6+6+3+7+4+1+6+2+6+3+2+6+6+3+6+3+10+2+6+6+4+1+2+5+2+4+2+12+6+6+8+6+6+2+6+3+6+6+16+4+4+1+2+1+3+2+6+6+6+1+6+2+2+18+8+3+4+2+9+4+4+10+6+6+12+3+8+6+10+6+2+6+4+9+2+6+8+4+2+6+10+12+12+12+36+3+5+2+3+12+6+1+4+2+2+5+6+10+14+3+6+6+3+6+6+2+7+6+6+12+12+9+9+9+6+2+12+12+6+3+9+4+12+12 -> 991 | D31: =3+3+1+3+1 -> 11 | E31: =1200+2400+2000+1800+5400+5400+2400+15600+12600+2700+7200+2700+1200+9000+3300+28000+13200+6300+4800+4800+4800+900+7200+6300+10800+9600+12600+13800+7200+2400+12600+8400+3600+13500+4200+12600+10800+6000+12000+14400+14300+14400+12600+6300+4200+12600+8700+8400+3300+9600+2700+18000+5000+7200+5500+8400+12600+16200+1700+7200+2000+19800+5400+14400+7200+3600+13500+6600+8400+5400+7200+7200+4200+6000+6300+11100+8400+2100+7800+6000+4200+7200+12600+6300+7200+16500+12600+4800+2000+4200+10800+2700+1800+8400+5400+2700+4500+1800+12600+7200+6000+6300+3600+3600+7200+12000+21000+6600+5400+3300+4200+5400+6900+4200+7200+13200+6000+14400+7200+7200+12600+12600+5400+4800+3600+7200+4800+5400+12600+3600+2400+1200+4800+9600+4800+2400+6000+9600+7200+10800+5400+1200+2400+2100+33710+10200 -> 1110010 | F31: =2700+4800+6300+5400+5300+6000+4200+19800+13800+12600+25200+7200+21000+16800+5400+6300+21600+5400+2600+4200+12600+14400+10800+10000+16200+19800+14400+7200+4800+12600+8700+6300+19800+8000+6000+8700+6300+8400+6600+19800+8700+10800+12600+12600+13800+7200+5700+6300+6300+6000+12600+6900+10800+5400+6600+14400+7200+7200+13200+15600+12600+14400+12600+7500+10800+6600+5400+7200+10800+3000+12600 -> 711400 | H31: =E31+F31+G31 -> 1821410
A32: 45929 | H32: =E32+F32+G32 -> 0
A33: 45930 | B33: =3+6+1+3 -> 13 | C33: =4+4+6+2+6+5+3+2 -> 32 | E33: =4800+7200+5000+6300+2400 -> 25700 | F33: =4800+6900 -> 11700 | G33: =14580 -> 14580 | H33: =E33+F33+G33 -> 51980
H34: =E34+F34+G34 -> 0

Sheet GASTOS OCTUBRE
A1: DETALLES GASTOS ENTREGADOS POR CONTRATISTA, FACTURAS "A"
K2: PAGOS
A3: FECHA | B3: ABONO | C3: RUBRO | D3: PROVEEDOR | E3: CANTIDAD | F3: DESCRIPCIÓN | G3: $ c/IVA+Ing.Br | H3: IVA | I3: 1/2IVA | J3: Perc.Ing.Bruto | K3: EFECTIVO | L3: TRANFERENCIA | M3: PEYA WALLET
A4: 45930 | B4: C | C4: PEDIDO YA | D4: PEDIDO YA | E4: 1 | F4: GASTOS DE COMICION 15-9 AL 21-9 | G4: =20677+4894.54+7415.75 -> 32987.29 | K4: 0 | M4: =G4 -> 32987.29
A5: 45940 | B5: C | C5: CUBANITO COMUN | D5: MAXI | E5: 600 | F5: 1 CAJA X 600 CUBANITOS COMUNES ($156,00 X UNIDAD) | G5: =62400+31200 -> 93600 | K5: =G5 -> 93600
A6: 45943 | B6: C | C6: DULCE DE LECHE | D6: JULIA | E6: 4 | F6: 4 POTE X 10KG DULCE DE LECHE PIGUENSE | G6: =25000*4 -> 100000 | K6: =SUM(G6) -> 100000
A7: 45943 | B7: C | C7: CONTADOR | D7: JORGE | E7: 1 | F7: PAGO MENSUAL JORGE | G7: 10000 | L7: =G7 -> 10000
A8: 45941 | B8: C | C8: IMPUESTO | D8: ARCA | E8: 1 | F8: MONOTRIBUTO MES OCTUBRE | G8: 11677.6 | L8: =G8 -> 11677.6
A9: 45930 | B9: C | C9: PEDIDO YA | D9: PEDIDO YA | E9: 1 | F9: GASTOS DE COMICION 22-9 AL 28-9 | G9: =1119.23+235.04 -> 1354.27 | K9: 0 | M9: =G9 -> 1354.27
A10: 45945 | B10: C | C10: EXTRACCION | D10: ERICA | F10: EXTRACCION MES SEPTIEMBRE EFECTIVO | G10: 650000 | K10: 400000 | L10: 250000
A11: 45945 | B11: C | C11: EXTRACCION | D11: MATIAS | F11: EXTRACCION MES SEPTIEMBRE BANCARIZADA X TRANFERENCIAS | G11: 650000 | K11: 350000 | L11: 300000
A12: 45947 | B12: C | C12: PEDIDO YA | D12: PEDIDO YA | E12: 1 | F12: GASTOS DE COMICION 29-9 AL 5-10 | G12: =31291.02+4829.1+7585.22+6600 -> 50305.34 | K12: 0 | M12: =G12 -> 50305.34
A13: 45951 | B13: C | C13: PLAGAS | D13: LUGONES | F13: CONTROL DE PLGAS MES OCTUBRE | G13: 16000 | L13: =G13 -> 16000
A14: 45954 | B14: C | C14: PEDIDO YA | D14: PEDIDO YA | E14: 1 | F14: GASTOS DE COMICION 6-10 AL 12-10 | G14: =54138.37+33500+17314.66+26000-5187.61 -> 125765.42 | K14: 0 | M14: =G14 -> 125765.42
A15: 45958 | B15: C | C15: CUBANITO COMUN | D15: MAXI | E15: 400 | F15: 1 CAJA X 400 CUBANITOS COMUNES ($156,00 X UNIDAD) | G15: 62400
A16: 45958 | B16: C | C16: CUBANITO BAÑADO | D16: MAXI | E16: 400 | F16: 1 CAJA X 400 CUBANITOS BAÑADOS ($358,00 X UNIDAD) | G16: 143200
A17: 45958 | B17: C | C17: CUBANITO BAÑADO | D17: MAXI | E17: 200 | F17: 1 CAJA X 400 CUBANITOS BAÑADOS ($358,00 X UNIDAD) | G17: 71100 | K17: =G15+G16+G17 -> 276700
M19: =203823-G14+5187.61 -> 83245.19
B50: C
B51: C
B52: C
B53: C
B54: C
B55: C
B56: C
B57: C
B58: C
B59: C
B60: C
B61: C
... B80: C
A85: 45854 | B85: M | C85: CUBANITO COMUN
A86: 45906 | B86: C | C86: DULCE DE LECHE | D86: LUZ AZUL | E86: 1 | F86: 1 POTE X 10KG DULCE DE LECHE LUZ AZUL | G86: 41000 | K86: 41000
A87: 45907 | B87: C | C87: CUBANITO COMUN | D87: MAXI | E87: 400 | F87: 1 CAJA X 400 CUBANITOS COMUNES ($156,00 X UNIDAD) | G87: 62400
A88: 45907 | B88: C | C88: CUBANITO BAÑADO | D88: MAXI | E88: 400 | F88: 1 CAJA X 400 CUBANITOS BAÑADOS ($358,00 X UNIDAD) | G88: 143200
A89: 45907 | B89: C | C89: DULCE DE LECHE | D89: MAXI | E89: 2 | F89: 1 POTE X 10KG DULCE DE LECHE PIGUENSE | G89: 51000 | K89: =SUM(G87:G89) -> 256600
A90: 45910 | B90: C | C90: VESTIMENTA | D90: ARRUMACO | E90: 1 | F90: 2 DELANTALES + 2 COFIA | G90: =12000+10000 -> 22000 | K90: =G90 -> 22000
A91: 45911 | B91: C | C91: IMPUESTO | D91: MUNICIPALIDAD | E91: 1 | F91: TASA SEGURIDAD E HIGIENE SEPTIEMBRE 2025 | G91: 14384 | L91: =G91 -> 14384
A92: 45911 | B92: C | C92: IMPUESTO | D92: ARCA | E92: 1 | F92: MONOTRIBUTO MES SEPTIEMBRE | G92: 11677.6 | L92: =G92 -> 11677.6
A93: 45912 | B93: C | C93: DULCE DE LECHE | D93: JULIA | E93: 2 | F93: 1 POTE X 10KG DULCE DE LECHE PIGUENSE | G93: 51000 | K93: =SUM(G93) -> 51000
A94: 45907 | B94: C | C94: CUBANITO COMUN | D94: MAXI | E94: 400 | F94: 1 CAJA X 400 CUBANITOS COMUNES ($156,00 X UNIDAD) | G94: 62400
A95: 45907 | B95: C | C95: CUBANITO BAÑADO | D95: MAXI | E95: 400 | F95: 1 CAJA X 400 CUBANITOS BAÑADOS ($358,00 X UNIDAD) | G95: 143200
A96: 45907 | B96: C | C96: CUBANITO BAÑADO | D96: MAXI | E96: 400 | F96: 1 CAJA X 400 CUBANITOS BAÑADOS BLANCOS ($358,00 X UNIDAD) | G96: 143200 | K96: =G94+G95+G96 -> 348800
A97: 45913 | B97: C | C97: GARRAPIÑADA | D97: CHICA | E97: 5 | F97: 35KG DE GARRAPIÑADA ($10.000 X KG) | G97: =10000*5 -> 50000 | K97: 0 | L97: =G97 -> 50000
A98: 45915 | B98: C | C98: REPUESTOS | D98: NITRAM | E98: 1 | F98: REPUESTOS PARA HACER PUNTERA DE CUBANERA | G98: 12750 | K98: 0 | L98: =G98 -> 12750
A99: 45916 | B99: C | C99: DULCE DE LECHE | D99: LUZ AZUL | E99: 2 | F99: 2 POTE X 10KG DULCE DE LECHE LUZ AZUL (42261.50) | G99: 84523 | K99: =G99 -> 84523
A100: 45916 | B100: C | C100: DULCE DE LECHE | D100: LUZ AZUL | E100: 4 | F100: 4 POTE X 10KG DULCE DE LECHE LUZ AZUL (42261.50) | G100: 169046 | L100: =G100 -> 169046
A101: 45916 | B101: C | C101: DULCE DE LECHE | D101: JULIA | E101: 6 | F101: 6 POTE X 10KG DULCE DE LECHE PIGUENSE ($25.000) | G101: =25000*6 -> 150000 | K101: =SUM(G101) -> 150000
A102: 45916 | B102: C | C102: REPUESTOS | D102: ALFA RODAMIENTO | E102: 1 | F102: REPUESTOS ORRIN PARA CUBANERA | G102: 1500 | K102: =G102 -> 1500
A103: 45917 | B103: C | C103: BOLSAS | D103: PAPELERA SAN LUIS | E103: 600 | F103: 500 BOLSAS N3L+ 100 BOLSAS N4 | G103: 13800 | L103: 13800
A104: 45918 | B104: C | C104: CONTADOR | D104: JORGE | E104: 1 | F104: PAGO MENSUAL JORGE | G104: 10000 | L104: =G104 -> 10000
A105: 45918 | B105: C | C105: GARRAPIÑADA | D105: GLORIA | E105: 10 | F105: 10 KG DE GARRAPIÑADA ($8.000 X KG) | G105: =8000*10 -> 80000 | K105: =G105 -> 80000
A106: 45919 | B106: C | C106: CUBANITO COMUN | D106: MAXI | E106: 600 | F106: 1 CAJA X 400 CUBANITOS COMUNES ($156,00 X UNIDAD) | G106: =62400+31200 -> 93600
A107: 45919 | B107: C | C107: CUBANITO BAÑADO | D107: MAXI | E107: 400 | F107: 1 CAJA X 400 CUBANITOS BAÑADOS ($358,00 X UNIDAD) | G107: 143200 | L107: =G106+G107 -> 236800
A108: 45918 | B108: C | C108: DULCE DE LECHE | D108: LUZ AZUL | E108: 3 | F108: 3 POTE X 10KG DULCE DE LECHE LUZ AZUL (42261.50) | G108: =42261.5*3 -> 126784.5 | K108: =G108 -> 126784.5 | L108: 0
A109: 45919 | B109: C | C109: PEDIDO YA | D109: PEDIDO YA | E109: 1 | F109: GASTOS DE COMICION 1-9 AL 7-9 | G109: =8925.94+415.87+2079.59 -> 11421.4 | K109: 0 | M109: =G109 -> 11421.4
A110: 45922 | B110: C | C110: PLAGAS | D110: LUGONES | F110: CONTROL DE PLGAS MES septiembre | G110: 16000 | L110: =G110 -> 16000
A111: 45922 | B111: C | C111: GARRAFA | D111: GARRAFAS DON BOSCO | F111: CARGA DE GARRAFA | G111: 7000 | K111: 7000
A112: 45924 | B112: C | C112: DULCE DE LECHE | D112: JULIA | E112: 4 | F112: 4 POTE X 10KG DULCE DE LECHE PIGUENSE ($25.000) | G112: =25000*4 -> 100000 | K112: =SUM(G112) -> 100000
A113: 45926 | B113: C | C113: CUBANITO COMUN | D113: MAXI | E113: 1200 | F113: 3 CAJA X 400 CUBANITOS COMUNES ($156,00 X UNIDAD) | G113: =62400*3 -> 187200
A114: 45926 | B114: C | C114: CUBANITO BAÑADO | D114: MAXI | E114: 2000 | F114: 5 CAJA X 400 CUBANITOS BAÑADOS ($358,00 X UNIDAD) | G114: =143200*5 -> 716000 | K114: =G113+G114-25000-62400 -> 815800
A115: 45929 | B115: C | C115: EMPLEADA | D115: EMPLEADA | E115: 2 | F115: MILI TRABAJO EL 27/09+28/09 | G115: =30000*2 -> 60000 | K115: =G115 -> 60000
A116: 45930 | B116: C | C116: PEDIDO YA | D116: PEDIDO YA | E116: 1 | F116: GASTOS DE COMICION 15-9 AL 21-9 | G116: =20677+4894.54+7415.75+15750 -> 48737.29 | K116: 0 | M116: =G116 -> 48737.29
A117: 45930 | B117: C | C117: EXTRACCION | D117: ERICA | F117: EXTRACCION MES SEPTIEMBRE EFECTIVO | G117: 1300000 | K117: 800000 | L117: 500000
A118: 45930 | B118: C | C118: EXTRACCION | D118: MATIAS | F118: EXTRACCION MES SEPTIEMBRE BANCARIZADA X TRANFERENCIAS | G118: 1300000 | K118: 400000 | L118: 900000
A119: 45854 | B119: M | C119: CUBANITO BAÑADO
A120: 45854 | B120: M | C120: DULCE DE LECHE
A121: 45853 | B121: M | C121: GARRAPIÑADA
A122: 45855 | B122: C | C122: CONTADOR
A123: 45855 | B123: C | C123: IMPUESTO
A124: 45856 | B124: C | C124: DULCE DE LECHE
A125: 45859 | B125: C | C125: PLAGAS
A126: 45859 | B126: C | C126: IMPUESTO
A127: 45863 | B127: C | C127: CUBANITO COMUN
A128: 45863 | B128: C | C128: CUBANITO BAÑADO
A129: 45863 | B129: C | C129: DULCE DE LECHE
A130: 45860 | B130: C | C130: DULCE DE LECHE
... A138: 45869 | B138: C | C138: EXTRACCION
A141: INSERTAR FILAS ANTES QUE ESTA
H148: =+H145/0.105 -> 0 | I148: =+I145/0.105 -> 0

Sheet VENTAS OCTUBRE
A1: MES:
B2: CUBANITOS | E2: METODO DE PAGO | H2: TOTAL | J2: MES OCTUBRE
A3: DIA | B3: COMUNES | C3: BAÑADOS | D3: OTRO | E3: EFECTIVO | F3: TRANSFERENCIA | G3: PEDIDOS YA | H3: VENTAS $
A4: 45931 | B4: =6+6+6+5+2+4+2 -> 31 | C4: =6+6+6+6+2 -> 26 | D4: =3+1+2 -> 6 | E4: =15000+7200+7200+6600+2400+5400+1800 -> 45600 | F4: =4500+9000+6000 -> 19500 | H4: =E4+F4 -> 65100 | J4: Tranferencia | K4: =SUMIF(F4:F31,">0") -> 738000
A5: 45932 | B5: =6+6+4+6+3 -> 25 | C5: =4+12+3 -> 19 | E5: =5400 -> 5400 | F5: =5400+8400+14400 -> 28200 | G5: =6600+8100 -> 14700 | H5: =E5+F5 -> 33600 | J5: efectivo | K5: =SUMIF(E4:E31,">0") -> 1388600
A6: 45933 | B6: 1 | C6: =4+6 -> 10 | E6: =5700+7200 -> 12900 | H6: =E6+F6 -> 12900 | J6: PedidosYA | K6: =SUMIF(G4:G34,">0") -> 580660
A7: 45934 | B7: =2+6+2+6+4+2+6+12+4 -> 44 | C7: =6+6+9+6+4+2+8+2+12+4 -> 59 | D7: 1 | E7: =7200+12600+4200+10800 -> 34800 | F7: =12600+6600+7800+13200+14400+8400 -> 63000 | G7: =9600+7800 -> 17400 | H7: =E7+F7 -> 97800 | J7: TOTAL | K7: =K4+K5+K6 -> 2707260
A8: 45935 | B8: =2+12+8+12+6+12+6+24+18+2+8+4+6+6+6+12+6+2+6+6+8+9+6+6+4+2 -> 199 | C8: =2+2+6+6+6+6+7+3+8+4+4+6+4+6+6+4+6+6+2+4+9+6+6+4 -> 123 | D8: =1+3+1+1 -> 6 | E8: =6600+16200+12600+21600+3600+25800+8400+9600+12600+4200+5400+10800+6600+4800 -> 148800 | F8: =7200+10800+10800+12600+12000+12600+12600+4800+12000+18900+5400+7200+5400 -> 132300 | G8: =9600+9600+11200+8600+6600+22800+6600 -> 75000 | H8: =E8+F8 -> 281100
A9: 45936 | B9: =12+2+3 -> 17 | C9: =5+3+6+9 -> 23 | D9: 3 | E9: =10800+3600+3000+7200+13500 -> 38100 | F9: =7800 -> 7800 | H9: =E9+F9 -> 45900 | J9: CONSUMO CUBANITOS
A10: 45937 | B10: =6+3+13+3+6+6+4+18 -> 59 | C10: =6+6+1+3+5+6+4+6+12 -> 49 | D10: =3+3 -> 6 | E10: =16200+6900+9900+12600+4800+5000+16200+14000 -> 85600 | F10: =7200+3600+7200 -> 18000 | G10: =12500 -> 12500 | H10: =E10+F10 -> 103600 | J10: COMUNES | K10: BAÑADOS
A11: 45938 | B11: =6+2+1+8+4 -> 21 | C11: =2+4+4 -> 10 | E11: =5400+1500+2400+900+8400 -> 18600 | G11: =15200 -> 15200 | H11: =E11+F11 -> 18600 | J11: =SUM(B4:B33) -> 1244 | K11: =SUM(C4:C33) -> 1103
A12: 45939 | B12: =8+2+1+1+8+4+6+2 -> 32 | C12: =2+6+12+3+6+6+5+2 -> 42 | D12: 3 | E12: =7200+1800+17400+4000+900+7200+7200+5400+4200 -> 55300 | F12: =2400+7200+9600 -> 19200 | G12: =9600 -> 9600 | H12: =E12+F12 -> 74500
A13: 45940 | B13: =6+4+12+12+3+12+10+12+6 -> 77 | C13: =4+9 -> 13 | D13: =1+3+1 -> 5 | E13: =4800+10800+13800+10200+5400 -> 45000 | F13: =6600+3600+10800 -> 21000 | G13: =17700+13200 -> 30900 | H13: =E13+F13 -> 66000
A14: 45941 | B14: =6+6+6+6+6+3+5 -> 38 | C14: =12+6+4+6+6+2+10+12+9+6+1 -> 74 | D14: =3+1 -> 4 | E14: =8500+4800+7200+2400+12000+19800 -> 54700 | F14: =14400+5400+5700 -> 25500 | G14: =9600+17400+6600+17700+9600 -> 60900 | H14: =E14+F14 -> 80200
A15: 45942 | B15: =6+1+6+1+4+12+3+6+6+6+2+6+3+3+6+4+1+10+1+2+4+4+4+7+6 -> 114 | C15: =2+6+7+4+6+12+3+3+6+2+2+6+3+3+5+5+2+6+4+12+7+4+8+8+8+13+6 -> 153 | D15: =1+2+3+3 -> 9 | E15: =5400+3300+7200+6300+6000+12600+9800+9000+6000+3600+6900+11400+900+6600+16200+13200+13200+21900+7200 -> 166700 | F15: =9300+9600+5400+5400+4200+9900+6300+7200+14400+8400+8400 -> 88500 | G15: =16200+13200+19200+6400 -> 55000 | H15: =E15+F15 -> 255200
A16: 45943 | B16: =6+2+8+4+12+4+1+1+4+6+6+4+3+3 -> 64 | C16: =4+1+2+3+4+1 -> 15 | D16: 1 | E16: =1800+7200+3600+3600+2100+4500+3600+3600+5400+5400+2700 -> 43500 | F16: =5400+4800+10800+8400+3900 -> 33300 | H16: =E16+F16 -> 76800
A17: 45944 | B17: =3+4+8+8+6 -> 29 | C17: =3+4+2 -> 9 | D17: 1 | E17: =6300+3700+8400+12000+2400 -> 32800 | F17: =5400 -> 5400 | H17: =E17+F17 -> 38200
A18: 45945 | B18: =8+6+4 -> 18 | C18: =4+6+6+6 -> 22 | E18: =4800+7200 -> 12000 | F18: =7200+10800 -> 18000 | G18: =16200 -> 16200 | H18: =E18+F18 -> 30000
A19: 45946 | B19: =12+2+12+4+12+1+2 -> 45 | C19: =6+1+1+2+3+3 -> 16 | D19: =3+3 -> 6 | E19: =18200+3000+1200+10800+6600+3300+1800+3600 -> 48500 | F19: =10800+7800 -> 18600 | H19: =E19+F19 -> 67100
A20: 45947 | B20: =10+4+4 -> 18 | C20: =10+6+4+6 -> 26 | E20: =12000+9000+7200+8400+3600 -> 40200 | F20: =7200 -> 7200 | H20: =E20+F20 -> 47400
A21: 45948 | B21: =4+6+2 -> 12 | C21: =6+3+4+9+6+3+4+24+4+6 -> 69 | D21: =3 -> 3 | E21: =9600+3600+3600+14400+3000+6600+28800+4800 -> 74400 | F21: =4800+3600+7200 -> 15600 | G21: =16200 -> 16200 | H21: =E21+F21 -> 90000
A22: 45949 | B22: =3+2+2+6+12+2 -> 27 | C22: =4+4+10+2+4+6+5 -> 35 | D22: =3+3 -> 6 | E22: =6600+12000+4200+8400+4800+10000 -> 46000 | G22: =9700+13200+10200 -> 33100 | H22: =E22+F22 -> 46000
A23: 45950 | B23: =8+2+4+2 -> 16 | C23: =4+4 -> 8 | E23: =7200+6600 -> 13800 | F23: =6600+3600 -> 10200 | H23: =E23+F23 -> 24000
A24: 45951 | B24: =8 -> 8 | C24: =4+7 -> 11 | D24: =3 -> 3 | E24: =4800+7200 -> 12000 | F24: =8400+3000 -> 11400 | H24: =E24+F24 -> 23400
A25: 45952 | B25: =4+4+6+2+6+3+6 -> 31 | C25: =4+1+4+4 -> 13 | D25: =3 -> 3 | E25: =8400+4800+5400+5400 -> 24000 | F25: =5400+6600+10500 -> 22500 | H25: =E25+F25 -> 46500
A26: 45953 | B26: =4 -> 4 | C26: =4+6+4+8 -> 22 | E26: =8400+7200+4800+9600 -> 30000 | H26: =E26+F26 -> 30000
A27: 45954 | B27: =9+1 -> 10 | C27: =3+6+2+2 -> 13 | D27: 3 | E27: =3600+11000+2400+3300 -> 20300 | F27: 7200 | H27: =E27+F27 -> 27500
A28: 45955 | B28: =6+6+10+12+4+8+4+9+5 -> 64 | C28: =3+6+6+8+4+8+1 -> 36 | D28: =6+3 -> 9 | E28: =6000+3600+16800+10500+4800+19200 -> 60900 | F28: =15600+10800+9600+4800+4800+9600 -> 55200 | G28: =5700+13000+28800 -> 47500 | H28: =E28+F28 -> 116100
A29: 45956 | B29: =6+10+14+6+6+6+6+8+6+6+2+2+12+9+8+3+4+4+2+4+6 -> 130 | C29: =6+4+6+6+12+12+6+6+4+4+12+4+12+2+4+6+2+4+4+12+6 -> 134 | D29: =1+9+1+1+1+4 -> 17 | E29: =10200+17400+12600+15000+7200+13800+6600+6600+25200+4800+8100+22800+9600+9000+8400+4200+1600 -> 183100 | F29: =12600+9000+5400+7200+7200+5400+3600 -> 50400 | G29: =19200+22800+19200+7800+7700+11800+22800+11400 -> 122700 | H29: =E29+F29 -> 233500
A30: 45957 | B30: =6+6+6+2 -> 20 | C30: =2+6+2+2 -> 12 | E30: =7800+4200+2000 -> 14000 | F30: =5400+12600+2400 -> 20400 | H30: =E30+F30 -> 34400
A31: 45958 | B31: =6+3+12+2+24+1+1+3 -> 52 | C31: =8+1+6+1+2+2+2+6+2 -> 30 | E31: =5400+9600+4200+2400 -> 21600 | F31: =3900+7200+12000+3300+8100+5100 -> 39600 | G31: =28080 -> 28080 | H31: =E31+F31 -> 61200
A32: 45959 | B32: =3+3+1 -> 7 | C32: =2+3+4+2 -> 11 | D32: =1 -> 1 | E32: =6300+900 -> 7200 | F32: =6000+2400 -> 8400 | G32: =6960 -> 6960 | H32: =E32+F32 -> 15600
A33: 45960 | B33: =4+10+4+4+3+6 -> 31 | C33: =4+8+2+6 -> 20 | D33: =3+3 -> 6 | E33: =13200+3000 -> 16200 | F33: =4800+6000+3600+12900 -> 27300 | G33: =11700+7020 -> 18720 | H33: =E33+F33 -> 43500
A34: 45961 | B34: =6+12 -> 18 | E34: =5400+11000 -> 16400 | H34: =E34+F34 -> 16400

Sheet GASTOS NOVIEMBRE
A1: DETALLES GASTOS ENTREGADOS POR CONTRATISTA, FACTURAS "A"
K2: PAGOS
A3: FECHA | B3: ABONO | C3: RUBRO | D3: PROVEEDOR | E3: CANTIDAD | F3: DESCRIPCIÓN | G3: $ c/IVA+Ing.Br | H3: IVA | I3: 1/2IVA | J3: Perc.Ing.Bruto | K3: EFECTIVO | L3: TRANFERENCIA | M3: PEYA WALLET
A4: 45965 | B4: C | C4: DULCE DE LECHE | D4: LUZ AZUL | E4: 2 | F4: 2 POTE X 10KG DULCE DE LECHE LUZ AZUL | G4: =2*42250 -> 84500 | K4: =SUM(G4) -> 84500
A5: 45962 | B5: C | C5: PEDIDO YA | D5: PEDIDO YA | E5: 1 | F5: GASTOS DE COMICION 13-10 AL 19-10 | G5: =22662.95+4759.22+24000 -> 51422.17 | K5: 0 | M5: =G5 -> 51422.17
A6: 45969 | B6: C | C6: DULCE DE LECHE | D6: JULIA | E6: 2 | F6: 4 POTE X 10KG DULCE DE LECHE PIGUENSE | G6: =25500*2 -> 51000 | K6: =SUM(G6) -> 51000
A7: 45969 | B7: C | C7: PEDIDO YA | D7: PEDIDO YA | E7: 1 | F7: GASTOS DE COMICION 20-10 AL 26-10 | G7: =56143.31+19200+15822.1+51000 -> 142165.41 | K7: 0 | M7: =G7 -> 142165.41
A8: 45970 | B8: C | C8: CUBANITO COMUN | D8: MAXI | E8: 400 | F8: 1 CAJA X 400 CUBANITOS COMUNES ($156,00 X UNIDAD) | G8: =400*156 -> 62400 | L8: =G8 -> 62400
A9: 45970 | B9: C | C9: EXTRACCION | D9: ERICA | F9: EXTRACCION MES SEPTIEMBRE EFECTIVO | G9: 800000 | K9: 400000 | L9: 0 | M9: 400000
A10: 45970 | B10: C | C10: EXTRACCION | D10: MATIAS | F10: EXTRACCION MES SEPTIEMBRE BANCARIZADA X TRANFERENCIAS | G10: 800000 | K10: 69500 | L10: =G10-M10-K10 -> 566938.74 | M10: 163561.26
A11: 45974 | B11: C | C11: CONTADOR | D11: JORGE | E11: 1 | F11: PAGO MENSUAL JORGE | G11: 15000 | L11: =G11 -> 15000
A12: 45975 | B12: C | C12: PEDIDO YA | D12: PEDIDO YA | E12: 1 | F12: GASTOS DE COMICION 27-10 AL 02-11 | G12: =37049.82+7780.46+23000-19200 -> 48630.28 | K12: 0 | M12: =G12 -> 48630.28
A13: 45976 | B13: C | C13: CUBANITO COMUN | D13: MAXI | E13: 400 | F13: 1 CAJA X 400 CUBANITOS COMUNES ($156,00 X UNIDAD) | G13: 62400
A14: 45976 | B14: C | C14: CUBANITO BAÑADO | D14: MAXI | E14: 400 | F14: 1 CAJA X 400 CUBANITOS BAÑADOS ($358,00 X UNIDAD) | G14: 143200
A15: 45958 | B15: C | C15: CUBANITO BAÑADO | D15: MAXI | E15: 200 | F15: 1 CAJA X 200 CUBANITOS BAÑADOS ($358,00 X UNIDAD) | G15: 71100 | K15: =G13+G14+G15 -> 276700
A16: 45978 | B16: C | C16: BOLSAS | D16: Plasticos blancon | E16: 100 | F16: 100 BOLSAS NCAMISETAS DE 40X50 | G16: 2900 | K16: =G16 -> 2900
A17: 45978 | B17: C | C17: IMPUESTO | D17: ARCA | E17: 1 | F17: MONOTRIBUTO MES NOVIEMBRE | G17: 44580.74 | L17: =G17 -> 44580.74
A18: 45978 | B18: C | C18: IMPUESTO | D18: MUNICIPALIDAD | E18: 1 | F18: TASA SEGURIDAD E HIGIENE NOVIEMBRE 2025 | G18: 15103 | L18: =G18 -> 15103
A19: 45980 | B19: C | C19: DULCE DE LECHE | D19: LUZ AZUL | E19: 2 | F19: 2 POTE X 10KG DULCE DE LECHE LUZ AZUL | G19: 88300 | K19: =SUM(G19) -> 88300 | M19: =G4+G5+G6+G8+G11+G12+G13+G14+G15+G16+G17+G18+G19 -> 740536.19
A20: 45986 | B20: C | C20: PEDIDO YA | D20: PEDIDO YA | E20: 1 | F20: GASTOS DE COMICION 3-11 AL 09-11 | G20: =29489.56+10260+8347.41 -> 48096.97 | K20: 0 | M20: =G20 -> 48096.97
A21: 45987 | B21: C | C21: PLAGAS | D21: LUGONES | F21: CONTROL DE PLGAS MES OCTUBRE | G21: 16000 | L21: =G21 -> 16000
A22: 45988 | B22: C | C22: BOLSAS | D22: PAPELERA SAN LUIS | E22: 1000 | F22: 500 BOLSAS N3L+ 500 BOLSAS N4 | G22: 25000 | K22: =G22 -> 25000
A23: 45988 | B23: C | C23: BOLSAS | D23: MICRO ENVASES | E23: 1 | F23: 100 GUANTES+ BOLSAS CAMISETAS | G23: 5000 | K23: =G23 -> 5000
A24: 45990 | B24: C | C24: DULCE DE LECHE | D24: LUZ AZUL | E24: 1 | F24: 1 POTE X 10KG DULCE DE LECHE LUZ AZUL | G24: =44000 -> 44000 | K24: =SUM(G24) -> 44000
A25: 45990 | B25: C | C25: PEDIDO YA | D25: PEDIDO YA | E25: 1 | F25: GASTOS DE COMICION 10-11 AL 16-11 | G25: =41590.59+8734.02+27620 -> 77944.61 | K25: 0 | M25: =G25 -> 77944.61
A26: 45991 | B26: C | C26: CUBANITO COMUN | D26: MAXI | E26: 200 | F26: 1 CAJA X 200 CUBANITOS COMUNES ($156,00 X UNIDAD) | G26: 31200 | L26: =G26 -> 31200
A27: 45991 | B27: C | C27: CUBANITO COMUN | D27: MAXI | E27: 200 | F27: 1 CAJA X 200 CUBANITOS BAÑADOS ($358,00 X UNIDAD) | G27: 71600 | L27: =G27 -> 71600
A28: 45991 | B28: C | C28: EXTRACCION | D28: ERICA | F28: EXTRACCION MES SEPTIEMBRE EFECTIVO | G28: 350000 | K28: 0 | L28: =G28-M28 -> 106000 | M28: 244000
A29: 45991 | B29: C | C29: EXTRACCION | D29: MATIAS | F29: EXTRACCION MES SEPTIEMBRE BANCARIZADA X TRANFERENCIAS | G29: 350000 | K29: 0 | L29: 350000
G31: =G4+G5+G6+G7+G8+G11+G12+G13+G14+G15+G16+G17+G18+G19+G20+G21+G22+G23+G24+G25+G26+G27 -> 1201543.2
A53: 45930 | B53: C | C53: PEDIDO YA | D53: PEDIDO YA | E53: 1 | F53: GASTOS DE COMICION 15-9 AL 21-9 | G53: =20677+4894.54+7415.75 -> 32987.29 | K53: 0 | M53: =G53 -> 32987.29
A54: 45940 | B54: C | C54: CUBANITO COMUN | D54: MAXI | E54: 600 | F54: 1 CAJA X 600 CUBANITOS COMUNES ($156,00 X UNIDAD) | G54: =62400+31200 -> 93600 | K54: =G54 -> 93600
A55: 45943 | B55: C | C55: DULCE DE LECHE | D55: JULIA | E55: 4 | F55: 4 POTE X 10KG DULCE DE LECHE PIGUENSE | G55: =25000*4 -> 100000 | K55: =SUM(G55) -> 100000
A56: 45943 | B56: C | C56: CONTADOR | D56: JORGE | E56: 1 | F56: PAGO MENSUAL JORGE | G56: 10000 | L56: =G56 -> 10000
A57: 45941 | B57: C | C57: IMPUESTO | D57: ARCA | E57: 1 | F57: MONOTRIBUTO MES OCTUBRE | G57: 11677.6 | L57: =G57 -> 11677.6
A58: 45930 | B58: C | C58: PEDIDO YA | D58: PEDIDO YA | E58: 1 | F58: GASTOS DE COMICION 22-9 AL 28-9 | G58: =1119.23+235.04 -> 1354.27 | K58: 0 | M58: =G58 -> 1354.27
A59: 45945 | B59: C | C59: EXTRACCION | D59: ERICA | F59: EXTRACCION MES SEPTIEMBRE EFECTIVO | G59: 650000 | K59: 400000 | L59: 250000
A60: 45945 | B60: C | C60: EXTRACCION | D60: MATIAS | F60: EXTRACCION MES SEPTIEMBRE BANCARIZADA X TRANFERENCIAS | G60: 650000 | K60: 350000 | L60: 300000
A61: 45947 | B61: C | C61: PEDIDO YA | D61: PEDIDO YA | E61: 1 | F61: GASTOS DE COMICION 29-9 AL 5-10 | G61: =31291.02+4829.1+7585.22+6600 -> 50305.34 | K61: 0 | M61: =G61 -> 50305.34
A62: 45951 | B62: C | C62: PLAGAS | D62: LUGONES | F62: CONTROL DE PLGAS MES OCTUBRE | G62: 16000 | L62: =G62 -> 16000
A63: 45954 | B63: C | C63: PEDIDO YA | D63: PEDIDO YA | E63: 1 | F63: GASTOS DE COMICION 6-10 AL 12-10 | G63: =54138.37+33500+17314.66+26000-5187.61 -> 125765.42 | K63: 0 | M63: =G63 -> 125765.42
A64: 45958 | B64: C | C64: CUBANITO COMUN | D64: MAXI | E64: 400 | F64: 1 CAJA X 400 CUBANITOS COMUNES ($156,00 X UNIDAD) | G64: 62400
A65: 45958 | B65: C | C65: CUBANITO BAÑADO | D65: MAXI | E65: 400 | F65: 1 CAJA X 400 CUBANITOS BAÑADOS ($358,00 X UNIDAD) | G65: 143200
A66: 45958 | B66: C | C66: CUBANITO BAÑADO | D66: MAXI | E66: 200 | F66: 1 CAJA X 200 CUBANITOS BAÑADOS ($358,00 X UNIDAD) | G66: 71100 | K66: =G64+G65+G66 -> 276700
M68: =203823-G63+5187.61 -> 83245.19
B99: C
B100: C
B101: C
B102: C
B103: C
B104: C
B105: C
B106: C
B107: C
B108: C
B109: C
B110: C
... B129: C
A134: 45854 | B134: M | C134: CUBANITO COMUN
A135: 45906 | B135: C | C135: DULCE DE LECHE | D135: LUZ AZUL | E135: 1 | F135: 1 POTE X 10KG DULCE DE LECHE LUZ AZUL | G135: 41000 | K135: 41000
A136: 45907 | B136: C | C136: CUBANITO COMUN | D136: MAXI | E136: 400 | F136: 1 CAJA X 400 CUBANITOS COMUNES ($156,00 X UNIDAD) | G136: 62400
A137: 45907 | B137: C | C137: CUBANITO BAÑADO | D137: MAXI | E137: 400 | F137: 1 CAJA X 400 CUBANITOS BAÑADOS ($358,00 X UNIDAD) | G137: 143200
A138: 45907 | B138: C | C138: DULCE DE LECHE | D138: MAXI | E138: 2 | F138: 1 POTE X 10KG DULCE DE LECHE PIGUENSE | G138: 51000 | K138: =SUM(G136:G138) -> 256600
A139: 45910 | B139: C | C139: VESTIMENTA | D139: ARRUMACO | E139: 1 | F139: 2 DELANTALES + 2 COFIA | G139: =12000+10000 -> 22000 | K139: =G139 -> 22000
A140: 45911 | B140: C | C140: IMPUESTO | D140: MUNICIPALIDAD | E140: 1 | F140: TASA SEGURIDAD E HIGIENE SEPTIEMBRE 2025 | G140: 14384 | L140: =G140 -> 14384
A141: 45911 | B141: C | C141: IMPUESTO | D141: ARCA | E141: 1 | F141: MONOTRIBUTO MES SEPTIEMBRE | G141: 11677.6 | L141: =G141 -> 11677.6
A142: 45912 | B142: C | C142: DULCE DE LECHE | D142: JULIA | E142: 2 | F142: 1 POTE X 10KG DULCE DE LECHE PIGUENSE | G142: 51000 | K142: =SUM(G142) -> 51000
A143: 45907 | B143: C | C143: CUBANITO COMUN | D143: MAXI | E143: 400 | F143: 1 CAJA X 400 CUBANITOS COMUNES ($156,00 X UNIDAD) | G143: 62400
A144: 45907 | B144: C | C144: CUBANITO BAÑADO | D144: MAXI | E144: 400 | F144: 1 CAJA X 400 CUBANITOS BAÑADOS ($358,00 X UNIDAD) | G144: 143200
A145: 45907 | B145: C | C145: CUBANITO BAÑADO | D145: MAXI | E145: 400 | F145: 1 CAJA X 400 CUBANITOS BAÑADOS BLANCOS ($358,00 X UNIDAD) | G145: 143200 | K145: =G143+G144+G145 -> 348800
A146: 45913 | B146: C | C146: GARRAPIÑADA | D146: CHICA | E146: 5 | F146: 35KG DE GARRAPIÑADA ($10.000 X KG) | G146: =10000*5 -> 50000 | K146: 0 | L146: =G146 -> 50000
A147: 45915 | B147: C | C147: REPUESTOS | D147: NITRAM | E147: 1 | F147: REPUESTOS PARA HACER PUNTERA DE CUBANERA | G147: 12750 | K147: 0 | L147: =G147 -> 12750
A148: 45916 | B148: C | C148: DULCE DE LECHE | D148: LUZ AZUL | E148: 2 | F148: 2 POTE X 10KG DULCE DE LECHE LUZ AZUL (42261.50) | G148: 84523 | K148: =G148 -> 84523
A149: 45916 | B149: C | C149: DULCE DE LECHE | D149: LUZ AZUL | E149: 4 | F149: 4 POTE X 10KG DULCE DE LECHE LUZ AZUL (42261.50) | G149: 169046 | L149: =G149 -> 169046
A150: 45916 | B150: C | C150: DULCE DE LECHE | D150: JULIA | E150: 6 | F150: 6 POTE X 10KG DULCE DE LECHE PIGUENSE ($25.000) | G150: =25000*6 -> 150000 | K150: =SUM(G150) -> 150000
A151: 45916 | B151: C | C151: REPUESTOS | D151: ALFA RODAMIENTO | E151: 1 | F151: REPUESTOS ORRIN PARA CUBANERA | G151: 1500 | K151: =G151 -> 1500
A152: 45917 | B152: C | C152: BOLSAS | D152: PAPELERA SAN LUIS | E152: 600 | F152: 500 BOLSAS N3L+ 100 BOLSAS N4 | G152: 13800 | L152: 13800
A153: 45918 | B153: C | C153: CONTADOR | D153: JORGE | E153: 1 | F153: PAGO MENSUAL JORGE | G153: 10000 | L153: =G153 -> 10000
A154: 45918 | B154: C | C154: GARRAPIÑADA | D154: GLORIA | E154: 10 | F154: 10 KG DE GARRAPIÑADA ($8.000 X KG) | G154: =8000*10 -> 80000 | K154: =G154 -> 80000
A155: 45919 | B155: C | C155: CUBANITO COMUN | D155: MAXI | E155: 600 | F155: 1 CAJA X 400 CUBANITOS COMUNES ($156,00 X UNIDAD) | G155: =62400+31200 -> 93600
A156: 45919 | B156: C | C156: CUBANITO BAÑADO | D156: MAXI | E156: 400 | F156: 1 CAJA X 400 CUBANITOS BAÑADOS ($358,00 X UNIDAD) | G156: 143200 | L156: =G155+G156 -> 236800
A157: 45918 | B157: C | C157: DULCE DE LECHE | D157: LUZ AZUL | E157: 3 | F157: 3 POTE X 10KG DULCE DE LECHE LUZ AZUL (42261.50) | G157: =42261.5*3 -> 126784.5 | K157: =G157 -> 126784.5 | L157: 0
A158: 45919 | B158: C | C158: PEDIDO YA | D158: PEDIDO YA | E158: 1 | F158: GASTOS DE COMICION 1-9 AL 7-9 | G158: =8925.94+415.87+2079.59 -> 11421.4 | K158: 0 | M158: =G158 -> 11421.4
A159: 45922 | B159: C | C159: PLAGAS | D159: LUGONES | F159: CONTROL DE PLGAS MES septiembre | G159: 16000 | L159: =G159 -> 16000
A160: 45922 | B160: C | C160: GARRAFA | D160: GARRAFAS DON BOSCO | F160: CARGA DE GARRAFA | G160: 7000 | K160: 7000
A161: 45924 | B161: C | C161: DULCE DE LECHE | D161: JULIA | E161: 4 | F161: 4 POTE X 10KG DULCE DE LECHE PIGUENSE ($25.000) | G161: =25000*4 -> 100000 | K161: =SUM(G161) -> 100000
A162: 45926 | B162: C | C162: CUBANITO COMUN | D162: MAXI | E162: 1200 | F162: 3 CAJA X 400 CUBANITOS COMUNES ($156,00 X UNIDAD) | G162: =62400*3 -> 187200
A163: 45926 | B163: C | C163: CUBANITO BAÑADO | D163: MAXI | E163: 2000 | F163: 5 CAJA X 400 CUBANITOS BAÑADOS ($358,00 X UNIDAD) | G163: =143200*5 -> 716000 | K163: =G162+G163-25000-62400 -> 815800
A164: 45929 | B164: C | C164: EMPLEADA | D164: EMPLEADA | E164: 2 | F164: MILI TRABAJO EL 27/09+28/09 | G164: =30000*2 -> 60000 | K164: =G164 -> 60000
A165: 45930 | B165: C | C165: PEDIDO YA | D165: PEDIDO YA | E165: 1 | F165: GASTOS DE COMICION 15-9 AL 21-9 | G165: =20677+4894.54+7415.75+15750 -> 48737.29 | K165: 0 | M165: =G165 -> 48737.29
A166: 45930 | B166: C | C166: EXTRACCION | D166: ERICA | F166: EXTRACCION MES SEPTIEMBRE EFECTIVO | G166: 1300000 | K166: 800000 | L166: 500000
A167: 45930 | B167: C | C167: EXTRACCION | D167: MATIAS | F167: EXTRACCION MES SEPTIEMBRE BANCARIZADA X TRANFERENCIAS | G167: 1300000 | K167: 400000 | L167: 900000
A168: 45854 | B168: M | C168: CUBANITO BAÑADO
A169: 45854 | B169: M | C169: DULCE DE LECHE
A170: 45853 | B170: M | C170: GARRAPIÑADA
A171: 45855 | B171: C | C171: CONTADOR
A172: 45855 | B172: C | C172: IMPUESTO
A173: 45856 | B173: C | C173: DULCE DE LECHE
A174: 45859 | B174: C | C174: PLAGAS
A175: 45859 | B175: C | C175: IMPUESTO
...

Sheet VENTAS NOVIEMBRE
A1: MES:
B2: CUBANITOS | E2: METODO DE PAGO | H2: TOTAL | J2: MES NOVIEMBRE
A3: DIA | B3: COMUNES | C3: BAÑADOS | D3: OTRO | E3: EFECTIVO | F3: TRANSFERENCIA | G3: PEDIDOS YA | H3: VENTAS $
A4: 45962 | B4: =2+15+6+2+6+12+6+12+4+6 -> 71 | C4: =4+6+2+6+6+6+2+1+1+4 -> 38 | D4: 3 | E4: =6600+3600+7200+1000+3000+1000+4800 -> 27200 | F4: =13500+4200+12600+5400+18000+5400+2400 -> 61500 | G4: =19200+15600 -> 34800 | H4: =E4+F4 -> 88700 | J4: Tranferencia | K4: =SUMIF(F4:F31,">0") -> 768420
A5: 45963 | B5: =12+4+2+4+3+18+4+4+2+6+6+6+4+1+3+12 -> 91 | C5: =6+4+6+8+1+6+8+12+4+6+12+4+6+2+4+2+2+6+6 -> 105 | D5: 3 | E5: =9000+3900+16200+13200+11600+2400+11400+10800 -> 78500 | F5: =18000+8400+3000+13200+7200+14400+8400+7200+4800+12600+8400+3300+9900 -> 118800 | G5: =25400+7800 -> 33200 | H5: =E5+F5 -> 197300 | J5: efectivo | K5: =SUMIF(E4:E31,">0") -> 927900
A6: 45964 | B6: =3+4+6+4+1+6+6+1 -> 31 | C6: =2+2+6+1 -> 11 | D6: 3 | E6: =3000+600+6000+3300+5400+12600 -> 30900 | F6: =6000+5400+2100 -> 13500 | H6: =E6+F6 -> 44400 | J6: PedidosYA | K6: =SUMIF(G4:G34,">0") -> 518820
A7: 45965 | B7: =1+12 -> 13 | C7: =6+3 -> 9 | E7: =3600+900+10800 -> 15300 | F7: 7200 | H7: =E7+F7 -> 22500 | J7: TOTAL | K7: =K4+K5+K6 -> 2215140
A8: 45966 | B8: =8+8+1+8 -> 25 | C8: =4+2+2+4 -> 12 | E8: 0 | F8: =4800+7200+2400+7200+3300 -> 24900 | G8: =16200 -> 16200 | H8: =E8+F8 -> 24900
A9: 45967 | B9: =6+4+3+8+1+3 -> 25 | C9: =12+7+5+3+3+4+4+3+3 -> 44 | D9: =1+1 -> 2 | E9: =3600+3600+13200+7500 -> 27900 | F9: =14400+6000+7500+4800+4500 -> 37200 | G9: 20700 | H9: =E9+F9 -> 65100 | J9: CONSUMO CUBANITOS
A10: 45968 | B10: =4+2+6+3+12+6 -> 33 | C10: =5+2+4+4+3+12+24 -> 54 | D10: =3+3+3+3 -> 12 | E10: =2400+6600+4800+9600+9300+5400+3000+28800 -> 69900 | F10: =6000+10800 -> 16800 | G10: =7020+20520 -> 27540 | H10: =E10+F10 -> 86700 | J10: COMUNES | K10: BAÑADOS
A11: 45969 | B11: =5+6+3+1+6+1+9+4+3+4+8+6 -> 56 | C11: =3+8+3+6+6+6+13+3+2+9+4+4 -> 67 | D11: =1+3 -> 4 | E11: =12600+900+21000+1200+3300+3600+5700+8400+5400 -> 62100 | F11: =3600+9600+8100+2700+7200+7200+18900+12000 -> 69300 | G11: 5700 | H11: =E11+F11 -> 131400 | J11: =SUM(B4:B33) -> 1163 | K11: =SUM(C4:C33) -> 961
A12: 45970 | B12: =8+6+18+12+6+12+12+6+6+4+12+6+1+6+2+6 -> 123 | C12: =5+6+6+6+4+12+2+6+4+2 -> 53 | D12: 1 | E12: =6000+5400+16200+7200+12000+10800+5700+7200+10800+6600+7800 -> 95700 | F12: =7200+10800+5400+4800+14400+3300+5400 -> 51300 | G12: =15600+7800+7800+11400 -> 42600 | H12: =E12+F12 -> 147000
A13: 45971 | B13: =2+10+16+12+1 -> 41 | C13: =1+2+2+2 -> 7 | E13: =3000+9000+2400+10800 -> 25200 | F13: =11400+3300 -> 14700 | H13: =E13+F13 -> 39900
A14: 45972 | B14: =8+6+2+2+6+5+3 -> 32 | C14: =6+4+4+1+5+3 -> 23 | E14: =7200+12000+5400+4800+1800+3000+10500 -> 44700 | F14: =5400+6300 -> 11700 | H14: =E14+F14 -> 56400
A15: 45973 | B15: =3+4+3+2 -> 12 | C15: =5+8+6+3+2 -> 24 | E15: =2700+13200+6300+4200 -> 26400 | F15: =6000+7200 -> 13200 | H15: =E15+F15 -> 39600
A16: 45974 | B16: =6+2+1+6+6+6+2 -> 29 | C16: =2+1+4+6 -> 13 | E16: =5400+4200+2100+6600 -> 18300 | F16: 7020 | G16: =7020+10260 -> 17280 | H16: =E16+F16 -> 25320
A17: 45975 | B17: =5+2+4 -> 11 | C17: =3+12+4 -> 19 | E17: =8100+1800+12800 -> 22700 | F17: 14400 | H17: =E17+F17 -> 37100
A18: 45976 | B18: =6+6+15+6+4+8+6+8+2+6+12 -> 79 | C18: =6+6+4+6+10+6+6 -> 44 | D18: =3+1+3 -> 7 | E18: =8400+13500+8400+8400+10200+12600 -> 61500 | F18: =12600+7200+10800 -> 30600 | G18: =19200+19200+21600 -> 60000 | H18: =E18+F18 -> 92100
A19: 45977 | B19: =2+3+3+4+4+6+2+4+6+1+6+3+6+4+4+4+2 -> 64 | C19: =2+3+3+4+12+4+6+4+2+6+6+4+6+4+4+6+4 -> 80 | D19: =1+3+1+3+3+3 -> 14 | E19: =3000+4200+8400+14400+8400+6600+7800+8400+15600+3000+3600+3600+10200+6600 -> 103800 | F19: =6300+6000+3900+7500+8400 -> 32100 | G19: =9600+19200+20800+7600 -> 57200 | H19: =E19+F19 -> 135900
A20: 45978 | B20: =3+3+12 -> 18 | C20: 3 | D20: 1 | E20: 3900 | F20: =6300+10800 -> 17100 | H20: =E20+F20 -> 21000
A21: 45979 | B21: =12+3+3+1+24+3+6+3 -> 55 | C21: =5+3+3+2+3+3+12+8+8 -> 47 | D21: 1 | E21: =10800+3300+6300+5400+6300+14400 -> 46500 | F21: =6000+7500+2700+3600+9600+9600 -> 39000 | G21: =31200 -> 31200 | H21: =E21+F21 -> 85500
A22: 45980 | B22: =5+6+2+4+6+2 -> 25 | C22: =4+5+2+2+12 -> 25 | E22: =4800+1800+3600 -> 10200 | F22: =10500+7800+5400+4200+14400 -> 42300 | H22: =E22+F22 -> 52500
A23: 45981 | B23: =3+3 -> 6 | C23: 3 | D23: 1 | E23: =1200+2700 -> 3900 | F23: =6300 -> 6300 | H23: =E23+F23 -> 10200
A24: 45982 | B24: =12+3+2+6+4+3+6 -> 36 | C24: =4+6+8+2 -> 20 | E24: =6000+13200 -> 19200 | F24: =10800+2700+600+12600+2700+7800 -> 37200 | H24: =E24+F24 -> 56400
A25: 45983 | B25: =1+4+6 -> 11 | C25: =1+6+9+8+6+6 -> 36 | E25: 18900 | F25: =2100+7200+7200+12600 -> 29100 | G25: 15200 | H25: =E25+F25 -> 48000
A26: 45984 | B26: =18+6+1+4+6+3 -> 38 | C26: =6+6+12+4+6+2+3 -> 39 | E26: 6300 | F26: =23400+12600+7200 -> 43200 | G26: =22800+8900+9000+7800 -> 48500 | H26: =E26+F26 -> 49500
A27: 45985 | B27: =3+4+6+2+6+6+6+3+2 -> 38 | C27: =3+8+2+6+6+6+3+7+2 -> 43 | E27: =6300+13200+4200+5400+7200+11400 -> 47700 | F27: =5400+6300+4200 -> 15900 | G27: =7800+11400+7800+13300 -> 40300 | H27: =E27+F27 -> 63600
A28: 45986 | B28: =3+4 -> 7 | C28: 3 | F28: =6300+3600 -> 9900 | H28: =E28+F28 -> 9900
A29: 45987 | B29: =2+5+6+1 -> 14 | C29: =2+6+1 -> 9 | D29: 6 | E29: =1800+6900+12600+6000+2100 -> 29400 | H29: =E29+F29 -> 29400
A30: 45988 | B30: =2+4+4+6 -> 16 | C30: =4+4 -> 8 | D30: 1 | E30: =6600+8400+6000+5400 -> 26400 | H30: =E30+F30 -> 26400
A31: 45989 | B31: =10+2+6 -> 18 | C31: 2 | E31: 5400 | F31: 4200 | G31: 13000 | H31: =E31+F31 -> 9600
A32: 45990 | B32: =6+2+4+6+6+4+5+3+4+5 -> 45 | C32: =4+3+4+8+4+4 -> 27 | D32: =3+1 -> 4 | E32: =3600+5400+5400+13200+4500+5400 -> 37500 | F32: =3000+3600+6600+9300+4800+3900 -> 31200 | G32: 15400 | H32: =E32+F32 -> 68700
A33: 45991 | B33: =18+6+8+6+6+6+3+4+6+6+12+4+9+3+3 -> 100 | C33: =6+12+2+12+6+6+2+6+12+4+3+4+12+6 -> 93 | D33: =3+1+3+1 -> 8 | E33: =16200+21600+3000+12600+6000+7800+9600+6000+9200+11500+15600+7800 -> 126900 | F33: =12600+3600+19800+3000+13800+14700+3000 -> 70500 | G33: 40000 | H33: =E33+F33 -> 197400
H34: =E34+F34 -> 0

Sheet GASTOS DICIEMBRE
A1: DETALLES GASTOS ENTREGADOS POR CONTRATISTA, FACTURAS "A"
K2: PAGOS
A3: FECHA | B3: ABONO | C3: RUBRO | D3: PROVEEDOR | E3: CANTIDAD | F3: DESCRIPCIÓN | G3: $ c/IVA+Ing.Br | H3: IVA | I3: 1/2IVA | J3: Perc.Ing.Bruto | K3: EFECTIVO | L3: TRANFERENCIA | M3: PEYA WALLET
A4: 45992 | B4: C | C4: CUBANITO COMUN | D4: MAXI | E4: 200 | F4: 1 CAJA X 400 CUBANITOS COMUNES ($168,50 X UNIDAD) | G4: =168.5*E4 -> 33700
A5: 45992 | B5: C | C5: CUBANITO BAÑADO | D5: MAXI | E5: 200 | F5: 1 CAJA X 400 CUBANITOS BAÑADOS ($490,00 X UNIDAD) | G5: =490*E5 -> 98000 | K5: =G4+G5 -> 131700
A6: 45992 | B6: C | C6: BOLSAS | D6: PLASTICOS BLANCOS | E6: 400 | F6: 400 BOLSAS GARRAPIÑADAS | G6: 6470 | L6: =G6 -> 6470
A7: 45995 | B7: C | C7: DULCE DE LECHE | D7: LUZ AZUL | E7: 1 | F7: 1 POTE X 10KG DULCE DE LECHE LUZ AZUL (44500) | G7: 44500 | K7: =G7 -> 44500 | L7: 0
A8: 46000 | B8: C | C8: CUBANITO COMUN | D8: MAXI | E8: 200 | F8: 1 CAJA X 400 CUBANITOS COMUNES ($168,50 X UNIDAD) | G8: =168.5*E8 -> 33700 | K8: =G8 -> 33700
A9: 46020 | B9: C | C9: PEDIDO YA | D9: PEDIDO YA | E9: 1 | F9: GASTOS DE COMICION 17-11 AL 23-11 | G9: =21827+2559.04+5121.07 -> 29507.11 | K9: 0 | M9: =G9 -> 29507.11
A10: 46000 | B10: C | C10: DULCE DE LECHE | D10: LUZ AZUL | E10: 1 | F10: 1 POTE X 10KG DULCE DE LECHE LUZ AZUL (44500) | G10: 44200 | K10: =G10 -> 44200 | L10: 0
A11: 46020 | B11: C | C11: PEDIDO YA | D11: PEDIDO YA | E11: 1 | F11: GASTOS DE COMICION 24-11 AL 30-11 | G11: =29688.3+5539.28+22900-9239.74 -> 48887.84 | K11: 0 | M11: =G11 -> 48887.84
A12: 46000 | B12: C | C12: CUBANITO COMUN | D12: MAXI | E12: 200 | F12: 1 CAJA X 200 CUBANITOS BAÑADOS ($490,00 X UNIDAD) | G12: 98000 | K12: =G12 -> 98000
A13: 46004 | B13: C | C13: CONTADOR | D13: JORGE | E13: 1 | F13: PAGO MENSUAL JORGE | G13: 15000 | L13: =G13 -> 15000
A14: 46007 | B14: C | C14: CUBANITO COMUN | D14: MAXI | E14: 200 | F14: 1 CAJA X 400 CUBANITOS COMUNES ($168,50 X UNIDAD) | G14: =168.5*E14 -> 33700
A15: 46007 | B15: C | C15: CUBANITO BAÑADO | D15: MAXI | E15: 100 | F15: 1 CAJA X 100 CUBANITOS BAÑADOS ($490,00 X UNIDAD) | G15: 24500 | K15: =G14+G15 -> 58200
A16: 46010 | B16: C | C16: DULCE DE LECHE | D16: JULIA | E16: 2 | F16: 2 POTE X 10KG DULCE DE LECHE LUZ AZUL (25500) | G16: =25500*2 -> 51000 | K16: =G16 -> 51000 | L16: 0
A17: 46010 | B17: C | C17: PEDIDO YA | D17: PEDIDO YA | E17: 1 | F17: GASTOS DE COMICION 1-12 AL 7-12 | G17: =31961.12+6711.84 -> 38672.96 | K17: 0 | M17: =G17 -> 38672.96
A18: 45941 | B18: C | C18: IMPUESTO | D18: ARCA | E18: 1 | F18: MONOTRIBUTO MES OCTUBRE | G18: 44580.74 | L18: =G18 -> 44580.74
A19: 46011 | B19: C | C19: GARRAPIÑADA | D19: CHICA | E19: 2 | F19: 2KG DE GARRAPIÑADA ($9.000 X KG) | G19: =9000*2 -> 18000 | K19: =G19 -> 18000
A20: 46012 | B20: C | C20: PLAGAS | D20: LUGONES | F20: CONTROL DE PLGAS MES OCTUBRE | G20: 16000 | K20: =G20 -> 16000
A21: 45992 | B21: C | C21: CUBANITO COMUN | D21: MAXI | E21: 200 | F21: 1 CAJA X 400 CUBANITOS COMUNES ($168,50 X UNIDAD) | G21: =168.5*E21 -> 33700
A22: 45992 | B22: C | C22: CUBANITO BAÑADO | D22: MAXI | E22: 100 | F22: 1 CAJA X 100 CUBANITOS BAÑADOS ($490,00 X UNIDAD) | G22: 24500 | K22: =G21+G22 -> 58200
A23: 46017 | B23: C | C23: PEDIDO YA | D23: PEDIDO YA | E23: 1 | F23: GASTOS DE COMICION 8-12 AL 14-12 | G23: =62064.57+12576.59+58700-2176.06 -> 131165.1 | K23: 0 | M23: =G23 -> 131165.1
A24: 45945 | B24: C | C24: EXTRACCION | D24: ERICA | F24: EXTRACCION MES DICIEMBRE EFECTIVO | G24: 450000 | K24: 183000 | M24: =G24-K24 -> 267000
A25: 45945 | B25: C | C25: EXTRACCION | D25: MATIAS | F25: EXTRACCION MES DICIEMBRE EFECTIVO Y BANCARIZADA X TRANFERENCIAS | G25: 450000 | K25: 100000 | L25: 290000 | M25: =G25-K25-L25 -> 60000
K26: =G26 -> 0
G28: =G4+G5+G6+G7+G8+G9+G10+G11+G12+G13+G14+G15+G16+G17+G18+G19+G20+G21+G22+G23 -> 867783.75
A79: 45930 | B79: C | C79: PEDIDO YA | D79: PEDIDO YA | E79: 1 | F79: GASTOS DE COMICION 15-9 AL 21-9 | G79: =20677+4894.54+7415.75 -> 32987.29 | K79: 0 | M79: =G79 -> 32987.29
A80: 45940 | B80: C | C80: CUBANITO COMUN | D80: MAXI | E80: 600 | F80: 1 CAJA X 600 CUBANITOS COMUNES ($156,00 X UNIDAD) | G80: =62400+31200 -> 93600 | K80: =G80 -> 93600
A81: 45943 | B81: C | C81: DULCE DE LECHE | D81: JULIA | E81: 4 | F81: 4 POTE X 10KG DULCE DE LECHE PIGUENSE | G81: =25000*4 -> 100000 | K81: =SUM(G81) -> 100000
A82: 45943 | B82: C | C82: CONTADOR | D82: JORGE | E82: 1 | F82: PAGO MENSUAL JORGE | G82: 10000 | L82: =G82 -> 10000
A83: 45941 | B83: C | C83: IMPUESTO | D83: ARCA | E83: 1 | F83: MONOTRIBUTO MES OCTUBRE | G83: 11677.6 | L83: =G83 -> 11677.6
A84: 45930 | B84: C | C84: PEDIDO YA | D84: PEDIDO YA | E84: 1 | F84: GASTOS DE COMICION 22-9 AL 28-9 | G84: =1119.23+235.04 -> 1354.27 | K84: 0 | M84: =G84 -> 1354.27
A85: 45945 | B85: C | C85: EXTRACCION | D85: ERICA | F85: EXTRACCION MES SEPTIEMBRE EFECTIVO | G85: 650000 | K85: 400000 | L85: 250000
A86: 45945 | B86: C | C86: EXTRACCION | D86: MATIAS | F86: EXTRACCION MES SEPTIEMBRE BANCARIZADA X TRANFERENCIAS | G86: 650000 | K86: 350000 | L86: 300000
A87: 45947 | B87: C | C87: PEDIDO YA | D87: PEDIDO YA | E87: 1 | F87: GASTOS DE COMICION 29-9 AL 5-10 | G87: =31291.02+4829.1+7585.22+6600 -> 50305.34 | K87: 0 | M87: =G87 -> 50305.34
A88: 45951 | B88: C | C88: PLAGAS | D88: LUGONES | F88: CONTROL DE PLGAS MES OCTUBRE | G88: 16000 | L88: =G88 -> 16000
A89: 45954 | B89: C | C89: PEDIDO YA | D89: PEDIDO YA | E89: 1 | F89: GASTOS DE COMICION 6-10 AL 12-10 | G89: =54138.37+33500+17314.66+26000-5187.61 -> 125765.42 | K89: 0 | M89: =G89 -> 125765.42
A90: 45958 | B90: C | C90: CUBANITO COMUN | D90: MAXI | E90: 400 | F90: 1 CAJA X 400 CUBANITOS COMUNES ($156,00 X UNIDAD) | G90: 62400
A91: 45958 | B91: C | C91: CUBANITO BAÑADO | D91: MAXI | E91: 400 | F91: 1 CAJA X 400 CUBANITOS BAÑADOS ($358,00 X UNIDAD) | G91: 143200
A92: 45958 | B92: C | C92: CUBANITO BAÑADO | D92: MAXI | E92: 200 | F92: 1 CAJA X 200 CUBANITOS BAÑADOS ($358,00 X UNIDAD) | G92: 71100 | K92: =G90+G91+G92 -> 276700
A93: 46004 | B93: C | C93: GARRAPIÑADA | D93: CHICA | E93: 5 | F93: 35KG DE GARRAPIÑADA ($10.000 X KG) | G93: =10000*5 -> 50000 | K93: 0 | L93: =G93 -> 50000
M95: =203823-G89+5187.61 -> 83245.19
B126: C
B127: C
B128: C
B129: C
B130: C
B131: C
B132: C
B133: C
B134: C
B135: C
B136: C
B137: C
... B156: C
A161: 45854 | B161: M | C161: CUBANITO COMUN
A162: 45906 | B162: C | C162: DULCE DE LECHE | D162: LUZ AZUL | E162: 1 | F162: 1 POTE X 10KG DULCE DE LECHE LUZ AZUL | G162: 41000 | K162: 41000
A163: 45907 | B163: C | C163: CUBANITO COMUN | D163: MAXI | E163: 400 | F163: 1 CAJA X 400 CUBANITOS COMUNES ($156,00 X UNIDAD) | G163: 62400
A164: 45907 | B164: C | C164: CUBANITO BAÑADO | D164: MAXI | E164: 400 | F164: 1 CAJA X 400 CUBANITOS BAÑADOS ($358,00 X UNIDAD) | G164: 143200
A165: 45907 | B165: C | C165: DULCE DE LECHE | D165: MAXI | E165: 2 | F165: 1 POTE X 10KG DULCE DE LECHE PIGUENSE | G165: 51000 | K165: =SUM(G163:G165) -> 256600
A166: 45910 | B166: C | C166: VESTIMENTA | D166: ARRUMACO | E166: 1 | F166: 2 DELANTALES + 2 COFIA | G166: =12000+10000 -> 22000 | K166: =G166 -> 22000
A167: 45911 | B167: C | C167: IMPUESTO | D167: MUNICIPALIDAD | E167: 1 | F167: TASA SEGURIDAD E HIGIENE SEPTIEMBRE 2025 | G167: 14384 | L167: =G167 -> 14384
A168: 45911 | B168: C | C168: IMPUESTO | D168: ARCA | E168: 1 | F168: MONOTRIBUTO MES SEPTIEMBRE | G168: 11677.6 | L168: =G168 -> 11677.6
A169: 45912 | B169: C | C169: DULCE DE LECHE | D169: JULIA | E169: 2 | F169: 1 POTE X 10KG DULCE DE LECHE PIGUENSE | G169: 51000 | K169: =SUM(G169) -> 51000
A170: 45907 | B170: C | C170: CUBANITO COMUN | D170: MAXI | E170: 400 | F170: 1 CAJA X 400 CUBANITOS COMUNES ($156,00 X UNIDAD) | G170: 62400
A171: 45907 | B171: C | C171: CUBANITO BAÑADO | D171: MAXI | E171: 400 | F171: 1 CAJA X 400 CUBANITOS BAÑADOS ($358,00 X UNIDAD) | G171: 143200
A172: 45907 | B172: C | C172: CUBANITO BAÑADO | D172: MAXI | E172: 400 | F172: 1 CAJA X 400 CUBANITOS BAÑADOS BLANCOS ($358,00 X UNIDAD) | G172: 143200 | K172: =G170+G171+G172 -> 348800
A173: 45913 | B173: C | C173: GARRAPIÑADA | D173: CHICA | E173: 5 | F173: 35KG DE GARRAPIÑADA ($10.000 X KG) | G173: =10000*5 -> 50000 | K173: 0 | L173: =G173 -> 50000
A174: 45915 | B174: C | C174: REPUESTOS | D174: NITRAM | E174: 1 | F174: REPUESTOS PARA HACER PUNTERA DE CUBANERA | G174: 12750 | K174: 0 | L174: =G174 -> 12750
A175: 45916 | B175: C | C175: DULCE DE LECHE | D175: LUZ AZUL | E175: 2 | F175: 2 POTE X 10KG DULCE DE LECHE LUZ AZUL (42261.50) | G175: 84523 | K175: =G175 -> 84523
A176: 45916 | B176: C | C176: DULCE DE LECHE | D176: LUZ AZUL | E176: 4 | F176: 4 POTE X 10KG DULCE DE LECHE LUZ AZUL (42261.50) | G176: 169046 | L176: =G176 -> 169046
A177: 45916 | B177: C | C177: DULCE DE LECHE | D177: JULIA | E177: 6 | F177: 6 POTE X 10KG DULCE DE LECHE PIGUENSE ($25.000) | G177: =25000*6 -> 150000 | K177: =SUM(G177) -> 150000
A178: 45916 | B178: C | C178: REPUESTOS | D178: ALFA RODAMIENTO | E178: 1 | F178: REPUESTOS ORRIN PARA CUBANERA | G178: 1500 | K178: =G178 -> 1500
A179: 45917 | B179: C | C179: BOLSAS | D179: PAPELERA SAN LUIS | E179: 600 | F179: 500 BOLSAS N3L+ 100 BOLSAS N4 | G179: 13800 | L179: 13800
A180: 45918 | B180: C | C180: CONTADOR | D180: JORGE | E180: 1 | F180: PAGO MENSUAL JORGE | G180: 10000 | L180: =G180 -> 10000
A181: 45918 | B181: C | C181: GARRAPIÑADA | D181: GLORIA | E181: 10 | F181: 10 KG DE GARRAPIÑADA ($8.000 X KG) | G181: =8000*10 -> 80000 | K181: =G181 -> 80000
A182: 45919 | B182: C | C182: CUBANITO COMUN | D182: MAXI | E182: 600 | F182: 1 CAJA X 400 CUBANITOS COMUNES ($156,00 X UNIDAD) | G182: =62400+31200 -> 93600
A183: 45919 | B183: C | C183: CUBANITO BAÑADO | D183: MAXI | E183: 400 | F183: 1 CAJA X 400 CUBANITOS BAÑADOS ($358,00 X UNIDAD) | G183: 143200 | L183: =G182+G183 -> 236800
A184: 45918 | B184: C | C184: DULCE DE LECHE | D184: LUZ AZUL | E184: 3 | F184: 3 POTE X 10KG DULCE DE LECHE LUZ AZUL (42261.50) | G184: =42261.5*3 -> 126784.5 | K184: =G184 -> 126784.5 | L184: 0
A185: 45919 | B185: C | C185: PEDIDO YA | D185: PEDIDO YA | E185: 1 | F185: GASTOS DE COMICION 1-9 AL 7-9 | G185: =8925.94+415.87+2079.59 -> 11421.4 | K185: 0 | M185: =G185 -> 11421.4
A186: 45922 | B186: C | C186: PLAGAS | D186: LUGONES | F186: CONTROL DE PLGAS MES septiembre | G186: 16000 | L186: =G186 -> 16000
A187: 45922 | B187: C | C187: GARRAFA | D187: GARRAFAS DON BOSCO | F187: CARGA DE GARRAFA | G187: 7000 | K187: 7000
A188: 45924 | B188: C | C188: DULCE DE LECHE | D188: JULIA | E188: 4 | F188: 4 POTE X 10KG DULCE DE LECHE PIGUENSE ($25.000) | G188: =25000*4 -> 100000 | K188: =SUM(G188) -> 100000
A189: 45926 | B189: C | C189: CUBANITO COMUN | D189: MAXI | E189: 1200 | F189: 3 CAJA X 400 CUBANITOS COMUNES ($156,00 X UNIDAD) | G189: =62400*3 -> 187200
A190: 45926 | B190: C | C190: CUBANITO BAÑADO | D190: MAXI | E190: 2000 | F190: 5 CAJA X 400 CUBANITOS BAÑADOS ($358,00 X UNIDAD) | G190: =143200*5 -> 716000 | K190: =G189+G190-25000-62400 -> 815800
A191: 45929 | B191: C | C191: EMPLEADA | D191: EMPLEADA | E191: 2 | F191: MILI TRABAJO EL 27/09+28/09 | G191: =30000*2 -> 60000 | K191: =G191 -> 60000
A192: 45930 | B192: C | C192: PEDIDO YA | D192: PEDIDO YA | E192: 1 | F192: GASTOS DE COMICION 15-9 AL 21-9 | G192: =20677+4894.54+7415.75+15750 -> 48737.29 | K192: 0 | M192: =G192 -> 48737.29
A193: 45930 | B193: C | C193: EXTRACCION | D193: ERICA | F193: EXTRACCION MES SEPTIEMBRE EFECTIVO | G193: 1300000 | K193: 800000 | L193: 500000
A194: 45930 | B194: C | C194: EXTRACCION | D194: MATIAS | F194: EXTRACCION MES SEPTIEMBRE BANCARIZADA X TRANFERENCIAS | G194: 1300000 | K194: 400000 | L194: 900000
A195: 45854 | B195: M | C195: CUBANITO BAÑADO
A196: 45854 | B196: M | C196: DULCE DE LECHE
A197: 45853 | B197: M | C197: GARRAPIÑADA
A198: 45855 | B198: C | C198: CONTADOR
A199: 45855 | B199: C | C199: IMPUESTO
A200: 45856 | B200: C | C200: DULCE DE LECHE
A201: 45859 | B201: C | C201: PLAGAS
A202: 45859 | B202: C | C202: IMPUESTO
A203: 45863 | B203: C | C203: CUBANITO COMUN
A204: 45863 | B204: C | C204: CUBANITO BAÑADO
...

Sheet VENTAS DICIEMBRE
A1: MES:
B2: CUBANITOS | E2: METODO DE PAGO | H2: TOTAL | J2: MES DICIEMBRE
A3: DIA | B3: COMUNES | C3: BAÑADOS | D3: OTRO | E3: EFECTIVO | F3: TRANSFERENCIA | G3: PEDIDOS YA | H3: VENTAS $
A4: 45992 | B4: =2+12+6 -> 20 | C4: =4+3+6 -> 13 | E4: =7200 -> 7200 | F4: =3900+6000 -> 9900 | G4: =27000 -> 27000 | H4: =E4+F4 -> 17100 | J4: Tranferencia | K4: =SUMIF(F4:F31,">0") -> 420300
A5: 45993 | B5: =2+3+2+3 -> 10 | C5: =2+2+2+3 -> 9 | E5: =4600+2600 -> 7200 | F5: =5600+2000 -> 7600 | G5: 9600 | H5: =E5+F5 -> 14800 | J5: efectivo | K5: =SUMIF(E4:E31,">0") -> 629000
A6: 45994 | C6: 2 | E6: 2600 | H6: =E6+F6 -> 2600 | J6: PedidosYA | K6: =SUMIF(G4:G34,">0") -> 616900
A7: 45995 | B7: =6+10 -> 16 | C7: 4 | E7: =11200+10000 -> 21200 | H7: =E7+F7 -> 21200 | J7: TOTAL | K7: =K4+K5+K6 -> 1666200
A8: 45996 | B8: =6+10+4+3+6 -> 29 | C8: =4+10+4+2+3+3+4 -> 30 | E8: =5200+2600+7900 -> 15700 | F8: =6000+23000+5200+5200 -> 39400 | G8: =9600+7800 -> 17400 | H8: =E8+F8 -> 55100
A9: 45997 | B9: =6+1+2+8+12+7+6+5 -> 47 | C9: =6+2+4+5+2+3 -> 22 | D9: =1+1+1 -> 3 | E9: =13800+3600+8000+14200+7200+2600 -> 49400 | F9: =13500+10000 -> 23500 | G9: 10200 | H9: =E9+F9 -> 72900 | J9: CONSUMO CUBANITOS
A10: 45998 | B10: =6+8+4+4+6+2+5+6 -> 41 | C10: =12+10+8+4+6+2+3+6 -> 51 | D10: =1+1 -> 2 | E10: =21000+13800 -> 34800 | F10: =14400+14400+7000 -> 35800 | G10: =30600+14700+12200 -> 57500 | H10: =E10+F10 -> 70600 | J10: COMUNES | K10: BAÑADOS
A11: 45999 | B11: =8+12+2+6 -> 28 | C11: =8+6+2+6 -> 22 | D11: 3 | E11: =18400+12000+7800+3000+7000 -> 48200 | F11: 5800 | G11: =11400+7800 -> 19200 | H11: =E11+F11 -> 54000 | J11: =SUM(B4:B33) -> 684 | K11: =SUM(C4:C33) -> 594
A12: 46000 | B12: =3+2+3 -> 8 | C12: =2+3+2+3+6 -> 16 | E12: =2600+4600 -> 7200 | F12: 7800 | G12: =11400+9600 -> 21000 | H12: =E12+F12 -> 15000
A13: 46001 | B13: =3+4+12 -> 19 | C13: =8+4 -> 12 | E13: =3000+5200 -> 8200 | G13: =20400+15600 -> 36000 | H13: =E13+F13 -> 8200
A14: 46002 | B14: =6+2 -> 8 | C14: 3 | E14: =6000+2000 -> 8000 | F14: =3900 -> 3900 | H14: =E14+F14 -> 11900
A15: 46003 | C15: 6 | E15: 7800 | H15: =E15+F15 -> 7800
A16: 46004 | B16: =1+6+3+6+2+1+4 -> 23 | C16: =6+2+2+3+4+3+4+8 -> 32 | D16: 3 | E16: =10800+3600+6000+2600+6000+7200+3900+6200 -> 46300 | F16: 14400 | G16: 9600 | H16: =E16+F16 -> 60700
A17: 46005 | B17: =6+6+2+6+6+6+8+12+6+6+4+2+3+3+2+3+2+3+4 -> 90 | C17: =12+4+10+6+1+12+6+3+6+6+4+6+4+2+3+3+3+4+3+4+12+2+2 -> 118 | D17: =2+1 -> 3 | E17: =15600+5200+9700+19200+6000+13800+11600+4600+11200+9600+3900+9000+15600+2600 -> 137600 | F17: =7800+13200+12000+6900+2600 -> 42500 | G17: =19000+22800+19200+8300+19200+12800 -> 101300 | H17: =E17+F17 -> 180100
A18: 46006 | B18: =3+1+6+2+5+4 -> 21 | C18: =2+3+2+6 -> 13 | E18: =3000+9900+4600+5000+11800 -> 34300 | F18: 3600 | H18: =E18+F18 -> 37900
A19: 46007 | B19: =12+12+2 -> 26 | C19: =6+2+4+3 -> 15 | D19: 3 | E19: =17600+5200+5900 -> 28700 | F19: =12000+7800 -> 19800 | H19: =E19+F19 -> 48500
A20: 46008 | B20: =2+4+2 -> 8 | C20: =2+4+4+12+2 -> 24 | E20: 2600 | F20: =4600+9200+15600 -> 29400 | G20: 10200 | H20: =E20+F20 -> 32000
A21: 46009 | B21: =6+2+6+6 -> 20 | C21: =6+2+4+6 -> 18 | E21: =6000+6000 -> 12000 | F21: 7200 | G21: =11400+11600+11400 -> 34400 | H21: =E21+F21 -> 19200
A22: 46010 | B22: =2+3+6+3+2 -> 16 | C22: =16+3+6+3+6+6 -> 40 | E22: =9800+11400 -> 21200 | F22: =6900+13800+6900 -> 27600 | G22: 33000 | H22: =E22+F22 -> 48800
A23: 46011 | B23: =4+12+6 -> 22 | C23: =2+6+6 -> 14 | E23: =6600+11400 -> 18000 | F23: 12000 | G23: =11400+7800 -> 19200 | H23: =E23+F23 -> 30000
A24: 46012 | B24: =12+12+6+6+2+4+6+8 -> 56 | C24: =6+3+10+6+6+4 -> 35 | D24: 2 | E24: 15000 | F24: =12000+12000+6000+6300+4000 -> 40300 | G24: =19200+11400+19200+18000 -> 67800 | H24: =E24+F24 -> 55300
A25: 46013 | B25: =6+6+3+5+5+5+2 -> 32 | C25: =3+6+3 -> 12 | D25: 5 | E25: =7800+5000+4900+5000+5900 -> 28600 | F25: =6000+7800 -> 13800 | G25: 9600 | H25: =E25+F25 -> 42400
A26: 46014 | B26: =6+4+8 -> 18 | C26: =6+2 -> 8 | E26: 6600 | F26: 8000 | G26: 19200 | H26: =E26+F26 -> 14600
A27: 46015 | B27: =6+3+2+4 -> 15 | C27: =6+3+2+8 -> 19 | E27: =6900+4600+14400 -> 25900 | G27: =19200 -> 19200 | H27: =E27+F27 -> 25900
A28: 46016 | H28: =E28+F28 -> 0
A29: 46017 | B29: =12+3 -> 15 | C29: 3 | F29: 6900 | G29: 15600 | H29: =E29+F29 -> 6900
A30: 46018 | B30: =12+3+4+6+6+6+6 -> 43 | C30: =1+4+12 -> 17 | E30: =4300+6000+6000+6000 -> 22300 | F30: =12000+9200 -> 21200 | G30: 30600 | H30: =E30+F30 -> 43500
A31: 46019 | B31: =12+12+2+5+6 -> 37 | C31: =7+6+2+7+6 -> 28 | E31: =7800+4600 -> 12400 | F31: =12000+14100+13800 -> 39900 | G31: 28900 | H31: =E31+F31 -> 52300
A32: 46020 | H32: =E32+F32 -> 0
A33: 46021 | B33: =4+12 -> 16 | C33: 8 | E33: 12000 | G33: 20400 | H33: =E33+F33 -> 12000
A34: 46022 | H34: =E34+F34 -> 0

Sheet GASTOS ENERO
A1: DETALLES GASTOS ENTREGADOS POR CONTRATISTA, FACTURAS "A"
K2: PAGOS
A3: FECHA | B3: ABONO | C3: RUBRO | D3: PROVEEDOR | E3: CANTIDAD | F3: DESCRIPCIÓN | G3: $ c/IVA+Ing.Br | H3: IVA | I3: 1/2IVA | J3: Perc.Ing.Bruto | K3: EFECTIVO | L3: TRANFERENCIA | M3: PEYA WALLET
A4: 46024 | B4: C | C4: PEDIDO YA | D4: PEDIDO YA | E4: 1 | F4: GASTOS DE COMICION 15-12 AL 21-12 | G4: =48459.06+10176.4+22800 -> 81435.46 | K4: 0 | M4: =G4 -> 81435.46
A5: 46031 | B5: C | C5: CONTADOR | D5: JORGE | E5: 1 | F5: PAGO MENSUAL JORGE | G5: 15000 | L5: =G5 -> 15000
A6: 46024 | B6: C | C6: PEDIDO YA | D6: PEDIDO YA | E6: 1 | F6: GASTOS DE COMICION 22-12 AL 28-12 | G6: =33875.68+7114.1+7800 -> 48789.78 | K6: 0 | M6: =G6 -> 48789.78
A7: 46030 | B7: C | C7: DULCE DE LECHE | D7: LUZ AZUL | E7: 2 | F7: 2 POTE X 10KG DULCE DE LECHE LUZ AZUL (25500) | G7: 39760 | L7: 39760
A8: 46031 | B8: C | C8: EXTRACCION | D8: ERICA | F8: EXTRACCION MES ENERO PEYA | G8: 95000 | M8: =G8 -> 95000
A9: 46031 | B9: C | C9: EXTRACCION | D9: MATIAS | F9: EXTRACCION MES ENERO PEYA | G9: 95000 | M9: =G9 -> 95000
A10: 46036 | B10: C | C10: DULCE DE LECHE | D10: JULIA | E10: 2 | F10: 2 POTE X 10KG DULCE DE LECHE JULIA (25500) | G10: 51000 | K10: =G10 -> 51000 | L10: 0
A11: 46038 | B11: C | C11: CUBANITO COMUN | D11: MAXI | E11: 200 | F11: 1 CAJA X 400 CUBANITOS COMUNES ($168,50 X UNIDAD) | G11: =168.5*E11 -> 33700
A12: 46038 | B12: C | C12: CUBANITO BAÑADO | D12: MAXI | E12: 100 | F12: 1 CAJA X 100 CUBANITOS BAÑADOS ($490,00 X UNIDAD) | G12: =490*E12 -> 49000 | L12: =G11+G12 -> 82700
A13: 46038 | B13: C | C13: PEDIDO YA | D13: PEDIDO YA | E13: 1 | F13: GASTOS DE COMICION 29-12 AL 4-01-26 | G13: =23643.71+4465.34+28400-2380.17 -> 54128.88 | K13: 0 | M13: =G13 -> 54128.88
A14: 46039 | B14: C | C14: EXTRACCION | D14: MATIAS | F14: EXTRACCION MES ENERO PEYA | G14: 37750 | M14: =G14 -> 37750
A15: 46040 | B15: C | C15: IMPUESTO | D15: ARCA | E15: 1 | F15: MONOTRIBUTO MES ENERO | G15: 44580.74 | L15: =G15 -> 44580.74
A16: 46042 | B16: C | C16: CUBANITO COMUN | D16: MAXI | E16: 200 | F16: 1 CAJA X 400 CUBANITOS COMUNES ($168,50 X UNIDAD) | G16: =168.5*E16 -> 33700
A17: 46042 | B17: C | C17: CUBANITO BAÑADO | D17: MAXI | E17: 200 | F17: 1 CAJA X 100 CUBANITOS BAÑADOS ($490,00 X UNIDAD) | G17: =490*E17 -> 98000 | L17: =G16+G17 -> 131700
A18: 46046 | B18: C | C18: PEDIDO YA | D18: PEDIDO YA | E18: 1 | F18: GASTOS DE COMICION 5-1 AL 11-01-26 | G18: =37677.19+7912.21+15600 -> 61189.4 | K18: 0 | M18: =G18 -> 61189.4
A19: 46047 | B19: C | C19: EXTRACCION | D19: MATIAS | F19: EXTRACCION MES ENERO PEYA | G19: 85310.6 | M19: =G19 -> 85310.6
A20: 46049 | B20: C | C20: PLAGAS | D20: LUGONES | F20: CONTROL DE PLGAS MES ENERO | G20: 18000 | L20: =G20 -> 18000
A21: 46049 | B21: C | C21: DULCE DE LECHE | D21: JULIA | E21: 2 | F21: 2 POTE X 10KG DULCE DE LECHE JULIA (25500) | G21: 51000 | K21: =G21 -> 51000 | L21: 0
A22: 46051 | B22: C | C22: CUBANITO COMUN | D22: MAXI | E22: 400 | F22: 1 CAJA X 400 CUBANITOS COMUNES ($168,50 X UNIDAD) | G22: =168.5*E22 -> 67400
A23: 46051 | B23: C | C23: CUBANITO BAÑADO | D23: MAXI | E23: 300 | F23: 1 CAJA X 100 CUBANITOS BAÑADOS ($490,00 X UNIDAD) | G23: =490*E23 -> 147000 | K23: =G22+G23 -> 214400
A24: 46051 | B24: C | C24: GARRAPIÑADA | D24: CHICA | E24: 3 | F24: 3KG DE GARRAPIÑADA ($9.000 X KG) | G24: =9000*E24 -> 27000 | L24: =G24 -> 27000
A25: 46052 | B25: C | C25: PEDIDO YA | D25: PEDIDO YA | E25: 1 | F25: GASTOS DE COMICION 12-1 AL 18-01-26 | G25: =15068.25+3164.33 -> 18232.58 | K25: 0 | M25: =G25 -> 18232.58
A26: 46052 | B26: C | C26: EXTRACCION | D26: MATIAS | F26: EXTRACCION MES ENERO PEYA | G26: 39967.42 | M26: =G26 -> 39967.42
A27: 46053 | B27: C | C27: EXTRACCION | D27: MATIAS | F27: EXTRACCION MES ENERO EFECTIVO Y BANCARIZADA X TRANFERENCIAS | G27: =K27+L27 -> 719050 | K27: 481800 | L27: 237250
G30: =G4+G5+G6+G7+G10+G11+G12+G12+G13+G15+G16+G17+G18+G20+G21+G22+G23+G24 -> 969684.26
A61: 45992 | B61: C | C61: CUBANITO BAÑADO | D61: MAXI | E61: 200 | F61: 1 CAJA X 400 CUBANITOS BAÑADOS ($490,00 X UNIDAD) | G61: =490*E61 -> 98000 | K61: =G28+G61 -> 98000
A62: 45992 | B62: C | C62: BOLSAS | D62: PLASTICOS BLANCOS | E62: 400 | F62: 400 BOLSAS GARRAPIÑADAS | G62: 6470 | L62: =G62 -> 6470
A63: 45995 | B63: C | C63: DULCE DE LECHE | D63: LUZ AZUL | E63: 1 | F63: 1 POTE X 10KG DULCE DE LECHE LUZ AZUL (44500) | G63: 44500 | K63: =G63 -> 44500 | L63: 0
A64: 46000 | B64: C | C64: CUBANITO COMUN | D64: MAXI | E64: 200 | F64: 1 CAJA X 400 CUBANITOS COMUNES ($168,50 X UNIDAD) | G64: =168.5*E64 -> 33700 | K64: =G64 -> 33700
A65: 46020 | B65: C | C65: PEDIDO YA | D65: PEDIDO YA | E65: 1 | F65: GASTOS DE COMICION 17-11 AL 23-11 | G65: =21827+2559.04+5121.07 -> 29507.11 | K65: 0 | M65: =G65 -> 29507.11
A66: 46000 | B66: C | C66: DULCE DE LECHE | D66: LUZ AZUL | E66: 1 | F66: 1 POTE X 10KG DULCE DE LECHE LUZ AZUL (44500) | G66: 44200 | K66: =G66 -> 44200 | L66: 0
A67: 46020 | B67: C | C67: PEDIDO YA | D67: PEDIDO YA | E67: 1 | F67: GASTOS DE COMICION 24-11 AL 30-11 | G67: =29688.3+5539.28+22900-9239.74 -> 48887.84 | K67: 0 | M67: =G67 -> 48887.84
A68: 46000 | B68: C | C68: CUBANITO COMUN | D68: MAXI | E68: 200 | F68: 1 CAJA X 200 CUBANITOS BAÑADOS ($490,00 X UNIDAD) | G68: 98000 | K68: =G68 -> 98000
A69: 46004 | B69: C | C69: CONTADOR | D69: JORGE | E69: 1 | F69: PAGO MENSUAL JORGE | G69: 15000 | L69: =G69 -> 15000
A70: 46007 | B70: C | C70: CUBANITO COMUN | D70: MAXI | E70: 200 | F70: 1 CAJA X 400 CUBANITOS COMUNES ($168,50 X UNIDAD) | G70: =168.5*E70 -> 33700
A71: 46007 | B71: C | C71: CUBANITO BAÑADO | D71: MAXI | E71: 100 | F71: 1 CAJA X 100 CUBANITOS BAÑADOS ($490,00 X UNIDAD) | G71: 24500 | K71: =G70+G71 -> 58200
A72: 46010 | B72: C | C72: DULCE DE LECHE | D72: JULIA | E72: 2 | F72: 2 POTE X 10KG DULCE DE LECHE LUZ AZUL (25500) | G72: =25500*2 -> 51000 | K72: =G72 -> 51000 | L72: 0
A73: 46010 | B73: C | C73: PEDIDO YA | D73: PEDIDO YA | E73: 1 | F73: GASTOS DE COMICION 1-12 AL 7-12 | G73: =31961.12+6711.84 -> 38672.96 | K73: 0 | M73: =G73 -> 38672.96
A74: 45941 | B74: C | C74: IMPUESTO | D74: ARCA | E74: 1 | F74: MONOTRIBUTO MES OCTUBRE | G74: 44580.74 | L74: =G74 -> 44580.74
A75: 46011 | B75: C | C75: GARRAPIÑADA | D75: CHICA | E75: 2 | F75: 2KG DE GARRAPIÑADA ($9.000 X KG) | G75: =9000*2 -> 18000 | K75: =G75 -> 18000
A76: 46012 | B76: C | C76: PLAGAS | D76: LUGONES | F76: CONTROL DE PLGAS MES OCTUBRE | G76: 16000 | K76: =G76 -> 16000
A77: 45992 | B77: C | C77: CUBANITO COMUN | D77: MAXI | E77: 200 | F77: 1 CAJA X 400 CUBANITOS COMUNES ($168,50 X UNIDAD) | G77: =168.5*E77 -> 33700
A78: 45992 | B78: C | C78: CUBANITO BAÑADO | D78: MAXI | E78: 100 | F78: 1 CAJA X 100 CUBANITOS BAÑADOS ($490,00 X UNIDAD) | G78: 24500 | K78: =G77+G78 -> 58200
A79: 46017 | B79: C | C79: PEDIDO YA | D79: PEDIDO YA | E79: 1 | F79: GASTOS DE COMICION 8-12 AL 14-12 | G79: =62064.57+12576.59+58700-2176.06 -> 131165.1 | K79: 0 | M79: =G79 -> 131165.1
A80: 45945 | B80: C | C80: EXTRACCION | D80: ERICA | F80: EXTRACCION MES SEPTIEMBRE EFECTIVO | G80: 450000 | K80: 183000 | M80: =G80-K80 -> 267000
A81: 45945 | B81: C | C81: EXTRACCION | D81: MATIAS | F81: EXTRACCION MES SEPTIEMBRE BANCARIZADA X TRANFERENCIAS | G81: 450000 | K81: 100000 | L81: 290000 | M81: =G81-K81-L81 -> 60000
K82: =G82 -> 0
G84: =G28+G61+G62+G63+G64+G65+G66+G67+G68+G69+G70+G71+G72+G73+G74+G75+G76+G77+G78+G79 -> 834083.75
A135: 45930 | B135: C | C135: PEDIDO YA | D135: PEDIDO YA | E135: 1 | F135: GASTOS DE COMICION 15-9 AL 21-9 | G135: =20677+4894.54+7415.75 -> 32987.29 | K135: 0 | M135: =G135 -> 32987.29
A136: 45940 | B136: C | C136: CUBANITO COMUN | D136: MAXI | E136: 600 | F136: 1 CAJA X 600 CUBANITOS COMUNES ($156,00 X UNIDAD) | G136: =62400+31200 -> 93600 | K136: =G136 -> 93600
A137: 45943 | B137: C | C137: DULCE DE LECHE | D137: JULIA | E137: 4 | F137: 4 POTE X 10KG DULCE DE LECHE PIGUENSE | G137: =25000*4 -> 100000 | K137: =SUM(G137) -> 100000
A138: 45943 | B138: C | C138: CONTADOR | D138: JORGE | E138: 1 | F138: PAGO MENSUAL JORGE | G138: 10000 | L138: =G138 -> 10000
A139: 45941 | B139: C | C139: IMPUESTO | D139: ARCA | E139: 1 | F139: MONOTRIBUTO MES OCTUBRE | G139: 11677.6 | L139: =G139 -> 11677.6
A140: 45930 | B140: C | C140: PEDIDO YA | D140: PEDIDO YA | E140: 1 | F140: GASTOS DE COMICION 22-9 AL 28-9 | G140: =1119.23+235.04 -> 1354.27 | K140: 0 | M140: =G140 -> 1354.27
A141: 45945 | B141: C | C141: EXTRACCION | D141: ERICA | F141: EXTRACCION MES SEPTIEMBRE EFECTIVO | G141: 650000 | K141: 400000 | L141: 250000
A142: 45945 | B142: C | C142: EXTRACCION | D142: MATIAS | F142: EXTRACCION MES SEPTIEMBRE BANCARIZADA X TRANFERENCIAS | G142: 650000 | K142: 350000 | L142: 300000
A143: 45947 | B143: C | C143: PEDIDO YA | D143: PEDIDO YA | E143: 1 | F143: GASTOS DE COMICION 29-9 AL 5-10 | G143: =31291.02+4829.1+7585.22+6600 -> 50305.34 | K143: 0 | M143: =G143 -> 50305.34
A144: 45951 | B144: C | C144: PLAGAS | D144: LUGONES | F144: CONTROL DE PLGAS MES OCTUBRE | G144: 16000 | L144: =G144 -> 16000
A145: 45954 | B145: C | C145: PEDIDO YA | D145: PEDIDO YA | E145: 1 | F145: GASTOS DE COMICION 6-10 AL 12-10 | G145: =54138.37+33500+17314.66+26000-5187.61 -> 125765.42 | K145: 0 | M145: =G145 -> 125765.42
A146: 45958 | B146: C | C146: CUBANITO COMUN | D146: MAXI | E146: 400 | F146: 1 CAJA X 400 CUBANITOS COMUNES ($156,00 X UNIDAD) | G146: 62400
A147: 45958 | B147: C | C147: CUBANITO BAÑADO | D147: MAXI | E147: 400 | F147: 1 CAJA X 400 CUBANITOS BAÑADOS ($358,00 X UNIDAD) | G147: 143200
A148: 45958 | B148: C | C148: CUBANITO BAÑADO | D148: MAXI | E148: 200 | F148: 1 CAJA X 200 CUBANITOS BAÑADOS ($358,00 X UNIDAD) | G148: 71100 | K148: =G146+G147+G148 -> 276700
A149: 46004 | B149: C | C149: GARRAPIÑADA | D149: CHICA | E149: 5 | F149: 35KG DE GARRAPIÑADA ($10.000 X KG) | G149: =10000*5 -> 50000 | K149: 0 | L149: =G149 -> 50000
M151: =203823-G145+5187.61 -> 83245.19
B182: C
B183: C
B184: C
B185: C
B186: C
B187: C
B188: C
B189: C
B190: C
B191: C
B192: C
B193: C
... B212: C
A217: 45854 | B217: M | C217: CUBANITO COMUN
A218: 45906 | B218: C | C218: DULCE DE LECHE | D218: LUZ AZUL | E218: 1 | F218: 1 POTE X 10KG DULCE DE LECHE LUZ AZUL | G218: 41000 | K218: 41000
A219: 45907 | B219: C | C219: CUBANITO COMUN | D219: MAXI | E219: 400 | F219: 1 CAJA X 400 CUBANITOS COMUNES ($156,00 X UNIDAD) | G219: 62400
A220: 45907 | B220: C | C220: CUBANITO BAÑADO | D220: MAXI | E220: 400 | F220: 1 CAJA X 400 CUBANITOS BAÑADOS ($358,00 X UNIDAD) | G220: 143200
A221: 45907 | B221: C | C221: DULCE DE LECHE | D221: MAXI | E221: 2 | F221: 1 POTE X 10KG DULCE DE LECHE PIGUENSE | G221: 51000 | K221: =SUM(G219:G221) -> 256600
A222: 45910 | B222: C | C222: VESTIMENTA | D222: ARRUMACO | E222: 1 | F222: 2 DELANTALES + 2 COFIA | G222: =12000+10000 -> 22000 | K222: =G222 -> 22000
A223: 45911 | B223: C | C223: IMPUESTO | D223: MUNICIPALIDAD | E223: 1 | F223: TASA SEGURIDAD E HIGIENE SEPTIEMBRE 2025 | G223: 14384 | L223: =G223 -> 14384
A224: 45911 | B224: C | C224: IMPUESTO | D224: ARCA | E224: 1 | F224: MONOTRIBUTO MES SEPTIEMBRE | G224: 11677.6 | L224: =G224 -> 11677.6
A225: 45912 | B225: C | C225: DULCE DE LECHE | D225: JULIA | E225: 2 | F225: 1 POTE X 10KG DULCE DE LECHE PIGUENSE | G225: 51000 | K225: =SUM(G225) -> 51000
A226: 45907 | B226: C | C226: CUBANITO COMUN | D226: MAXI | E226: 400 | F226: 1 CAJA X 400 CUBANITOS COMUNES ($156,00 X UNIDAD) | G226: 62400
A227: 45907 | B227: C | C227: CUBANITO BAÑADO | D227: MAXI | E227: 400 | F227: 1 CAJA X 400 CUBANITOS BAÑADOS ($358,00 X UNIDAD) | G227: 143200
A228: 45907 | B228: C | C228: CUBANITO BAÑADO | D228: MAXI | E228: 400 | F228: 1 CAJA X 400 CUBANITOS BAÑADOS BLANCOS ($358,00 X UNIDAD) | G228: 143200 | K228: =G226+G227+G228 -> 348800
A229: 45913 | B229: C | C229: GARRAPIÑADA | D229: CHICA | E229: 5 | F229: 35KG DE GARRAPIÑADA ($10.000 X KG) | G229: =10000*5 -> 50000 | K229: 0 | L229: =G229 -> 50000
A230: 45915 | B230: C | C230: REPUESTOS | D230: NITRAM | E230: 1 | F230: REPUESTOS PARA HACER PUNTERA DE CUBANERA | G230: 12750 | K230: 0 | L230: =G230 -> 12750
A231: 45916 | B231: C | C231: DULCE DE LECHE | D231: LUZ AZUL | E231: 2 | F231: 2 POTE X 10KG DULCE DE LECHE LUZ AZUL (42261.50) | G231: 84523 | K231: =G231 -> 84523
A232: 45916 | B232: C | C232: DULCE DE LECHE | D232: LUZ AZUL | E232: 4 | F232: 4 POTE X 10KG DULCE DE LECHE LUZ AZUL (42261.50) | G232: 169046 | L232: =G232 -> 169046
A233: 45916 | B233: C | C233: DULCE DE LECHE | D233: JULIA | E233: 6 | F233: 6 POTE X 10KG DULCE DE LECHE PIGUENSE ($25.000) | G233: =25000*6 -> 150000 | K233: =SUM(G233) -> 150000
A234: 45916 | B234: C | C234: REPUESTOS | D234: ALFA RODAMIENTO | E234: 1 | F234: REPUESTOS ORRIN PARA CUBANERA | G234: 1500 | K234: =G234 -> 1500
A235: 45917 | B235: C | C235: BOLSAS | D235: PAPELERA SAN LUIS | E235: 600 | F235: 500 BOLSAS N3L+ 100 BOLSAS N4 | G235: 13800 | L235: 13800
A236: 45918 | B236: C | C236: CONTADOR | D236: JORGE | E236: 1 | F236: PAGO MENSUAL JORGE | G236: 10000 | L236: =G236 -> 10000
...

Sheet VENTAS ENERO
A1: MES:
B2: CUBANITOS | E2: METODO DE PAGO | H2: TOTAL | J2: MES ENERO
A3: DIA | B3: COMUNES | C3: BAÑADOS | D3: OTRO | E3: EFECTIVO | F3: TRANSFERENCIA | G3: PEDIDOS YA | H3: VENTAS $
A4: 46023 | H4: =E4+F4 -> 0 | J4: Tranferencia | K4: =SUMIF(F4:F31,">0") -> 429400
A5: 46024 | H5: =E5+F5 -> 0 | J5: efectivo | K5: =SUMIF(E4:E31,">0") -> 605100
A6: 46025 | B6: =3+20+4+6+2 -> 35 | C6: =2+3+2+6+4 -> 17 | D6: 3 | E6: =2600+3000+20000+13800 -> 39400 | F6: =6900+6600+7200 -> 20700 | H6: =E6+F6 -> 60100 | J6: PedidosYA | K6: =SUMIF(G4:G34,">0") -> 569300
A7: 46026 | B7: =6+6+4+12+6+24 -> 58 | C7: =4+6+4+4+1+4+10 -> 33 | D7: =3+2 -> 5 | E7: =13800+7600+20800+6000+2400 -> 50600 | F7: =3900+9000+13000 -> 25900 | G7: =7600+7100+31200 -> 45900 | H7: =E7+F7 -> 76500 | J7: TOTAL | K7: =K4+K5+K6 -> 1603800
A8: 46027 | H8: =E8+F8 -> 0
A9: 46028 | B9: 8 | C9: =4+12 -> 16 | F9: 15600 | G9: 18000 | H9: =E9+F9 -> 15600 | J9: CONSUMO CUBANITOS
A10: 46029 | H10: =E10+F10 -> 0 | J10: COMUNES | K10: BAÑADOS
A11: 46030 | B11: =3+8+3+4 -> 18 | C11: =1+3+8 -> 12 | D11: 3 | E11: =8000+3000+14400 -> 25400 | F11: 43000 | G11: 9600 | H11: =E11+F11 -> 68400 | J11: =SUM(B4:B33) -> 745 | K11: =SUM(C4:C33) -> 504
A12: 46031 | B12: =1+8+3+9+6 -> 27 | C12: =2+1+3+3+12 -> 21 | D12: 3 | E12: =3600+6900+21600 -> 32100 | F12: 8000 | G12: =6700+17400 -> 24100 | H12: =E12+F12 -> 40100
A13: 46032 | B13: =1+4+12+24+6 -> 47 | C13: =4+1+6+6 -> 17 | E13: =6200+6000 -> 12200 | F13: =5200+7800 -> 13000 | G13: =27000+31200 -> 58200 | H13: =E13+F13 -> 25200
A14: 46033 | B14: =8+2+3+12+1 -> 26 | C14: =2+9+1 -> 12 | E14: =10600+3000+2300+15600 -> 31500 | G14: 21000 | H14: =E14+F14 -> 31500
A15: 46034 | H15: =E15+F15 -> 0
A16: 46035 | B16: 1 | C16: 3 | E16: 4900 | H16: =E16+F16 -> 4900
A17: 46036 | B17: 2 | C17: =12+2 -> 14 | E17: 15600 | F17: 4600 | H17: =E17+F17 -> 20200
A18: 46037 | B18: =4+6+6+3+6+3+1+4 -> 33 | C18: =8+3+3+3 -> 17 | D18: 1 | E18: =6000+6000+4000+1200 -> 17200 | F18: =14400+9900+6900+4900 -> 36100 | H18: =E18+F18 -> 53300
A19: 46038 | B19: =2+12+6+12+1 -> 33 | C19: =2+6+12+1 -> 21 | F19: =4600+27600+2300 -> 34500 | G19: =15600+19200 -> 34800 | H19: =E19+F19 -> 34500
A20: 46039 | B20: =3+6+6+5+8+2 -> 30 | C20: =6+3+5+4+1 -> 19 | D20: 1 | E20: =6900+6000+11500+13200+3300 -> 40900 | F20: =7800+7200 -> 15000 | H20: =E20+F20 -> 55900
A21: 46040 | B21: =6+6+12+2+6+4+3+18+6+12+6+3+6+4+3+3+2 -> 102 | C21: =4+4+6+6+6+8+3+3+6+3+3+4+4 -> 60 | D21: =1+1+3 -> 5 | E21: =13800+7800+12000+4000+6900+19200+9900+7800+6000+6300+5200+6900+10200 -> 116000 | F21: =5200+5200+13800+2000+10400+6000+8200 -> 50800 | G21: =7800+15600 -> 23400 | H21: =E21+F21 -> 166800
A22: 46041 | H22: =E22+F22 -> 0
A23: 46042 | B23: =3+2+8+12+12+3 -> 40 | C23: =3+10+3 -> 16 | D23: 3 | E23: =15000+6900 -> 21900 | F23: =9900+12000+12000 -> 33900 | G23: 10400 | H23: =E23+F23 -> 55800
A24: 46043 | B24: =3+3+2+4+3 -> 15 | C24: =3+2+3+12+6+1 -> 27 | D24: =2+2+1 -> 5 | E24: =2000+6400+5800 -> 14200 | F24: =2600+6900+15600+9000 -> 34100 | G24: 12800 | H24: =E24+F24 -> 48300
A25: 46044 | B25: =4+6+3+2+2+6 -> 23 | C25: =4+2 -> 6 | D25: 1 | E25: =4000+7200+5800 -> 17000 | F25: 3000 | G25: =7800+7800 -> 15600 | H25: =E25+F25 -> 20000
A26: 46045 | B26: =12+12+2 -> 26 | C26: =8+6+4+10 -> 28 | E26: 10400 | F26: =12000+5200+15000 -> 32200 | G26: 27000 | H26: =E26+F26 -> 42600
A27: 46046 | B27: =12+6+8+6+18 -> 50 | C27: =6+6+6 -> 18 | E27: =3000+15800 -> 18800 | F27: 18000 | G27: =15600+19200+19200 -> 54000 | H27: =E27+F27 -> 36800
A28: 46047 | B28: =6+6+14+6+3+8+3+6+6+5+18 -> 81 | C28: =12+6+12+6+6+3+3+12 -> 60 | D28: 1 | E28: =15600+13800+19200+14000+3000+21600+5000 -> 92200 | F28: =15000+18000 -> 33000 | G28: =22800+9600+10400+13500 -> 56300 | H28: =E28+F28 -> 125200
A29: 46048 | H29: =E29+F29 -> 0
A30: 46049 | B30: =8+6+6 -> 20 | C30: =6+6+12+4+4 -> 32 | E30: =22800+5200 -> 28000 | F30: 8000 | G30: =19200+19200+7600 -> 46000 | H30: =E30+F30 -> 36000
A31: 46050 | B31: =3+6+12 -> 21 | C31: =3+3 -> 6 | E31: =6900+3900+6000 -> 16800 | G31: 15600 | H31: =E31+F31 -> 16800
A32: 46051 | B32: =4+3+6+6 -> 19 | C32: =12+12+4+3+6 -> 37 | E32: =15600+5200+4000+6900+6000 -> 37700 | F32: 15600 | G32: 19200 | H32: =E32+F32 -> 53300
A33: 46052 | B33: =12+12+6 -> 30 | C33: =4+2+6 -> 12 | E33: 13800 | F33: =12000+2600 -> 14600 | G33: =7600+15600 -> 23200 | H33: =E33+F33 -> 28400
A34: 46053 | B34: =3+3+6+9+18+1 -> 40 | C34: =5+3+12+3 -> 23 | E34: =6900+3000+1000 -> 10900 | F34: 21600 | G34: =13400+17400+23400 -> 54200 | H34: =E34+F34 -> 32500

Sheet GASTOS FEBRERO
A1: DETALLES GASTOS ENTREGADOS POR CONTRATISTA, FACTURAS "A"
K2: PAGOS
A3: FECHA | B3: ABONO | C3: RUBRO | D3: PROVEEDOR | E3: CANTIDAD | F3: DESCRIPCIÓN | G3: $ c/IVA+Ing.Br | H3: IVA | I3: 1/2IVA | J3: Perc.Ing.Bruto | K3: EFECTIVO | L3: TRANFERENCIA | M3: PEYA WALLET
A4: 46059 | B4: C | C4: DULCE DE LECHE | D4: JULIA | E4: 2 | F4: 2 POTE X 10KG DULCE DE LECHE LUZ AZUL (25500) | G4: =27000*2 -> 54000 | K4: 30000 | L4: 24000
A5: 46059 | B5: C | C5: PEDIDO YA | D5: PEDIDO YA | E5: 1 | F5: GASTOS DE COMICION 19-1 AL 25-1 | G5: =51645.05+10845.46+25000 -> 87490.51 | K5: 0 | M5: =G5 -> 87490.51
A6: 46060 | B6: C | C6: EXTRACCION | D6: MATIAS | F6: EXTRACCION MES SEPTIEMBRE BANCARIZADA X TRANFERENCIAS | G6: 113609.49 | M6: =G6-K6-L6 -> 113609.49
A7: 46061 | B7: C | C7: CUBANITO COMUN | D7: MAXI | E7: 250 | F7: 1 CAJA X 400 CUBANITOS COMUNES ($168,50 X UNIDAD) | G7: =168.5*E7 -> 42125 | H7: =168.5*F7 -> #VALUE! | I7: =168.5*G7 -> 7098062.5 | J7: =168.5*H7 -> #VALUE!
A8: 46061 | B8: C | C8: CUBANITO BAÑADO | D8: MAXI | E8: 400 | F8: 1 CAJA X 100 CUBANITOS BAÑADOS ($490,00 X UNIDAD) | G8: =490*E8 -> 196000 | L8: =G7+G8-100000 -> 138125 | M8: 100000
A9: 46065 | B9: C | C9: CUBANITO COMUN | D9: MAXI | E9: 300 | F9: 1 CAJA X 400 CUBANITOS COMUNES ($168,50 X UNIDAD) | G9: =168.5*E9 -> 50550 | L9: =G9 -> 50550
A10: 46065 | B10: C | C10: PEDIDO YA | D10: PEDIDO YA | E10: 1 | F10: GASTOS DE COMICION 26-01 AL 1-02 | G10: =53499.76+9501.9+13230.35+22800 -> 99032.01 | K10: 0 | M10: =G10 -> 99032.01
A11: 46066 | B11: C | C11: DULCE DE LECHE | D11: JULIA | E11: 2 | F11: 2 POTE X 10KG DULCE DE LECHE LUZ AZUL (27300) | G11: =27300*2 -> 54600 | L11: =G11 -> 54600
A12: 45701 | B12: C | C12: CONTADOR | D12: JORGE | E12: 1 | F12: PAGO MENSUAL JORGE | G12: 15000 | L12: =G12 -> 15000
A13: 46070 | B13: C | C13: IMPUESTO | D13: ARCA | E13: 1 | F13: MONOTRIBUTO MES OCTUBRE | G13: 50951.74 | L13: =G13 -> 50951.74
A14: 46070 | B14: C | C14: IMPUESTO | D14: MUNICIPALIDAD | E14: 1 | F14: TASA SEGURIDAD E HIGIENE FEBRERO 2026 | G14: 15914 | L14: =G14 -> 15914
A15: 46070 | B15: C | C15: CUBANITO COMUN | D15: MAXI | E15: 200 | F15: 1 CAJA X 400 CUBANITOS COMUNES ($168,50 X UNIDAD) | G15: =168.5*E15 -> 33700 | H15: =168.5*F15 -> #VALUE! | I15: =168.5*G15 -> 5678450 | J15: =168.5*H15 -> #VALUE!
A16: 46070 | B16: C | C16: CUBANITO BAÑADO | D16: MAXI | E16: 250 | F16: 1 CAJA X 100 CUBANITOS BAÑADOS ($490,00 X UNIDAD) | G16: =490*E16 -> 122500 | L16: =G15+G16-100000 -> 56200 | M16: 100000
A17: 46071 | B17: C | C17: EXTRACCION | D17: MATIAS | F17: EXTRACCION MES SEPTIEMBRE BANCARIZADA X TRANFERENCIAS | G17: 367690 | K17: =G17 -> 367690
A18: 46072 | B18: C | C18: PEDIDO YA | D18: PEDIDO YA | E18: 1 | F18: GASTOS DE COMICION 02-02 AL 8-02 | G18: =71219.6+13018.39+37200-9227.28 -> 112210.71 | K18: 0 | M18: =G18 -> 112210.71
A19: 46073 | B19: C | C19: GARRAFA | D19: GARRAFAS DON BOSCO | F19: CARGA DE GARRAFA | G19: 8000 | K19: =G19 -> 8000
A20: 46073 | B20: C | C20: EXTRACCION | D20: MATIAS | F20: EXTRACCION MES SEPTIEMBRE BANCARIZADA X TRANFERENCIAS | G20: 55624.29 | M20: =G20 -> 55624.29
A21: 46074 | B21: C | C21: CUBANITO COMUN | D21: MAXI | E21: 300 | F21: 1 CAJA X 400 CUBANITOS COMUNES ($168,50 X UNIDAD) | G21: =168.5*E21 -> 50550 | H21: =168.5*F21 -> #VALUE! | I21: =168.5*G21 -> 8517675 | J21: =168.5*H21 -> #VALUE! | K21: =G21 -> 50550
A22: 46076 | B22: C | C22: DULCE DE LECHE | D22: JULIA | E22: 2 | F22: 2 POTE X 10KG DULCE DE LECHE LUZ AZUL (27300) | G22: =27300*2 -> 54600 | K22: =G22 -> 54600
A23: 46076 | B23: C | C23: PLAGAS | D23: LUGONES | F23: CONTROL DE PLGAS MES FEBRERO | G23: 18000 | L23: =G23 -> 18000
A24: 46079 | B24: C | C24: PEDIDO YA | D24: PEDIDO YA | E24: 1 | F24: GASTOS DE COMICION 09-02 AL 15-02 | G24: =57308.03+8300+13777.69+47700 -> 127085.72 | K24: 0 | M24: =G24 -> 127085.72
A25: 46080 | B25: C | C25: CUBANITO COMUN | D25: MAXI | E25: 200 | F25: 1 CAJA X 400 CUBANITOS COMUNES ($217 X UNIDAD) | G25: =217*E25 -> 43400 | H25: =168.5*F25 -> #VALUE! | I25: =168.5*G25 -> 7312900 | J25: =168.5*H25 -> #VALUE!
A26: 46080 | B26: C | C26: CUBANITO BAÑADO | D26: MAXI | E26: 200 | F26: 1 CAJA X 100 CUBANITOS BAÑADOS NEGROS ($490,00 X UNIDAD) | G26: =490*E26 -> 98000
A27: 46080 | B27: C | C27: CUBANITO COMUN | D27: MAXI | E27: 100 | F27: 1 CAJA X 100 CUBANITOS BAÑADOS BLANCOS ($490,00 X UNIDAD) | G27: =490.5*E27 -> 49050 | K27: =G25+G26+G27 -> 190450
A28: 46080 | B28: C | C28: EXTRACCION | D28: MATIAS | F28: EXTRACCION MES SEPTIEMBRE BANCARIZADA X TRANFERENCIAS | G28: 98314.28 | M28: =G28 -> 98314.28
G30: =G4+G7+G8+G9+G11+G12+G13+G14+G15+G16+G19+G21+G22+G23+G25+G26+G27 -> 956940.74
A61: 45992 | B61: C | C61: CUBANITO BAÑADO | D61: MAXI | E61: 200 | F61: 1 CAJA X 400 CUBANITOS BAÑADOS ($490,00 X UNIDAD) | G61: =490*E61 -> 98000 | K61: =G14+G61 -> 113914
A62: 45992 | B62: C | C62: BOLSAS | D62: PLASTICOS BLANCOS | E62: 400 | F62: 400 BOLSAS GARRAPIÑADAS | G62: 6470 | L62: =G62 -> 6470
A63: 45995 | B63: C | C63: DULCE DE LECHE | D63: LUZ AZUL | E63: 1 | F63: 1 POTE X 10KG DULCE DE LECHE LUZ AZUL (44500) | G63: 44500 | K63: =G63 -> 44500 | L63: 0
A64: 46000 | B64: C | C64: CUBANITO COMUN | D64: MAXI | E64: 200 | F64: 1 CAJA X 400 CUBANITOS COMUNES ($168,50 X UNIDAD) | G64: =168.5*E64 -> 33700 | K64: =G64 -> 33700
A65: 46020 | B65: C | C65: PEDIDO YA | D65: PEDIDO YA | E65: 1 | F65: GASTOS DE COMICION 17-11 AL 23-11 | G65: =21827+2559.04+5121.07 -> 29507.11 | K65: 0 | M65: =G65 -> 29507.11
A66: 46000 | B66: C | C66: DULCE DE LECHE | D66: LUZ AZUL | E66: 1 | F66: 1 POTE X 10KG DULCE DE LECHE LUZ AZUL (44500) | G66: 44200 | K66: =G66 -> 44200 | L66: 0
A67: 46020 | B67: C | C67: PEDIDO YA | D67: PEDIDO YA | E67: 1 | F67: GASTOS DE COMICION 24-11 AL 30-11 | G67: =29688.3+5539.28+22900-9239.74 -> 48887.84 | K67: 0 | M67: =G67 -> 48887.84
A68: 46000 | B68: C | C68: CUBANITO COMUN | D68: MAXI | E68: 200 | F68: 1 CAJA X 200 CUBANITOS BAÑADOS ($490,00 X UNIDAD) | G68: 98000 | K68: =G68 -> 98000
A69: 46004 | B69: C | C69: CONTADOR | D69: JORGE | E69: 1 | F69: PAGO MENSUAL JORGE | G69: 15000 | L69: =G69 -> 15000
A70: 46007 | B70: C | C70: CUBANITO COMUN | D70: MAXI | E70: 200 | F70: 1 CAJA X 400 CUBANITOS COMUNES ($168,50 X UNIDAD) | G70: =168.5*E70 -> 33700
A71: 46007 | B71: C | C71: CUBANITO BAÑADO | D71: MAXI | E71: 100 | F71: 1 CAJA X 100 CUBANITOS BAÑADOS ($490,00 X UNIDAD) | G71: 24500 | K71: =G70+G71 -> 58200
A72: 46010 | B72: C | C72: DULCE DE LECHE | D72: JULIA | E72: 2 | F72: 2 POTE X 10KG DULCE DE LECHE LUZ AZUL (25500) | G72: =25500*2 -> 51000 | K72: =G72 -> 51000 | L72: 0
A73: 46010 | B73: C | C73: PEDIDO YA | D73: PEDIDO YA | E73: 1 | F73: GASTOS DE COMICION 1-12 AL 7-12 | G73: =31961.12+6711.84 -> 38672.96 | K73: 0 | M73: =G73 -> 38672.96
A74: 45941 | B74: C | C74: IMPUESTO | D74: ARCA | E74: 1 | F74: MONOTRIBUTO MES OCTUBRE | G74: 44580.74 | L74: =G74 -> 44580.74
A75: 46011 | B75: C | C75: GARRAPIÑADA | D75: CHICA | E75: 2 | F75: 2KG DE GARRAPIÑADA ($9.000 X KG) | G75: =9000*2 -> 18000 | K75: =G75 -> 18000
A76: 46012 | B76: C | C76: PLAGAS | D76: LUGONES | F76: CONTROL DE PLGAS MES OCTUBRE | G76: 16000 | K76: =G76 -> 16000
A77: 45992 | B77: C | C77: CUBANITO COMUN | D77: MAXI | E77: 200 | F77: 1 CAJA X 400 CUBANITOS COMUNES ($168,50 X UNIDAD) | G77: =168.5*E77 -> 33700
A78: 45992 | B78: C | C78: CUBANITO BAÑADO | D78: MAXI | E78: 100 | F78: 1 CAJA X 100 CUBANITOS BAÑADOS ($490,00 X UNIDAD) | G78: 24500 | K78: =G77+G78 -> 58200
A79: 46017 | B79: C | C79: PEDIDO YA | D79: PEDIDO YA | E79: 1 | F79: GASTOS DE COMICION 8-12 AL 14-12 | G79: =62064.57+12576.59+58700-2176.06 -> 131165.1 | K79: 0 | M79: =G79 -> 131165.1
A80: 45945 | B80: C | C80: EXTRACCION | D80: ERICA | F80: EXTRACCION MES SEPTIEMBRE EFECTIVO | G80: 450000 | K80: 183000 | M80: =G80-K80 -> 267000
A81: 45945 | B81: C | C81: EXTRACCION | D81: MATIAS | F81: EXTRACCION MES SEPTIEMBRE BANCARIZADA X TRANFERENCIAS | G81: 450000 | K81: 100000 | L81: 290000 | M81: =G81-K81-L81 -> 60000
K82: =G82 -> 0
G84: =G14+G61+G62+G63+G64+G65+G66+G67+G68+G69+G70+G71+G72+G73+G74+G75+G76+G77+G78+G79 -> 849997.75
A135: 45930 | B135: C | C135: PEDIDO YA | D135: PEDIDO YA | E135: 1 | F135: GASTOS DE COMICION 15-9 AL 21-9 | G135: =20677+4894.54+7415.75 -> 32987.29 | K135: 0 | M135: =G135 -> 32987.29
A136: 45940 | B136: C | C136: CUBANITO COMUN | D136: MAXI | E136: 600 | F136: 1 CAJA X 600 CUBANITOS COMUNES ($156,00 X UNIDAD) | G136: =62400+31200 -> 93600 | K136: =G136 -> 93600
A137: 45943 | B137: C | C137: DULCE DE LECHE | D137: JULIA | E137: 4 | F137: 4 POTE X 10KG DULCE DE LECHE PIGUENSE | G137: =25000*4 -> 100000 | K137: =SUM(G137) -> 100000
A138: 45943 | B138: C | C138: CONTADOR | D138: JORGE | E138: 1 | F138: PAGO MENSUAL JORGE | G138: 10000 | L138: =G138 -> 10000
A139: 45941 | B139: C | C139: IMPUESTO | D139: ARCA | E139: 1 | F139: MONOTRIBUTO MES OCTUBRE | G139: 11677.6 | L139: =G139 -> 11677.6
A140: 45930 | B140: C | C140: PEDIDO YA | D140: PEDIDO YA | E140: 1 | F140: GASTOS DE COMICION 22-9 AL 28-9 | G140: =1119.23+235.04 -> 1354.27 | K140: 0 | M140: =G140 -> 1354.27
A141: 45945 | B141: C | C141: EXTRACCION | D141: ERICA | F141: EXTRACCION MES SEPTIEMBRE EFECTIVO | G141: 650000 | K141: 400000 | L141: 250000
A142: 45945 | B142: C | C142: EXTRACCION | D142: MATIAS | F142: EXTRACCION MES SEPTIEMBRE BANCARIZADA X TRANFERENCIAS | G142: 650000 | K142: 350000 | L142: 300000
A143: 45947 | B143: C | C143: PEDIDO YA | D143: PEDIDO YA | E143: 1 | F143: GASTOS DE COMICION 29-9 AL 5-10 | G143: =31291.02+4829.1+7585.22+6600 -> 50305.34 | K143: 0 | M143: =G143 -> 50305.34
A144: 45951 | B144: C | C144: PLAGAS | D144: LUGONES | F144: CONTROL DE PLGAS MES OCTUBRE | G144: 16000 | L144: =G144 -> 16000
A145: 45954 | B145: C | C145: PEDIDO YA | D145: PEDIDO YA | E145: 1 | F145: GASTOS DE COMICION 6-10 AL 12-10 | G145: =54138.37+33500+17314.66+26000-5187.61 -> 125765.42 | K145: 0 | M145: =G145 -> 125765.42
A146: 45958 | B146: C | C146: CUBANITO COMUN | D146: MAXI | E146: 400 | F146: 1 CAJA X 400 CUBANITOS COMUNES ($156,00 X UNIDAD) | G146: 62400
A147: 45958 | B147: C | C147: CUBANITO BAÑADO | D147: MAXI | E147: 400 | F147: 1 CAJA X 400 CUBANITOS BAÑADOS ($358,00 X UNIDAD) | G147: 143200
A148: 45958 | B148: C | C148: CUBANITO BAÑADO | D148: MAXI | E148: 200 | F148: 1 CAJA X 200 CUBANITOS BAÑADOS ($358,00 X UNIDAD) | G148: 71100 | K148: =G146+G147+G148 -> 276700
A149: 46004 | B149: C | C149: GARRAPIÑADA | D149: CHICA | E149: 5 | F149: 35KG DE GARRAPIÑADA ($10.000 X KG) | G149: =10000*5 -> 50000 | K149: 0 | L149: =G149 -> 50000
M151: =203823-G145+5187.61 -> 83245.19
B182: C
B183: C
B184: C
B185: C
B186: C
B187: C
B188: C
B189: C
B190: C
B191: C
B192: C
B193: C
... B212: C
A217: 45854 | B217: M | C217: CUBANITO COMUN
A218: 45906 | B218: C | C218: DULCE DE LECHE | D218: LUZ AZUL | E218: 1 | F218: 1 POTE X 10KG DULCE DE LECHE LUZ AZUL | G218: 41000 | K218: 41000
A219: 45907 | B219: C | C219: CUBANITO COMUN | D219: MAXI | E219: 400 | F219: 1 CAJA X 400 CUBANITOS COMUNES ($156,00 X UNIDAD) | G219: 62400
A220: 45907 | B220: C | C220: CUBANITO BAÑADO | D220: MAXI | E220: 400 | F220: 1 CAJA X 400 CUBANITOS BAÑADOS ($358,00 X UNIDAD) | G220: 143200
A221: 45907 | B221: C | C221: DULCE DE LECHE | D221: MAXI | E221: 2 | F221: 1 POTE X 10KG DULCE DE LECHE PIGUENSE | G221: 51000 | K221: =SUM(G219:G221) -> 256600
A222: 45910 | B222: C | C222: VESTIMENTA | D222: ARRUMACO | E222: 1 | F222: 2 DELANTALES + 2 COFIA | G222: =12000+10000 -> 22000 | K222: =G222 -> 22000
A223: 45911 | B223: C | C223: IMPUESTO | D223: MUNICIPALIDAD | E223: 1 | F223: TASA SEGURIDAD E HIGIENE SEPTIEMBRE 2025 | G223: 14384 | L223: =G223 -> 14384
A224: 45911 | B224: C | C224: IMPUESTO | D224: ARCA | E224: 1 | F224: MONOTRIBUTO MES SEPTIEMBRE | G224: 11677.6 | L224: =G224 -> 11677.6
A225: 45912 | B225: C | C225: DULCE DE LECHE | D225: JULIA | E225: 2 | F225: 1 POTE X 10KG DULCE DE LECHE PIGUENSE | G225: 51000 | K225: =SUM(G225) -> 51000
A226: 45907 | B226: C | C226: CUBANITO COMUN | D226: MAXI | E226: 400 | F226: 1 CAJA X 400 CUBANITOS COMUNES ($156,00 X UNIDAD) | G226: 62400
A227: 45907 | B227: C | C227: CUBANITO BAÑADO | D227: MAXI | E227: 400 | F227: 1 CAJA X 400 CUBANITOS BAÑADOS ($358,00 X UNIDAD) | G227: 143200
A228: 45907 | B228: C | C228: CUBANITO BAÑADO | D228: MAXI | E228: 400 | F228: 1 CAJA X 400 CUBANITOS BAÑADOS BLANCOS ($358,00 X UNIDAD) | G228: 143200 | K228: =G226+G227+G228 -> 348800
A229: 45913 | B229: C | C229: GARRAPIÑADA | D229: CHICA | E229: 5 | F229: 35KG DE GARRAPIÑADA ($10.000 X KG) | G229: =10000*5 -> 50000 | K229: 0 | L229: =G229 -> 50000
A230: 45915 | B230: C | C230: REPUESTOS | D230: NITRAM | E230: 1 | F230: REPUESTOS PARA HACER PUNTERA DE CUBANERA | G230: 12750 | K230: 0 | L230: =G230 -> 12750
A231: 45916 | B231: C | C231: DULCE DE LECHE | D231: LUZ AZUL | E231: 2 | F231: 2 POTE X 10KG DULCE DE LECHE LUZ AZUL (42261.50) | G231: 84523 | K231: =G231 -> 84523
A232: 45916 | B232: C | C232: DULCE DE LECHE | D232: LUZ AZUL | E232: 4 | F232: 4 POTE X 10KG DULCE DE LECHE LUZ AZUL (42261.50) | G232: 169046 | L232: =G232 -> 169046
A233: 45916 | B233: C | C233: DULCE DE LECHE | D233: JULIA | E233: 6 | F233: 6 POTE X 10KG DULCE DE LECHE PIGUENSE ($25.000) | G233: =25000*6 -> 150000 | K233: =SUM(G233) -> 150000
A234: 45916 | B234: C | C234: REPUESTOS | D234: ALFA RODAMIENTO | E234: 1 | F234: REPUESTOS ORRIN PARA CUBANERA | G234: 1500 | K234: =G234 -> 1500
A235: 45917 | B235: C | C235: BOLSAS | D235: PAPELERA SAN LUIS | E235: 600 | F235: 500 BOLSAS N3L+ 100 BOLSAS N4 | G235: 13800 | L235: 13800
...

Sheet VENTAS FEBRERO
A1: MES:
B2: CUBANITOS | E2: METODO DE PAGO | H2: TOTAL | J2: MES FEBRERO
A3: DIA | B3: COMUNES | C3: BAÑADOS | D3: OTRO | E3: EFECTIVO | F3: TRANSFERENCIA | G3: PEDIDOS YA | H3: VENTAS $
A4: 46054 | B4: =6+6+2+4+6 -> 24 | C4: =6+3+4+4+8 -> 25 | F4: =3900+7200+9200+16200 -> 36500 | G4: =7800+19200 -> 27000 | H4: =E4+F4 -> 36500 | J4: Tranferencia | K4: =SUMIF(F4:F31,">0") -> 743900
A5: 46055 | H5: =E5+F5 -> 0 | J5: efectivo | K5: =SUMIF(E4:E31,">0") -> 854000
A6: 46056 | B6: =6+3+2+12+2+6 -> 31 | C6: =3+4+2+12 -> 21 | D6: 1 | E6: =7800+7200+2600+13200+2000 -> 32800 | F6: 6900 | G6: 30600 | H6: =E6+F6 -> 39700 | J6: PedidosYA | K6: =SUMIF(G4:G34,">0") -> 829450
A7: 46057 | B7: =6+2+3+2+6+4+6+6+6 -> 41 | C7: =6+3+3+9+6+5+6 -> 38 | E7: 6900 | F7: =5900+6000+7800+10500+13800+6000+6000 -> 56000 | G7: =19200+19700 -> 38900 | H7: =E7+F7 -> 62900 | J7: TOTAL | K7: =K4+K5+K6 -> 2427350
A8: 46058 | B8: =4+1+6+12+12+6+3 -> 44 | C8: =8+1+6+5+6+3 -> 29 | D8: 1 | E8: =2300+6000+12000+13800 -> 34100 | F8: =14400+7700+7800+6900 -> 36800 | G8: 15600 | H8: =E8+F8 -> 70900
A9: 46059 | B9: 4 | C9: =6+2 -> 8 | F9: 6600 | G9: 11400 | H9: =E9+F9 -> 6600 | J9: CONSUMO CUBANITOS
A10: 46060 | B10: =5+5+12+3+3+3 -> 31 | C10: =6+6+3+1+1 -> 17 | E10: =4300+4300 -> 8600 | F10: =13800+6900 -> 20700 | G10: =19200+15600 -> 34800 | H10: =E10+F10 -> 29300 | J10: COMUNES | K10: BAÑADOS
A11: 46061 | B11: =18+2+6+4+2+12+6+1+8+6+12+4+12+6+12+6+3 -> 120 | C11: =6+4+6+8+3+6+6+2+12+12+2 -> 67 | D11: =1+1 -> 2 | E11: =2000+4000+10200+19200+13800+6000+6800 -> 62000 | F11: =18000+12000+11900+6600+27600 -> 76100 | G11: =19200+14850+11400+15600+32200+15600 -> 108850 | H11: =E11+F11 -> 138100 | J11: =SUM(B4:B33) -> 1062 | K11: =SUM(C4:C33) -> 772
A12: 46062 | B12: =3+4+6+12+4+4 -> 33 | C12: =3+6+8+7 -> 24 | D12: 1 | E12: =8100+4000+4000 -> 16100 | F12: 14400 | G12: =7800+27000+13300 -> 48100 | H12: =E12+F12 -> 30500
A13: 46063 | B13: =6+3+4+2+2 -> 17 | C13: =6+8+2+2 -> 18 | D13: 3 | E13: =13800+3000+4600+4600 -> 26000 | F13: 17400 | H13: =E13+F13 -> 43400
A14: 46064 | B14: =4+4+3+6+6 -> 23 | C14: =6+6+6+2+2+5 -> 27 | D14: =2+2 -> 4 | E14: =6400+15300+2400+2600 -> 26700 | F14: =4000+13800+2600+6500 -> 26900 | G14: 19200 | H14: =E14+F14 -> 53600
A15: 46065 | B15: =6+6+10+1+2+6+3+12 -> 46 | C15: =4+2+3 -> 9 | E15: =6000+10000+6000+9600 -> 31600 | F15: =6200+4600 -> 10800 | G15: =7800+15600 -> 23400 | H15: =E15+F15 -> 42400
A16: 46066 | B16: =2+2+3+2+7+6+2+2+3+6 -> 35 | C16: =10+6+24+3+4+6+4+2+3+6+6 -> 74 | D16: =3+1 -> 4 | E16: =13000+11400+4600+13800+4600+11400 -> 58800 | F16: =7200+10000+8400+6900+13800 -> 46300 | G16: =10200+9600 -> 19800 | H16: =E16+F16 -> 105100
A17: 46067 | B17: =6+4+6+4+6+6+6+3+3+6+1+6 -> 57 | C17: =6+4+6+5+1+6 -> 28 | E17: =9600+4000+6000+6000+6000 -> 31600 | F17: =10800+9500+2300+13800 -> 36400 | G17: =19200+7800+7800 -> 34800 | H17: =E17+F17 -> 68000
A18: 46068 | B18: =6+3+5+6+3+6+1+4+6 -> 40 | C18: =3+4+2+6+3+6+6+2+2 -> 34 | D18: =1+1+3 -> 5 | E18: =10000+7800+6600+6000 -> 30400 | F18: =7200+7800+16800+3600 -> 35400 | G18: =9600+11600+11200 -> 32400 | H18: =E18+F18 -> 65800
A19: 46069 | B19: =24+15+6+12+9+3+10+6+12+6 -> 103 | C19: =3+6+6+6+6+6+6 -> 39 | E19: =3900+7800+7800 -> 19500 | F19: =24000+7800+10000 -> 41800 | G19: =25200+19200+15600+11400+11700+19200+15600+7800 -> 125700 | H19: =E19+F19 -> 61300
A20: 46070 | B20: =3+4+3+1 -> 11 | C20: =6+4+1+6+5 -> 22 | E20: =3000+2300+7800 -> 13100 | F20: =10800+9200+6500 -> 26500 | H20: =E20+F20 -> 39600
A21: 46071 | B21: =12+6+2 -> 20 | C21: =3+6+7 -> 16 | E21: =12000+13800 -> 25800 | F21: =3900+11100 -> 15000 | H21: =E21+F21 -> 40800
A22: 46072 | B22: =2+8 -> 10 | C22: 4 | D22: 3 | E22: =3000+2200+6000 -> 11200 | G22: 10600 | H22: =E22+F22 -> 11200
A23: 46073 | B23: =6+6+12+10 -> 34 | C23: =6+6+2 -> 14 | D23: 3 | E23: =13200+14000 -> 27200 | F23: 18600 | G23: 19200 | H23: =E23+F23 -> 45800
A24: 46074 | B24: =6+6+12+6+6+4+6+6+1 -> 53 | C24: =2+4+6+4+6+3+4 -> 29 | D24: 1 | E24: =6600+6000+13200+6000+9000+4100+6000 -> 50900 | F24: =1500+5600+6600 -> 13700 | G24: =11600+7800+19200+7800 -> 46400 | H24: =E24+F24 -> 64600
A25: 46075 | B25: =12+2+6+6+6+4+6+3+4+6+3+3 -> 61 | C25: =4+4+6+8+10+12+3+1+3+3+10 -> 64 | E25: =13200+8200+16400+15000+6600+7800+1500+4400+6600+7800 -> 87500 | F25: =6000+6600+18000+15000+7800 -> 53400 | G25: =21000+8400 -> 29400 | H25: =E25+F25 -> 140900
A26: 46076 | B26: =10+2+3+2+4+8 -> 29 | C26: =4+2+4+12+4+4+4+6 -> 40 | D26: =5+3 -> 8 | E26: =11000+10400+3000 -> 24400 | F26: =8200+5300+13600+18000+14800+6000 -> 65900 | G26: 12600 | H26: =E26+F26 -> 90300
A27: 46077 | B27: =3+8+12+1+12+5+4+1+2 -> 48 | C27: =3+6+1+3+1+4 -> 18 | D27: 3 | E27: =1100+13200+7000+8900+2600+8200 -> 41000 | F27: 10800 | G27: =11200+29400 -> 40600 | H27: =E27+F27 -> 51800
A28: 46078 | B28: =6+4+2 -> 12 | C28: =6+2 -> 8 | D28: 3 | E28: 7400 | F28: 5200 | G28: 21000 | H28: =E28+F28 -> 12600
A29: 46079 | B29: =6+6+6+5+9 -> 32 | C29: =6+6+8+5+9 -> 34 | D29: 2 | E29: =15600+15600+13000 -> 44200 | F29: =12000+25800 -> 37800 | G29: 8400 | H29: =E29+F29 -> 82000
A30: 46080 | B30: =12+6+4+6+2+6 -> 36 | C30: =6+3+6+2+4 -> 21 | E30: =13200+4500+4400+3000 -> 25100 | F30: =6600+8200 -> 14800 | G30: =21000+16800 -> 37800 | H30: =E30+F30 -> 39900
A31: 46081 | B31: =3+2+6+6+12+6+10+1+1+4+6+4+6 -> 67 | C31: =2+1+6+6+6+6+6+3+4+4 -> 44 | D31: 1 | E31: =6300+4100+19800+15600+13200+9000+11000+7100+14000+4400+6600 -> 111100 | F31: =6600+6600 -> 13200 | G31: =12600+12600+7700 -> 32900 | H31: =E31+F31 -> 124300
H32: =E32+F32 -> 0
H33: =E33+F33 -> 0
H34: =E34+F34 -> 0

Sheet GASTOS MARZO
A1: DETALLES GASTOS ENTREGADOS POR CONTRATISTA, FACTURAS "A"
K2: PAGOS
A3: FECHA | B3: ABONO | C3: RUBRO | D3: PROVEEDOR | E3: CANTIDAD | F3: DESCRIPCIÓN | G3: $ c/IVA+Ing.Br | H3: IVA | I3: 1/2IVA | J3: Perc.Ing.Bruto | K3: EFECTIVO | L3: TRANFERENCIA | M3: PEYA WALLET
A4: 46082 | B4: C | C4: EXTRACCION | D4: MATIAS | F4: EXTRACCION MES FEBRERO TRANFERENCIA | G4: 335000 | L4: =G4 -> 335000
A5: 46084 | B5: C | C5: DULCE DE LECHE | D5: JULIA | E5: 2 | F5: 2 POTE X 10KG DULCE DE LECHE PIGUENSE (27300) | G5: =27300*2 -> 54600 | K5: =G5 -> 54600 | L5: 0
A63: 45992 | B63: C | C63: CUBANITO BAÑADO | D63: MAXI | E63: 200 | F63: 1 CAJA X 400 CUBANITOS BAÑADOS ($490,00 X UNIDAD) | G63: =490*E63 -> 98000 | K63: =G16+G63 -> 98000
A64: 45992 | B64: C | C64: BOLSAS | D64: PLASTICOS BLANCOS | E64: 400 | F64: 400 BOLSAS GARRAPIÑADAS | G64: 6470 | L64: =G64 -> 6470
A65: 45995 | B65: C | C65: DULCE DE LECHE | D65: LUZ AZUL | E65: 1 | F65: 1 POTE X 10KG DULCE DE LECHE LUZ AZUL (44500) | G65: 44500 | K65: =G65 -> 44500 | L65: 0
A66: 46000 | B66: C | C66: CUBANITO COMUN | D66: MAXI | E66: 200 | F66: 1 CAJA X 400 CUBANITOS COMUNES ($168,50 X UNIDAD) | G66: =168.5*E66 -> 33700 | K66: =G66 -> 33700
A67: 46020 | B67: C | C67: PEDIDO YA | D67: PEDIDO YA | E67: 1 | F67: GASTOS DE COMICION 17-11 AL 23-11 | G67: =21827+2559.04+5121.07 -> 29507.11 | K67: 0 | M67: =G67 -> 29507.11
A68: 46000 | B68: C | C68: DULCE DE LECHE | D68: LUZ AZUL | E68: 1 | F68: 1 POTE X 10KG DULCE DE LECHE LUZ AZUL (44500) | G68: 44200 | K68: =G68 -> 44200 | L68: 0
A69: 46020 | B69: C | C69: PEDIDO YA | D69: PEDIDO YA | E69: 1 | F69: GASTOS DE COMICION 24-11 AL 30-11 | G69: =29688.3+5539.28+22900-9239.74 -> 48887.84 | K69: 0 | M69: =G69 -> 48887.84
A70: 46000 | B70: C | C70: CUBANITO COMUN | D70: MAXI | E70: 200 | F70: 1 CAJA X 200 CUBANITOS BAÑADOS ($490,00 X UNIDAD) | G70: 98000 | K70: =G70 -> 98000
A71: 46004 | B71: C | C71: CONTADOR | D71: JORGE | E71: 1 | F71: PAGO MENSUAL JORGE | G71: 15000 | L71: =G71 -> 15000
A72: 46007 | B72: C | C72: CUBANITO COMUN | D72: MAXI | E72: 200 | F72: 1 CAJA X 400 CUBANITOS COMUNES ($168,50 X UNIDAD) | G72: =168.5*E72 -> 33700
A73: 46007 | B73: C | C73: CUBANITO BAÑADO | D73: MAXI | E73: 100 | F73: 1 CAJA X 100 CUBANITOS BAÑADOS ($490,00 X UNIDAD) | G73: 24500 | K73: =G72+G73 -> 58200
A74: 46010 | B74: C | C74: DULCE DE LECHE | D74: JULIA | E74: 2 | F74: 2 POTE X 10KG DULCE DE LECHE LUZ AZUL (25500) | G74: =25500*2 -> 51000 | K74: =G74 -> 51000 | L74: 0
A75: 46010 | B75: C | C75: PEDIDO YA | D75: PEDIDO YA | E75: 1 | F75: GASTOS DE COMICION 1-12 AL 7-12 | G75: =31961.12+6711.84 -> 38672.96 | K75: 0 | M75: =G75 -> 38672.96
A76: 45941 | B76: C | C76: IMPUESTO | D76: ARCA | E76: 1 | F76: MONOTRIBUTO MES OCTUBRE | G76: 44580.74 | L76: =G76 -> 44580.74
A77: 46011 | B77: C | C77: GARRAPIÑADA | D77: CHICA | E77: 2 | F77: 2KG DE GARRAPIÑADA ($9.000 X KG) | G77: =9000*2 -> 18000 | K77: =G77 -> 18000
A78: 46012 | B78: C | C78: PLAGAS | D78: LUGONES | F78: CONTROL DE PLGAS MES OCTUBRE | G78: 16000 | K78: =G78 -> 16000
A79: 45992 | B79: C | C79: CUBANITO COMUN | D79: MAXI | E79: 200 | F79: 1 CAJA X 400 CUBANITOS COMUNES ($168,50 X UNIDAD) | G79: =168.5*E79 -> 33700
A80: 45992 | B80: C | C80: CUBANITO BAÑADO | D80: MAXI | E80: 100 | F80: 1 CAJA X 100 CUBANITOS BAÑADOS ($490,00 X UNIDAD) | G80: 24500 | K80: =G79+G80 -> 58200
A81: 46017 | B81: C | C81: PEDIDO YA | D81: PEDIDO YA | E81: 1 | F81: GASTOS DE COMICION 8-12 AL 14-12 | G81: =62064.57+12576.59+58700-2176.06 -> 131165.1 | K81: 0 | M81: =G81 -> 131165.1
A82: 45945 | B82: C | C82: EXTRACCION | D82: ERICA | F82: EXTRACCION MES SEPTIEMBRE EFECTIVO | G82: 450000 | K82: 183000 | M82: =G82-K82 -> 267000
A83: 45945 | B83: C | C83: EXTRACCION | D83: MATIAS | F83: EXTRACCION MES SEPTIEMBRE BANCARIZADA X TRANFERENCIAS | G83: 450000 | K83: 100000 | L83: 290000 | M83: =G83-K83-L83 -> 60000
K84: =G84 -> 0
G86: =G16+G63+G64+G65+G66+G67+G68+G69+G70+G71+G72+G73+G74+G75+G76+G77+G78+G79+G80+G81 -> 834083.75
A137: 45930 | B137: C | C137: PEDIDO YA | D137: PEDIDO YA | E137: 1 | F137: GASTOS DE COMICION 15-9 AL 21-9 | G137: =20677+4894.54+7415.75 -> 32987.29 | K137: 0 | M137: =G137 -> 32987.29
A138: 45940 | B138: C | C138: CUBANITO COMUN | D138: MAXI | E138: 600 | F138: 1 CAJA X 600 CUBANITOS COMUNES ($156,00 X UNIDAD) | G138: =62400+31200 -> 93600 | K138: =G138 -> 93600
A139: 45943 | B139: C | C139: DULCE DE LECHE | D139: JULIA | E139: 4 | F139: 4 POTE X 10KG DULCE DE LECHE PIGUENSE | G139: =25000*4 -> 100000 | K139: =SUM(G139) -> 100000
A140: 45943 | B140: C | C140: CONTADOR | D140: JORGE | E140: 1 | F140: PAGO MENSUAL JORGE | G140: 10000 | L140: =G140 -> 10000
A141: 45941 | B141: C | C141: IMPUESTO | D141: ARCA | E141: 1 | F141: MONOTRIBUTO MES OCTUBRE | G141: 11677.6 | L141: =G141 -> 11677.6
A142: 45930 | B142: C | C142: PEDIDO YA | D142: PEDIDO YA | E142: 1 | F142: GASTOS DE COMICION 22-9 AL 28-9 | G142: =1119.23+235.04 -> 1354.27 | K142: 0 | M142: =G142 -> 1354.27
A143: 45945 | B143: C | C143: EXTRACCION | D143: ERICA | F143: EXTRACCION MES SEPTIEMBRE EFECTIVO | G143: 650000 | K143: 400000 | L143: 250000
A144: 45945 | B144: C | C144: EXTRACCION | D144: MATIAS | F144: EXTRACCION MES SEPTIEMBRE BANCARIZADA X TRANFERENCIAS | G144: 650000 | K144: 350000 | L144: 300000
A145: 45947 | B145: C | C145: PEDIDO YA | D145: PEDIDO YA | E145: 1 | F145: GASTOS DE COMICION 29-9 AL 5-10 | G145: =31291.02+4829.1+7585.22+6600 -> 50305.34 | K145: 0 | M145: =G145 -> 50305.34
A146: 45951 | B146: C | C146: PLAGAS | D146: LUGONES | F146: CONTROL DE PLGAS MES OCTUBRE | G146: 16000 | L146: =G146 -> 16000
A147: 45954 | B147: C | C147: PEDIDO YA | D147: PEDIDO YA | E147: 1 | F147: GASTOS DE COMICION 6-10 AL 12-10 | G147: =54138.37+33500+17314.66+26000-5187.61 -> 125765.42 | K147: 0 | M147: =G147 -> 125765.42
A148: 45958 | B148: C | C148: CUBANITO COMUN | D148: MAXI | E148: 400 | F148: 1 CAJA X 400 CUBANITOS COMUNES ($156,00 X UNIDAD) | G148: 62400
A149: 45958 | B149: C | C149: CUBANITO BAÑADO | D149: MAXI | E149: 400 | F149: 1 CAJA X 400 CUBANITOS BAÑADOS ($358,00 X UNIDAD) | G149: 143200
A150: 45958 | B150: C | C150: CUBANITO BAÑADO | D150: MAXI | E150: 200 | F150: 1 CAJA X 200 CUBANITOS BAÑADOS ($358,00 X UNIDAD) | G150: 71100 | K150: =G148+G149+G150 -> 276700
A151: 46004 | B151: C | C151: GARRAPIÑADA | D151: CHICA | E151: 5 | F151: 35KG DE GARRAPIÑADA ($10.000 X KG) | G151: =10000*5 -> 50000 | K151: 0 | L151: =G151 -> 50000
M153: =203823-G147+5187.61 -> 83245.19
B184: C
B185: C
B186: C
B187: C
B188: C
B189: C
B190: C
B191: C
B192: C
B193: C
B194: C
B195: C
... B214: C
A219: 45854 | B219: M | C219: CUBANITO COMUN
A220: 45906 | B220: C | C220: DULCE DE LECHE | D220: LUZ AZUL | E220: 1 | F220: 1 POTE X 10KG DULCE DE LECHE LUZ AZUL | G220: 41000 | K220: 41000
A221: 45907 | B221: C | C221: CUBANITO COMUN | D221: MAXI | E221: 400 | F221: 1 CAJA X 400 CUBANITOS COMUNES ($156,00 X UNIDAD) | G221: 62400
A222: 45907 | B222: C | C222: CUBANITO BAÑADO | D222: MAXI | E222: 400 | F222: 1 CAJA X 400 CUBANITOS BAÑADOS ($358,00 X UNIDAD) | G222: 143200
A223: 45907 | B223: C | C223: DULCE DE LECHE | D223: MAXI | E223: 2 | F223: 1 POTE X 10KG DULCE DE LECHE PIGUENSE | G223: 51000 | K223: =SUM(G221:G223) -> 256600
A224: 45910 | B224: C | C224: VESTIMENTA | D224: ARRUMACO | E224: 1 | F224: 2 DELANTALES + 2 COFIA | G224: =12000+10000 -> 22000 | K224: =G224 -> 22000
A225: 45911 | B225: C | C225: IMPUESTO | D225: MUNICIPALIDAD | E225: 1 | F225: TASA SEGURIDAD E HIGIENE SEPTIEMBRE 2025 | G225: 14384 | L225: =G225 -> 14384
A226: 45911 | B226: C | C226: IMPUESTO | D226: ARCA | E226: 1 | F226: MONOTRIBUTO MES SEPTIEMBRE | G226: 11677.6 | L226: =G226 -> 11677.6
A227: 45912 | B227: C | C227: DULCE DE LECHE | D227: JULIA | E227: 2 | F227: 1 POTE X 10KG DULCE DE LECHE PIGUENSE | G227: 51000 | K227: =SUM(G227) -> 51000
A228: 45907 | B228: C | C228: CUBANITO COMUN | D228: MAXI | E228: 400 | F228: 1 CAJA X 400 CUBANITOS COMUNES ($156,00 X UNIDAD) | G228: 62400
A229: 45907 | B229: C | C229: CUBANITO BAÑADO | D229: MAXI | E229: 400 | F229: 1 CAJA X 400 CUBANITOS BAÑADOS ($358,00 X UNIDAD) | G229: 143200
A230: 45907 | B230: C | C230: CUBANITO BAÑADO | D230: MAXI | E230: 400 | F230: 1 CAJA X 400 CUBANITOS BAÑADOS BLANCOS ($358,00 X UNIDAD) | G230: 143200 | K230: =G228+G229+G230 -> 348800
A231: 45913 | B231: C | C231: GARRAPIÑADA | D231: CHICA | E231: 5 | F231: 35KG DE GARRAPIÑADA ($10.000 X KG) | G231: =10000*5 -> 50000 | K231: 0 | L231: =G231 -> 50000
A232: 45915 | B232: C | C232: REPUESTOS | D232: NITRAM | E232: 1 | F232: REPUESTOS PARA HACER PUNTERA DE CUBANERA | G232: 12750 | K232: 0 | L232: =G232 -> 12750
A233: 45916 | B233: C | C233: DULCE DE LECHE | D233: LUZ AZUL | E233: 2 | F233: 2 POTE X 10KG DULCE DE LECHE LUZ AZUL (42261.50) | G233: 84523 | K233: =G233 -> 84523
A234: 45916 | B234: C | C234: DULCE DE LECHE | D234: LUZ AZUL | E234: 4 | F234: 4 POTE X 10KG DULCE DE LECHE LUZ AZUL (42261.50) | G234: 169046 | L234: =G234 -> 169046
A235: 45916 | B235: C | C235: DULCE DE LECHE | D235: JULIA | E235: 6 | F235: 6 POTE X 10KG DULCE DE LECHE PIGUENSE ($25.000) | G235: =25000*6 -> 150000 | K235: =SUM(G235) -> 150000
A236: 45916 | B236: C | C236: REPUESTOS | D236: ALFA RODAMIENTO | E236: 1 | F236: REPUESTOS ORRIN PARA CUBANERA | G236: 1500 | K236: =G236 -> 1500
A237: 45917 | B237: C | C237: BOLSAS | D237: PAPELERA SAN LUIS | E237: 600 | F237: 500 BOLSAS N3L+ 100 BOLSAS N4 | G237: 13800 | L237: 13800
A238: 45918 | B238: C | C238: CONTADOR | D238: JORGE | E238: 1 | F238: PAGO MENSUAL JORGE | G238: 10000 | L238: =G238 -> 10000
A239: 45918 | B239: C | C239: GARRAPIÑADA | D239: GLORIA | E239: 10 | F239: 10 KG DE GARRAPIÑADA ($8.000 X KG) | G239: =8000*10 -> 80000 | K239: =G239 -> 80000
A240: 45919 | B240: C | C240: CUBANITO COMUN | D240: MAXI | E240: 600 | F240: 1 CAJA X 400 CUBANITOS COMUNES ($156,00 X UNIDAD) | G240: =62400+31200 -> 93600
A241: 45919 | B241: C | C241: CUBANITO BAÑADO | D241: MAXI | E241: 400 | F241: 1 CAJA X 400 CUBANITOS BAÑADOS ($358,00 X UNIDAD) | G241: 143200 | L241: =G240+G241 -> 236800
A242: 45918 | B242: C | C242: DULCE DE LECHE | D242: LUZ AZUL | E242: 3 | F242: 3 POTE X 10KG DULCE DE LECHE LUZ AZUL (42261.50) | G242: =42261.5*3 -> 126784.5 | K242: =G242 -> 126784.5 | L242: 0
A243: 45919 | B243: C | C243: PEDIDO YA | D243: PEDIDO YA | E243: 1 | F243: GASTOS DE COMICION 1-9 AL 7-9 | G243: =8925.94+415.87+2079.59 -> 11421.4 | K243: 0 | M243: =G243 -> 11421.4
A244: 45922 | B244: C | C244: PLAGAS | D244: LUGONES | F244: CONTROL DE PLGAS MES septiembre | G244: 16000 | L244: =G244 -> 16000
A245: 45922 | B245: C | C245: GARRAFA | D245: GARRAFAS DON BOSCO | F245: CARGA DE GARRAFA | G245: 7000 | K245: 7000
A246: 45924 | B246: C | C246: DULCE DE LECHE | D246: JULIA | E246: 4 | F246: 4 POTE X 10KG DULCE DE LECHE PIGUENSE ($25.000) | G246: =25000*4 -> 100000 | K246: =SUM(G246) -> 100000
A247: 45926 | B247: C | C247: CUBANITO COMUN | D247: MAXI | E247: 1200 | F247: 3 CAJA X 400 CUBANITOS COMUNES ($156,00 X UNIDAD) | G247: =62400*3 -> 187200
A248: 45926 | B248: C | C248: CUBANITO BAÑADO | D248: MAXI | E248: 2000 | F248: 5 CAJA X 400 CUBANITOS BAÑADOS ($358,00 X UNIDAD) | G248: =143200*5 -> 716000 | K248: =G247+G248-25000-62400 -> 815800
A249: 45929 | B249: C | C249: EMPLEADA | D249: EMPLEADA | E249: 2 | F249: MILI TRABAJO EL 27/09+28/09 | G249: =30000*2 -> 60000 | K249: =G249 -> 60000
A250: 45930 | B250: C | C250: PEDIDO YA | D250: PEDIDO YA | E250: 1 | F250: GASTOS DE COMICION 15-9 AL 21-9 | G250: =20677+4894.54+7415.75+15750 -> 48737.29 | K250: 0 | M250: =G250 -> 48737.29
A251: 45930 | B251: C | C251: EXTRACCION | D251: ERICA | F251: EXTRACCION MES SEPTIEMBRE EFECTIVO | G251: 1300000 | K251: 800000 | L251: 500000
A252: 45930 | B252: C | C252: EXTRACCION | D252: MATIAS | F252: EXTRACCION MES SEPTIEMBRE BANCARIZADA X TRANFERENCIAS | G252: 1300000 | K252: 400000 | L252: 900000
A253: 45854 | B253: M | C253: CUBANITO BAÑADO
A254: 45854 | B254: M | C254: DULCE DE LECHE
A255: 45853 | B255: M | C255: GARRAPIÑADA
A256: 45855 | B256: C | C256: CONTADOR
A257: 45855 | B257: C | C257: IMPUESTO
A258: 45856 | B258: C | C258: DULCE DE LECHE
A259: 45859 | B259: C | C259: PLAGAS
A260: 45859 | B260: C | C260: IMPUESTO
A261: 45863 | B261: C | C261: CUBANITO COMUN
...

Sheet VENTAS MARZO
A1: MES:
B2: CUBANITOS | E2: METODO DE PAGO | H2: TOTAL | J2: MES FEBRERO
A3: DIA | B3: COMUNES | C3: BAÑADOS | D3: OTRO | E3: EFECTIVO | F3: TRANSFERENCIA | G3: PEDIDOS YA | H3: VENTAS $
A4: 46082 | B4: =6+2+12+8+6+12+6+2+2+8+6+7+4 -> 81 | C4: =8+12+6+6+12+6+2+2+4+10+6+2 -> 76 | D4: 1 | E4: =28000+9000+15000+15600 -> 67600 | F4: =6600+3000+6400+8800+7700+7400 -> 39900 | G4: =25200+16800+11200+12600+42000+21000+11200 -> 140000 | H4: =E4+F4 -> 107500 | J4: Tranferencia | K4: =SUMIF(F4:F31,">0") -> 46500
A5: 46083 | J5: efectivo | K5: =SUMIF(E4:E31,">0") -> 93000
A6: 46084 | B6: =6+4+6 -> 16 | C6: =6+2 -> 8 | D6: 2 | E6: =15600+9800 -> 25400 | F6: 6600 | J6: PedidosYA | K6: =SUMIF(G4:G34,">0") -> 140000
A7: 46085 | J7: TOTAL | K7: =K4+K5+K6 -> 279500
A8: 46086
A9: 46087 | J9: CONSUMO CUBANITOS
A10: 46088 | J10: COMUNES | K10: BAÑADOS
A11: 46089 | J11: =SUM(B4:B33) -> 97 | K11: =SUM(C4:C33) -> 84
A12: 46090
A13: 46091
A14: 46092
A15: 46093
A16: 46094
A17: 46095
A18: 46096
A19: 46097
A20: 46098
A21: 46099
A22: 46100
A23: 46101
... A31: 46109
A32: 46110 | H32: =E32+F32 -> 0
A33: 46111 | H33: =E33+F33 -> 0
A34: 46112 | H34: =E34+F34 -> 0

Sheet CAJA REAL
J1: CAJA REAL
J2: Tranferencia | K2: =SUMIF(C5:C241,"<>0")-SUMIF(F5:F241,"<>0") -> 47060.28
J3: Efectivo | K3: =SUMIF(B7:B240,"<>0")-SUMIF(E7:E240,"<>0") -> 191100
J4: PEYA WALLET | K4: =SUMIF(D7:D241,"<>0")-SUMIF(G7:G241,"<>0")+9960.05+3359.82+1000 -> 8969.82
B5: VENTAS | E5: GASTOS | H5: TOTAL | J5: Cambio | K5: -23000
A6: DIA | B6: EFECTIVO | C6: TRANSFERENCIA | D6: PEYA WALLET | E6: EFECTIVO | F6: TRANSFERENCIA | G6: PEYA WALLET | H6: VENTAS $ | J6: Caja Carro | K6: 0
A7: 45854 | B7: ='VENTAS JULIO'!E4 -> 25300 | C7: ='VENTAS JULIO'!F4 -> 37500 | E7: 0 | F7: 0 | H7: =B7+C7 -> 62800 | K7: -52000
A8: 45855 | B8: ='VENTAS JULIO'!E5 -> 15000 | C8: ='VENTAS JULIO'!F5 -> 17700 | E8: ='GASTOS JULIO'!K19+'GASTOS JULIO'!K20 -> 0 | F8: ='GASTOS JULIO'!L19+'GASTOS JULIO'!L20 -> 33700 | H8: =B8+C8-E8-F8 -> -1000
A9: 45856 | B9: ='VENTAS JULIO'!E6 -> 46000 | C9: ='VENTAS JULIO'!F6 -> 21000 | E9: ='GASTOS JULIO'!K21 -> 25000 | F9: ='GASTOS JULIO'!L21 -> 0 | H9: =B9+C9-E9-F9 -> 42000 | K9: =K3+K5+K6+K7-69500 -> 46600
A10: 45857 | B10: ='VENTAS JULIO'!E7 -> 38200 | C10: ='VENTAS JULIO'!F7 -> 124500 | E10: =0 -> 0 | F10: =0 -> 0 | H10: =B10+C10-E10-F10 -> 162700
A11: 45858 | B11: ='VENTAS JULIO'!E8 -> 106300 | C11: ='VENTAS JULIO'!F8 -> 97000 | E11: =0 -> 0 | F11: =0 -> 0 | H11: =B11+C11-E11-F11 -> 203300
A12: 45859 | B12: ='VENTAS JULIO'!E9 -> 68500 | C12: ='VENTAS JULIO'!F9 -> 8100 | E12: ='GASTOS JULIO'!K22 -> 16000 | F12: ='GASTOS JULIO'!L23 -> 10143.98 | H12: =B12+C12-E12-F12 -> 50456.02 | J12: =K2-J13 -> -51068.22 | K12: =1600000 -> 1600000
A13: 45860 | B13: ='VENTAS JULIO'!E10 -> 92800 | C13: ='VENTAS JULIO'!F10 -> 39100 | E13: ='GASTOS JULIO'!K27 -> 50000 | F13: ='GASTOS JULIO'!L24 -> 0 | H13: =B13+C13-E13-F13 -> 81900 | J13: =98128.5 -> 98128.5 | K13: =K12/2 -> 800000
A14: 45861 | B14: ='VENTAS JULIO'!E11 -> 43600 | C14: ='VENTAS JULIO'!F11 -> 55900 | E14: ='GASTOS JULIO'!K36 -> 0 | F14: ='GASTOS JULIO'!L25 -> 0 | H14: =B14+C14-E14-F14 -> 99500 | J14: =K13-69500 -> 730500
A15: ='VENTAS JULIO'!A12 -> 45862 | B15: ='VENTAS JULIO'!E12 -> 26300 | C15: ='VENTAS JULIO'!F12 -> 19900 | E15: ='GASTOS JULIO'!K28 -> -100000 | F15: ='GASTOS JULIO'!L28 -> 100000 | H15: =B15+C15-E15-F15 -> 46200 | J15: =J14-J12 -> 781568.22 | K15: =K4-J15 -> -772598.4
A16: ='VENTAS JULIO'!A13 -> 45863 | B16: ='VENTAS JULIO'!E13 -> 56700 | C16: ='VENTAS JULIO'!F13 -> 22600 | E16: ='GASTOS JULIO'!K29+'GASTOS JULIO'!K26+'GASTOS JULIO'!K31 -> 319700 | F16: ='GASTOS JULIO'!L29 -> 0 | H16: =B16+C16-E16-F16 -> -240400 | K16: =K13-K15 -> 1572598.4
A17: ='VENTAS JULIO'!A14 -> 45864 | B17: ='VENTAS JULIO'!E14 -> 133900 | C17: ='VENTAS JULIO'!F14 -> 60600 | E17: 0 | F17: ='GASTOS JULIO'!L30 -> 0 | H17: =B17+C17-E17-F17 -> 194500 | J17: =J15+J12+69500 -> 800000
A18: ='VENTAS JULIO'!A15 -> 45865 | B18: ='VENTAS JULIO'!E15 -> 77200 | C18: ='VENTAS JULIO'!F15 -> 81300 | E18: 0 | F18: ='GASTOS JULIO'!L31 -> 0 | H18: =B18+C18-E18-F18 -> 158500
A19: ='VENTAS JULIO'!A16 -> 45866 | B19: ='VENTAS JULIO'!E16 -> 40100 | C19: ='VENTAS JULIO'!F16 -> 17200 | E19: ='GASTOS JULIO'!K33 -> 84900 | F19: ='GASTOS JULIO'!L32 -> 0 | H19: =B19+C19-E19-F19 -> -27600
A20: ='VENTAS JULIO'!A17 -> 45867 | B20: ='VENTAS JULIO'!E17 -> 37600 | C20: ='VENTAS JULIO'!F17 -> 9600 | E20: ='GASTOS JULIO'!K36 -> 0 | F20: ='GASTOS JULIO'!L33 -> 0 | H20: =B20+C20-E20-F20 -> 47200
A21: ='VENTAS JULIO'!A18 -> 45868 | B21: ='VENTAS JULIO'!E18 -> 27300 | C21: ='VENTAS JULIO'!F18 -> 33500 | E21: ='GASTOS JULIO'!K37 -> 0 | F21: ='GASTOS JULIO'!K5+'GASTOS JULIO'!K6+'GASTOS JULIO'!K7+'GASTOS JULIO'!K8+'GASTOS JULIO'!K10+'GASTOS JULIO'!K11+'GASTOS JULIO'!K17+'GASTOS JULIO'!K18 -> 349675.98 | H21: =B21+C21-E21-F21 -> -288875.98
A22: ='VENTAS JULIO'!A19 -> 45869 | B22: ='VENTAS JULIO'!E19 -> 36200 | C22: ='VENTAS JULIO'!F19 -> 72900 | E22: ='GASTOS JULIO'!K34 -> 200000 | F22: ='GASTOS JULIO'!L35 -> 200000 | H22: =B22+C22-E22-F22 -> -290900
A23: ='VENTAS AGOSTO'!A4 -> 45870 | B23: ='VENTAS AGOSTO'!E4 -> 48200 | C23: ='VENTAS AGOSTO'!F4 -> 0 | E23: ='GASTOS AGOSTO'!K4 -> 6000 | F23: 0 | H23: =B23+C23-E23-F23 -> 42200
A24: ='VENTAS AGOSTO'!A5 -> 45871 | B24: ='VENTAS AGOSTO'!E5 -> 78200 | C24: ='VENTAS AGOSTO'!F5 -> 45300 | E24: ='GASTOS AGOSTO'!K5 -> 0 | F24: 0 | H24: =B24+C24-E24-F24 -> 123500
A25: ='VENTAS AGOSTO'!A6 -> 45872 | B25: ='VENTAS AGOSTO'!E6 -> 70300 | C25: ='VENTAS AGOSTO'!F6 -> 133400 | E25: 0 | F25: 0 | H25: =B25+C25-E25-F25 -> 203700
A26: ='VENTAS AGOSTO'!A7 -> 45873 | B26: ='VENTAS AGOSTO'!E7 -> 35800 | C26: ='VENTAS AGOSTO'!F7 -> 11700 | E26: ='GASTOS AGOSTO'!K6+'GASTOS AGOSTO'!K9 -> 215500 | F26: 0 | H26: =B26+C26-E26-F26 -> -168000
A27: ='VENTAS AGOSTO'!A8 -> 45874 | B27: ='VENTAS AGOSTO'!E8 -> 24000 | C27: ='VENTAS AGOSTO'!F8 -> 17800 | E27: ='GASTOS AGOSTO'!K7+'GASTOS AGOSTO'!K10 -> 5000 | F27: 0 | H27: =B27+C27-E27-F27 -> 36800
A28: ='VENTAS AGOSTO'!A9 -> 45875 | B28: ='VENTAS AGOSTO'!E9 -> 45600 | C28: ='VENTAS AGOSTO'!F9 -> 7200 | E28: 0 | F28: 0 | H28: =B28+C28-E28-F28 -> 52800
A29: ='VENTAS AGOSTO'!A10 -> 45876 | B29: ='VENTAS AGOSTO'!E10 -> 0 | C29: ='VENTAS AGOSTO'!F10 -> 19200 | E29: 0 | F29: 0 | H29: =B29+C29-E29-F29 -> 19200
A30: ='VENTAS AGOSTO'!A11 -> 45877 | B30: ='VENTAS AGOSTO'!E11 -> 60900 | C30: ='VENTAS AGOSTO'!F11 -> 27000 | E30: 0 | F30: 0 | H30: =B30+C30-E30-F30 -> 87900
A31: ='VENTAS AGOSTO'!A12 -> 45878 | B31: ='VENTAS AGOSTO'!E12 -> 82100 | C31: ='VENTAS AGOSTO'!F12 -> 68000 | E31: 0 | F31: 0 | H31: =B31+C31-E31-F31 -> 150100
A32: ='VENTAS AGOSTO'!A13 -> 45879 | B32: ='VENTAS AGOSTO'!E13 -> 161500 | C32: ='VENTAS AGOSTO'!F13 -> 146700 | E32: 0 | F32: 0 | H32: =B32+C32-E32-F32 -> 308200
A33: ='VENTAS AGOSTO'!A14 -> 45880 | B33: ='VENTAS AGOSTO'!E14 -> 17600 | C33: ='VENTAS AGOSTO'!F14 -> 6300 | E33: 0 | F33: ='GASTOS AGOSTO'!L11 -> 11677.6 | H33: =B33+C33-E33-F33 -> 12222.4
A34: ='VENTAS AGOSTO'!A15 -> 45881 | B34: ='VENTAS AGOSTO'!E15 -> 16300 | C34: ='VENTAS AGOSTO'!F15 -> 0 | E34: 0 | F34: ='GASTOS AGOSTO'!L36 -> 0 | H34: =B34+C34-E34-F34 -> 16300
A35: ='VENTAS AGOSTO'!A16 -> 45882 | B35: ='VENTAS AGOSTO'!E16 -> 24100 | C35: ='VENTAS AGOSTO'!F16 -> 2400 | E35: 0 | F35: ='GASTOS AGOSTO'!L37 -> 0 | H35: =B35+C35-E35-F35 -> 26500
A36: ='VENTAS AGOSTO'!A17 -> 45883 | B36: ='VENTAS AGOSTO'!E17 -> 27700 | C36: ='VENTAS AGOSTO'!F17 -> 16200 | E36: ='GASTOS AGOSTO'!K15+'GASTOS AGOSTO'!K16+'GASTOS AGOSTO'!K17 -> 387550 | F36: 0 | H36: =B36+C36-E36-F36 -> -343650
A37: ='VENTAS AGOSTO'!A18 -> 45884 | B37: ='VENTAS AGOSTO'!E18 -> 37700 | C37: ='VENTAS AGOSTO'!F18 -> 39900 | E37: ='GASTOS AGOSTO'!K18+'GASTOS AGOSTO'!K19 -> 300000 | F37: ='GASTOS AGOSTO'!L18+'GASTOS AGOSTO'!L19 -> 554000 | H37: =B37+C37-E37-F37 -> -776400
A38: ='VENTAS AGOSTO'!A19 -> 45885 | B38: ='VENTAS AGOSTO'!E19 -> 46000 | C38: ='VENTAS AGOSTO'!F19 -> 43000 | E38: ='GASTOS AGOSTO'!K20 -> 6500 | F38: 0 | H38: =B38+C38-E38-F38 -> 82500
A39: ='VENTAS AGOSTO'!A20 -> 45886 | B39: ='VENTAS AGOSTO'!E20 -> 111300 | C39: ='VENTAS AGOSTO'!F20 -> 79900 | E39: ='GASTOS AGOSTO'!K21 -> 25000 | F39: 0 | H39: =B39+C39-E39-F39 -> 166200
A40: ='VENTAS AGOSTO'!A21 -> 45887 | B40: ='VENTAS AGOSTO'!E21 -> 21300 | C40: ='VENTAS AGOSTO'!F21 -> 13500 | E40: ='GASTOS AGOSTO'!K22 -> 16000 | F40: ='GASTOS AGOSTO'!L23 -> 10000 | H40: =B40+C40-E40-F40 -> 8800
A41: ='VENTAS AGOSTO'!A22 -> 45888 | B41: ='VENTAS AGOSTO'!E22 -> 12000 | C41: ='VENTAS AGOSTO'!F22 -> 10500 | E41: ='GASTOS AGOSTO'!K24 -> 85000 | F41: ='GASTOS AGOSTO'!L24 -> 0 | H41: =B41+C41-E41-F41 -> -62500
A42: ='VENTAS AGOSTO'!A23 -> 45889 | B42: ='VENTAS AGOSTO'!E23 -> 35400 | C42: ='VENTAS AGOSTO'!F23 -> 20800 | E42: ='GASTOS AGOSTO'!K36 -> 0 | F42: ='GASTOS AGOSTO'!L36 -> 0 | H42: =B42+C42-E42-F42 -> 56200
A43: ='VENTAS AGOSTO'!A24 -> 45890 | B43: ='VENTAS AGOSTO'!E24 -> 59500 | C43: ='VENTAS AGOSTO'!F24 -> 0 | E43: ='GASTOS AGOSTO'!G25 -> 35000 | F43: ='GASTOS AGOSTO'!L37 -> 0 | H43: =B43+C43-E43-F43 -> 24500
A44: ='VENTAS AGOSTO'!A25 -> 45891 | B44: ='VENTAS AGOSTO'!E25 -> 31200 | C44: ='VENTAS AGOSTO'!F25 -> 70800 | E44: ='GASTOS AGOSTO'!G36 -> 0 | F44: ='GASTOS AGOSTO'!L38 -> 0 | H44: =B44+C44-E44-F44 -> 102000
A45: ='VENTAS AGOSTO'!A26 -> 45892 | B45: ='VENTAS AGOSTO'!E26 -> 155600 | C45: ='VENTAS AGOSTO'!F26 -> 32800 | E45: ='GASTOS AGOSTO'!G37 -> 0 | F45: ='GASTOS AGOSTO'!L39 -> 0 | H45: =B45+C45-E45-F45 -> 188400
A46: ='VENTAS AGOSTO'!A27 -> 45893 | B46: ='VENTAS AGOSTO'!E27 -> 148500 | C46: ='VENTAS AGOSTO'!F27 -> 60500 | E46: ='GASTOS AGOSTO'!G26 -> 25000 | F46: ='GASTOS AGOSTO'!L40 -> 0 | H46: =B46+C46-E46-F46 -> 184000
A47: ='VENTAS AGOSTO'!A28 -> 45894 | B47: ='VENTAS AGOSTO'!E28 -> 5400 | C47: ='VENTAS AGOSTO'!F28 -> 13800 | E47: ='GASTOS AGOSTO'!G27+'GASTOS AGOSTO'!G28 -> 8200 | F47: ='GASTOS AGOSTO'!L41 -> 0 | H47: =B47+C47-E47-F47 -> 11000
A48: ='VENTAS AGOSTO'!A29 -> 45895 | B48: ='VENTAS AGOSTO'!E29 -> 44300 | C48: ='VENTAS AGOSTO'!F29 -> 21700 | E48: 0 | F48: ='GASTOS AGOSTO'!L42 -> 0 | H48: =B48+C48-E48-F48 -> 66000
A49: ='VENTAS AGOSTO'!A30 -> 45896 | B49: ='VENTAS AGOSTO'!E30 -> 28200 | C49: ='VENTAS AGOSTO'!F30 -> 6900 | E49: ='GASTOS AGOSTO'!G29+'GASTOS AGOSTO'!G30+'GASTOS AGOSTO'!G31+'GASTOS AGOSTO'!G32+'GASTOS AGOSTO'!G33-64 -> 404200 | F49: ='GASTOS AGOSTO'!L43 -> 0 | H49: =B49+C49-E49-F49 -> -369100
A50: ='VENTAS AGOSTO'!A31 -> 45897 | B50: ='VENTAS AGOSTO'!E31 -> 33800 | C50: ='VENTAS AGOSTO'!F31 -> 21600 | E50: 0 | F50: ='GASTOS AGOSTO'!L44 -> 0 | H50: =B50+C50-E50-F50 -> 55400
A51: ='VENTAS AGOSTO'!A32 -> 45898 | B51: ='VENTAS AGOSTO'!E32 -> 33100 | C51: ='VENTAS AGOSTO'!F32 -> 31500 | E51: ='GASTOS AGOSTO'!G34 -> 62400 | F51: ='GASTOS AGOSTO'!L35 -> 12000 | H51: =B51+C51-E51-F51 -> -9800
A52: ='VENTAS AGOSTO'!A33 -> 45899 | B52: ='VENTAS AGOSTO'!E33 -> 50800 | C52: ='VENTAS AGOSTO'!F33 -> 10800 | E52: ='GASTOS AGOSTO'!G36 -> 0 | F52: ='GASTOS AGOSTO'!L46 -> 0 | H52: =B52+C52-E52-F52 -> 61600
A53: ='VENTAS AGOSTO'!A34 -> 45900 | B53: ='VENTAS AGOSTO'!E34 -> 33600 | C53: ='VENTAS AGOSTO'!F34 -> 6000 | E53: ='GASTOS AGOSTO'!G37 -> 0 | F53: ='GASTOS AGOSTO'!L47 -> 0 | H53: =B53+C53-E53-F53 -> 39600
A54: ='VENTAS SEPTIEMBRE'!A4 -> 45901 | B54: ='VENTAS SEPTIEMBRE'!E4 -> 6000 | C54: ='VENTAS SEPTIEMBRE'!F4 -> 16200 | E54: 0 | F54: ='GASTOS AGOSTO'!L48 -> 0 | H54: =B54+C54-E54-F54 -> 22200
A55: ='VENTAS SEPTIEMBRE'!A5 -> 45902 | B55: ='VENTAS SEPTIEMBRE'!E5 -> 20700 | C55: ='VENTAS SEPTIEMBRE'!F5 -> 12600 | E55: ='GASTOS SEPTIEMBRE'!K37 -> 0 | F55: ='GASTOS AGOSTO'!L49 -> 0 | H55: =B55+C55-E55-F55 -> 33300
A56: ='VENTAS SEPTIEMBRE'!A6 -> 45903 | B56: ='VENTAS SEPTIEMBRE'!E6 -> 23200 | C56: ='VENTAS SEPTIEMBRE'!F6 -> 27000 | E56: ='GASTOS SEPTIEMBRE'!K38 -> 0 | F56: ='GASTOS AGOSTO'!L50 -> 0 | H56: =B56+C56-E56-F56 -> 50200
A57: ='VENTAS SEPTIEMBRE'!A7 -> 45904 | B57: ='VENTAS SEPTIEMBRE'!E7 -> 36700 | C57: ='VENTAS SEPTIEMBRE'!F7 -> 0 | E57: ='GASTOS SEPTIEMBRE'!K39 -> 0 | F57: ='GASTOS AGOSTO'!L51 -> 0 | H57: =B57+C57-E57-F57 -> 36700
A58: ='VENTAS SEPTIEMBRE'!A8 -> 45905 | B58: ='VENTAS SEPTIEMBRE'!E8 -> 75000 | C58: ='VENTAS SEPTIEMBRE'!F8 -> 62700 | E58: ='GASTOS SEPTIEMBRE'!K40 -> 0 | F58: ='GASTOS AGOSTO'!L52 -> 0 | H58: =B58+C58-E58-F58 -> 137700
A59: ='VENTAS SEPTIEMBRE'!A9 -> 45906 | B59: ='VENTAS SEPTIEMBRE'!E9 -> 74600 | C59: ='VENTAS SEPTIEMBRE'!F9 -> 49500 | E59: ='GASTOS SEPTIEMBRE'!K4 -> 41000 | F59: ='GASTOS AGOSTO'!L53 -> 0 | H59: =B59+C59-E59-F59 -> 83100
A60: ='VENTAS SEPTIEMBRE'!A10 -> 45907 | B60: ='VENTAS SEPTIEMBRE'!E10 -> 165920 | C60: ='VENTAS SEPTIEMBRE'!F10 -> 107400 | E60: ='GASTOS SEPTIEMBRE'!G5+'GASTOS SEPTIEMBRE'!G6+'GASTOS SEPTIEMBRE'!G7 -> 256600 | F60: ='GASTOS AGOSTO'!L54 -> 0 | H60: =B60+C60-E60-F60 -> 16720
A61: ='VENTAS SEPTIEMBRE'!A11 -> 45908 | B61: ='VENTAS SEPTIEMBRE'!E11 -> 40200 | C61: ='VENTAS SEPTIEMBRE'!F11 -> 22700 | E61: 0 | F61: ='GASTOS AGOSTO'!L55 -> 0 | H61: =B61+C61-E61-F61 -> 62900
A62: ='VENTAS SEPTIEMBRE'!A12 -> 45909 | B62: ='VENTAS SEPTIEMBRE'!E12 -> 25000 | C62: ='VENTAS SEPTIEMBRE'!F12 -> 7200 | E62: 0 | F62: ='GASTOS AGOSTO'!L56 -> 0 | H62: =B62+C62-E62-F62 -> 32200
A63: ='VENTAS SEPTIEMBRE'!A13 -> 45910 | B63: ='VENTAS SEPTIEMBRE'!E13 -> 26800 | C63: ='VENTAS SEPTIEMBRE'!F13 -> 30600 | E63: ='GASTOS SEPTIEMBRE'!K8 -> 22000 | F63: ='GASTOS AGOSTO'!L57 -> 0 | H63: =B63+C63-E63-F63 -> 35400
A64: ='VENTAS SEPTIEMBRE'!A14 -> 45911 | B64: ='VENTAS SEPTIEMBRE'!E14 -> 39100 | C64: ='VENTAS SEPTIEMBRE'!F14 -> 22200 | F64: ='GASTOS SEPTIEMBRE'!L9+'GASTOS SEPTIEMBRE'!L10 -> 26061.6 | H64: =B64+C64-E64-F64 -> 35238.4
A65: ='VENTAS SEPTIEMBRE'!A15 -> 45912 | B65: ='VENTAS SEPTIEMBRE'!E15 -> 40500 | C65: ='VENTAS SEPTIEMBRE'!F15 -> 26100 | E65: ='GASTOS SEPTIEMBRE'!K11 -> 51000 | F65: 0 | H65: =B65+C65-E65-F65 -> 15600
A66: ='VENTAS SEPTIEMBRE'!A16 -> 45913 | B66: ='VENTAS SEPTIEMBRE'!E16-10800 -> 87800 | C66: ='VENTAS SEPTIEMBRE'!F16 -> 57300 | E66: ='GASTOS SEPTIEMBRE'!K14 -> 348800 | F66: ='GASTOS SEPTIEMBRE'!L15 -> 50000 | H66: =B66+C66-E66-F66 -> -253700
A67: ='VENTAS SEPTIEMBRE'!A17 -> 45914 | B67: ='VENTAS SEPTIEMBRE'!E17 -> 208880 | C67: ='VENTAS SEPTIEMBRE'!F17 -> 123400 | E67: ='GASTOS SEPTIEMBRE'!K15 -> 0 | F67: 0 | H67: =B67+C67-E67-F67 -> 332280
A68: ='VENTAS SEPTIEMBRE'!A18 -> 45915 | B68: ='VENTAS SEPTIEMBRE'!E18 -> 25320 | C68: ='VENTAS SEPTIEMBRE'!F18 -> 2400 | E68: 0 | F68: ='GASTOS SEPTIEMBRE'!L16 -> 12750 | H68: =B68+C68-E68-F68 -> 14970
A69: ='VENTAS SEPTIEMBRE'!A19 -> 45916 | B69: ='VENTAS SEPTIEMBRE'!E19 -> 27800 | C69: ='VENTAS SEPTIEMBRE'!F19 -> 21000 | E69: ='GASTOS SEPTIEMBRE'!K17+'GASTOS SEPTIEMBRE'!K19+'GASTOS SEPTIEMBRE'!K20 -> 236023 | F69: ='GASTOS SEPTIEMBRE'!L18 -> 169046 | H69: =B69+C69-E69-F69 -> -356269
A70: ='VENTAS SEPTIEMBRE'!A20 -> 45917 | B70: ='VENTAS SEPTIEMBRE'!E20 -> 30600 | C70: ='VENTAS SEPTIEMBRE'!F20 -> 10500 | F70: ='GASTOS SEPTIEMBRE'!L21 -> 13800 | H70: =B70+C70-E70-F70 -> 27300
A71: ='VENTAS SEPTIEMBRE'!A21 -> 45918 | B71: ='VENTAS SEPTIEMBRE'!E21 -> 20400 | C71: ='VENTAS SEPTIEMBRE'!F21 -> 5100 | E71: ='GASTOS SEPTIEMBRE'!K26+'GASTOS SEPTIEMBRE'!K23 -> 206784.5 | F71: ='GASTOS SEPTIEMBRE'!L22+'GASTOS SEPTIEMBRE'!L25 -> 246800 | H71: =B71+C71-E71-F71 -> -428084.5
A72: ='VENTAS SEPTIEMBRE'!A22 -> 45919 | B72: ='VENTAS SEPTIEMBRE'!E22 -> 64400 | C72: ='VENTAS SEPTIEMBRE'!F22 -> 0 | D72: =51256.3+1746.86 -> 53003.16 | F72: ='GASTOS SEPTIEMBRE'!L23+'GASTOS SEPTIEMBRE'!L37 -> 0 | G72: ='GASTOS SEPTIEMBRE'!M27 -> 11421.4 | H72: =B72+C72-E72-F72 -> 64400
A73: ='VENTAS SEPTIEMBRE'!A23 -> 45920 | B73: ='VENTAS SEPTIEMBRE'!E23 -> 38400 | C73: ='VENTAS SEPTIEMBRE'!F23 -> 10800 | F73: ='GASTOS SEPTIEMBRE'!L24+'GASTOS SEPTIEMBRE'!L38 -> 0 | G73: ='GASTOS SEPTIEMBRE'!M37 -> 0 | H73: =B73+C73-E73-F73 -> 49200
A74: ='VENTAS SEPTIEMBRE'!A24 -> 45921 | B74: ='VENTAS SEPTIEMBRE'!E24 -> 83200 | C74: ='VENTAS SEPTIEMBRE'!F24 -> 39900 | F74: ='GASTOS SEPTIEMBRE'!L25+'GASTOS SEPTIEMBRE'!L39 -> 236800 | G74: ='GASTOS SEPTIEMBRE'!M38 -> 0 | H74: =B74+C74-E74-F74 -> -113700
A75: ='VENTAS SEPTIEMBRE'!A25 -> 45922 | B75: ='VENTAS SEPTIEMBRE'!E25 -> 2700 | C75: ='VENTAS SEPTIEMBRE'!F25 -> 0 | E75: ='GASTOS SEPTIEMBRE'!K29 -> 7000 | F75: ='GASTOS SEPTIEMBRE'!L28 -> 16000 | G75: ='GASTOS SEPTIEMBRE'!M39 -> 0 | H75: =B75+C75-E75-F75 -> -20300
A76: ='VENTAS SEPTIEMBRE'!A26 -> 45923 | B76: ='VENTAS SEPTIEMBRE'!E26 -> 33300 | C76: ='VENTAS SEPTIEMBRE'!F26 -> 18900 | E76: ='GASTOS SEPTIEMBRE'!K37 -> 0 | F76: ='GASTOS SEPTIEMBRE'!L29 -> 0 | G76: ='GASTOS SEPTIEMBRE'!M40 -> 0 | H76: =B76+C76-E76-F76 -> 52200
A77: ='VENTAS SEPTIEMBRE'!A27 -> 45924 | B77: ='VENTAS SEPTIEMBRE'!E27 -> 37800 | C77: ='VENTAS SEPTIEMBRE'!F27 -> 14700 | E77: ='GASTOS SEPTIEMBRE'!K30 -> 100000 | F77: ='GASTOS SEPTIEMBRE'!L37 -> 0 | G77: ='GASTOS SEPTIEMBRE'!M41 -> 0 | H77: =B77+C77-E77-F77 -> -47500
A78: ='VENTAS SEPTIEMBRE'!A28 -> 45925 | B78: ='VENTAS SEPTIEMBRE'!E28 -> 88500 | C78: ='VENTAS SEPTIEMBRE'!F28 -> 24600 | E78: ='GASTOS SEPTIEMBRE'!K37 -> 0 | F78: ='GASTOS SEPTIEMBRE'!L38 -> 0 | G78: ='GASTOS SEPTIEMBRE'!M42 -> 0 | H78: =B78+C78-E78-F78 -> 113100
A79: ='VENTAS SEPTIEMBRE'!A29 -> 45926 | D79: 157770 | G79: ='GASTOS SEPTIEMBRE'!M34 -> 41063.65
A80: ='VENTAS SEPTIEMBRE'!A30 -> 45927 | B80: ='VENTAS SEPTIEMBRE'!E30 -> 691200 | C80: ='VENTAS SEPTIEMBRE'!F30 -> 453900 | E80: ='GASTOS SEPTIEMBRE'!K39 -> 0 | F80: ='GASTOS SEPTIEMBRE'!L40 -> 0 | G80: ='GASTOS SEPTIEMBRE'!M44 -> 0 | H80: =B80+C80-E80-F80 -> 1145100
A81: ='VENTAS SEPTIEMBRE'!A31 -> 45928 | B81: ='VENTAS SEPTIEMBRE'!E31 -> 1110010 | C81: ='VENTAS SEPTIEMBRE'!F31 -> 711400 | E81: ='GASTOS SEPTIEMBRE'!K40 -> 0 | F81: ='GASTOS SEPTIEMBRE'!L41 -> 0 | G81: ='GASTOS SEPTIEMBRE'!M45 -> 0 | H81: =B81+C81-E81-F81 -> 1821410
A82: ='VENTAS SEPTIEMBRE'!A32 -> 45929 | B82: ='VENTAS SEPTIEMBRE'!E32 -> 0 | C82: ='VENTAS SEPTIEMBRE'!F32 -> 0 | E82: ='GASTOS SEPTIEMBRE'!K32+'GASTOS SEPTIEMBRE'!K33 -> 875800 | F82: ='GASTOS SEPTIEMBRE'!L42 -> 0 | G82: 0 | H82: =B82+C82-E82-F82 -> -875800
A83: ='VENTAS SEPTIEMBRE'!A33 -> 45930 | B83: ='VENTAS SEPTIEMBRE'!E33 -> 25700 | C83: ='VENTAS SEPTIEMBRE'!F33 -> 11700 | E83: ='GASTOS SEPTIEMBRE'!K35+'GASTOS SEPTIEMBRE'!K36 -> 1200000 | F83: ='GASTOS SEPTIEMBRE'!L35+'GASTOS SEPTIEMBRE'!L36 -> 1400000 | G83: 0 | H83: =B83+C83-E83-F83 -> -2562600
A84: ='VENTAS OCTUBRE'!A4 -> 45931 | B84: ='VENTAS OCTUBRE'!E4 -> 45600 | C84: ='VENTAS OCTUBRE'!F4 -> 19500 | E84: 0 | F84: 0 | G84: 0 | H84: =B84+C84-E84-F84 -> 65100
A85: ='VENTAS OCTUBRE'!A5 -> 45932 | B85: ='VENTAS OCTUBRE'!E5 -> 5400 | C85: ='VENTAS OCTUBRE'!F5 -> 28200 | E85: 0 | F85: 0 | G85: 0 | H85: =B85+C85-E85-F85 -> 33600
A86: ='VENTAS OCTUBRE'!A6 -> 45933 | B86: ='VENTAS OCTUBRE'!E6 -> 12900 | C86: ='VENTAS OCTUBRE'!F6 -> 0 | D86: 147870 | E86: 0 | F86: 0 | G86: ='GASTOS OCTUBRE'!M4 -> 32987.29 | H86: =B86+C86-E86-F86 -> 12900
A87: ='VENTAS OCTUBRE'!A7 -> 45934 | B87: ='VENTAS OCTUBRE'!E7 -> 34800 | C87: ='VENTAS OCTUBRE'!F7 -> 63000 | E87: 0 | F87: 0 | G87: 0 | H87: =B87+C87-E87-F87 -> 97800
A88: ='VENTAS OCTUBRE'!A8 -> 45935 | B88: ='VENTAS OCTUBRE'!E8 -> 148800 | C88: ='VENTAS OCTUBRE'!F8 -> 132300 | E88: 0 | F88: 0 | G88: 0 | H88: =B88+C88-E88-F88 -> 281100
A89: ='VENTAS OCTUBRE'!A9 -> 45936 | B89: ='VENTAS OCTUBRE'!E9 -> 38100 | C89: ='VENTAS OCTUBRE'!F9 -> 7800 | E89: 0 | F89: 0 | G89: 0 | H89: =B89+C89-E89-F89 -> 45900
A90: ='VENTAS OCTUBRE'!A10 -> 45937 | B90: ='VENTAS OCTUBRE'!E10 -> 85600 | C90: ='VENTAS OCTUBRE'!F10 -> 18000 | E90: 0 | F90: 0 | G90: 0 | H90: =B90+C90-E90-F90 -> 103600
A91: ='VENTAS OCTUBRE'!A11 -> 45938 | B91: ='VENTAS OCTUBRE'!E11 -> 18600 | C91: ='VENTAS OCTUBRE'!F11 -> 0 | E91: 0 | F91: 0 | G91: 0 | H91: =B91+C91-E91-F91 -> 18600
A92: ='VENTAS OCTUBRE'!A12 -> 45939 | B92: ='VENTAS OCTUBRE'!E12 -> 55300 | C92: ='VENTAS OCTUBRE'!F12 -> 19200 | E92: 0 | F92: 0 | G92: 0 | H92: =B92+C92-E92-F92 -> 74500
A93: ='VENTAS OCTUBRE'!A13 -> 45940 | B93: ='VENTAS OCTUBRE'!E13 -> 45000 | C93: ='VENTAS OCTUBRE'!F13 -> 21000 | E93: 0 | F93: 0 | G93: 0 | H93: =B93+C93-E93-F93 -> 66000
A94: ='VENTAS OCTUBRE'!A14 -> 45941 | B94: ='VENTAS OCTUBRE'!E14 -> 54700 | C94: ='VENTAS OCTUBRE'!F14 -> 25500 | E94: 0 | F94: 0 | G94: 0 | H94: =B94+C94-E94-F94 -> 80200
A95: ='VENTAS OCTUBRE'!A15 -> 45942 | B95: ='VENTAS OCTUBRE'!E15+4377.5 -> 171077.5 | C95: ='VENTAS OCTUBRE'!F15 -> 88500 | E95: 0 | F95: 0 | G95: 0 | H95: =B95+C95-E95-F95 -> 259577.5
A96: ='VENTAS OCTUBRE'!A16 -> 45943 | B96: ='VENTAS OCTUBRE'!E16 -> 43500 | C96: ='VENTAS OCTUBRE'!F16 -> 33300 | E96: ='GASTOS OCTUBRE'!K6 -> 100000 | F96: ='GASTOS OCTUBRE'!L7+'GASTOS OCTUBRE'!L8 -> 21677.6 | G96: 0 | H96: =B96+C96-E96-F96 -> -44877.6
A97: ='VENTAS OCTUBRE'!A17 -> 45944 | B97: ='VENTAS OCTUBRE'!E17 -> 32800 | C97: ='VENTAS OCTUBRE'!F17 -> 5400 | D97: 8640 | E97: ='GASTOS OCTUBRE'!K7 -> 0 | F97: =0 -> 0 | G97: ='GASTOS OCTUBRE'!G9 -> 1354.27 | H97: =B97+C97-E97-F97 -> 38200
A98: ='VENTAS OCTUBRE'!A18 -> 45945 | B98: ='VENTAS OCTUBRE'!E18+200 -> 12200 | C98: ='VENTAS OCTUBRE'!F18 -> 18000 | D98: =0 -> 0 | E98: ='GASTOS OCTUBRE'!K10+'GASTOS OCTUBRE'!K11 -> 750000 | F98: ='GASTOS OCTUBRE'!L10+'GASTOS OCTUBRE'!L11 -> 550000 | G98: ='GASTOS OCTUBRE'!G18 -> 0 | H98: =B98+C98-E98-F98 -> -1269800
A99: ='VENTAS OCTUBRE'!A19 -> 45946 | B99: ='VENTAS OCTUBRE'!E19 -> 48500 | C99: ='VENTAS OCTUBRE'!F19 -> 18600 | D99: =0 -> 0 | E99: 0 | F99: 0 | G99: ='GASTOS OCTUBRE'!G19 -> 0 | H99: =B99+C99-E99-F99 -> 67100
A100: ='VENTAS OCTUBRE'!A20 -> 45947 | B100: ='VENTAS OCTUBRE'!E20 -> 40200 | C100: ='VENTAS OCTUBRE'!F20 -> 7200 | D100: 128280 | E100: 0 | F100: 0 | G100: ='GASTOS OCTUBRE'!G12 -> 50305.34 | H100: =B100+C100-E100-F100 -> 47400
...
